{"3501":{"name":"OGenie 3501","traits":{"Background":"Dark Purple","Skin":"Flora","Clothing":"Retro Track Black","Hat":"Blue Bandana","Accessories":"Coffee Mug","Mouth":"Blonde Mo","Eyes":"Source Overflow White"}},"3502":{"name":"OGenie 3502","traits":{"Background":"Fog","Skin":"Celestial Fire","Clothing":"Olive Jacket","Hat":"Grey Mullet","Mouth":"Ohhh","Eyes":"Hollow Black","Accessories":"Gold Stud"}},"3503":{"name":"OGenie 3503","traits":{"Background":"Red","Skin":"Glaucus","Clothing":"OG Jersey Dark","Hat":"Ginger Mullet","Mouth":"Ohhh","Eyes":"OG Wayfarer"}},"3504":{"name":"OGenie 3504","traits":{"Background":"Fog","Skin":"Mars Tattoo","Clothing":"Flannel Dark Red","Hat":"B&W Visor","Mouth":"Grin","Eyes":"Meme","Accessories":"Punk Stud"}},"3505":{"name":"OGenie 3505","traits":{"Background":"Steel Blue","Skin":"Pluto Dark Tattoo","Clothing":"WeAreOG Black","Hat":"Punk Dark","Accessories":"OG Element","Mouth":"G Smile","Eyes":"Black & Brown Wayfarer"}},"3506":{"name":"OGenie 3506","traits":{"Background":"Fog","Skin":"OG Element Tattoo","Clothing":"Flannel OG Green","Hat":"Blonde Quiff","Accessories":"Air Element","Mouth":"Shmoke","Eyes":"Black Wayfarer"}},"3507":{"name":"Multiverse OGenie - OTatt","traits":{"MV OGenie 1/1":"OTatt"}},"3508":{"name":"OGenie 3508","traits":{"Background":"Concrete","head-gear":"Smoke Halo","Skin":"Hina","Clothing":"Blue Stripe","Hat":"OG Green Fade","Accessories":"Coffee Mug","Mouth":"You What!","Eyes":"Top G Black"}},"3509":{"name":"OGenie 3509","traits":{"Background":"Fossil","Skin":"Jord","Clothing":"Flannel Red","Hat":"Peaky Brown","Accessories":"Diamond Hand","Mouth":"Black Mo","Eyes":"Source Overflow Black"}},"3510":{"name":"OGenie 3510","traits":{"Background":"Fog","Skin":"Glaucus","Clothing":"The OG Jumper","Hat":"Bucket Hat Black","Mouth":"Toothpick","Eyes":"OG Wayfarer","Accessories":"G-Pods"}},"3511":{"name":"OGenie 3511","traits":{"Background":"Concrete","Skin":"Devine Water","Clothing":"Army Jacket","Hat":"Green Visor","Accessories":"Baseball Glove & Gold Ball","Mouth":"Toothpick","Eyes":"Cartoon"}},"3512":{"name":"OGenie 3512","traits":{"Background":"Fog","Skin":"Hina","Clothing":"OG Jersey Dark","Hat":"BW Cap OG Green","Accessories":"Water Fist","Mouth":"Blonde Mo","Eyes":"OMega Laser Blue"}},"3513":{"name":"OGenie 3513","traits":{"Background":"Fog","Skin":"Pan","Clothing":"Red Track","Hat":"OG Green Fade","Accessories":"Wooden Bat","Mouth":"You What!","Eyes":"Round Black"}},"3514":{"name":"OGenie 3514","traits":{"Background":"Tortilla","Skin":"Tartarus","Clothing":"Flannel Red","Hat":"Peaky Black","Accessories":"Diamond Stud","Mouth":"Rainbow Grin","Eyes":"Top G Green"}},"3515":{"name":"OGenie 3515","traits":{"Background":"Dark Purple","Skin":"Pluto","Clothing":"Black Suit","Hat":"Curly Dark","Accessories":"Flower Power","Mouth":"G Smile","Eyes":"Clubmaster Silver"}},"3516":{"name":"OGenie 3516","traits":{"Background":"Dusty Pink","Skin":"Mars","Clothing":"Blue Denim Jacket","Hat":"Orange Beanie","Accessories":"Double Gold Loop","Mouth":"Rainbow Grin","Eyes":"Bubblegum Pitvipers"}},"3517":{"name":"OGenie 3517","traits":{"Background":"Stone","Skin":"Golden Ra","Clothing":"PS Grey","Hat":"Horns","Mouth":"Brown Mo","Eyes":"Round Black"}},"3518":{"name":"OGenie 3518","traits":{"Background":"Lavender","head-gear":"Smoke Halo","Skin":"Devine Earth","Clothing":"WeAreOG Black","Hat":"Green Visor","Accessories":"Fire Element","Mouth":"Grin","Eyes":"Tech Specs"}},"3519":{"name":"OGenie 3519","traits":{"Background":"Concrete","Skin":"Balor Tattoo","Clothing":"OG-Unit Vest","Hat":"Clear Bandana","Mouth":"G Smile","Eyes":"Source Overflow White"}},"3520":{"name":"OGenie 3520","traits":{"Background":"Feudal","Skin":"Agassou","Clothing":"Gold Chain","Hat":"Genie Bun","Accessories":"Gold Axe","Mouth":"Ohhh","Eyes":"Source Overflow White"}},"3521":{"name":"OGenie 3521","traits":{"Background":"Tortilla","Skin":"Mars","Clothing":"Black Bomber","Hat":"Rose Dust Mullet","Mouth":"Grey Beard","Eyes":"Round Black"}},"3522":{"name":"OGenie 3522","traits":{"Background":"Fossil","Skin":"Balor","Clothing":"Coppice Sweatshirt White","Hat":"Black Mullet","Accessories":"SC Cocktail","Mouth":"Black Mo","Eyes":"Orange Pitvipers"}},"3523":{"name":"OGenie 3523","traits":{"Background":"Steel Blue","Skin":"Jord","Clothing":"WeAreOGT White","Hat":"B&W Visor","Accessories":"Stardust","Mouth":"Grey Beard","Eyes":"Black Wayfarer"}},"3524":{"name":"OGenie 3524","traits":{"Background":"Steel Blue","Skin":"Celestial Cosmos","Clothing":"PS Beige","Hat":"Curly Dark","Accessories":"Gold Loop","Mouth":"Yeeaa","Eyes":"Reading Round White"}},"3525":{"name":"OGenie 3525","traits":{"Background":"Lavender","Skin":"Amaterasu","Clothing":"Army Jacket","Hat":"BW Cap Black","Accessories":"Broken Cue","Mouth":"Brown Mo","Eyes":"Hollow White"}},"3526":{"name":"OGenie 3526","traits":{"Background":"Steel Blue","Skin":"Amaterasu","Clothing":"WeAreOG Black","Hat":"Ancient Helmet","Mouth":"G Smile","Eyes":"Tech Specs"}},"3527":{"name":"OGenie 3527","traits":{"Background":"Fossil","Skin":"OG Element","Clothing":"OG Jersey Blue","Hat":"Black Quiff","Accessories":"Double Gold Loop","Mouth":"Ohhh","Eyes":"Top G Black"}},"3528":{"name":"OGenie 3528","traits":{"Background":"Ash","Skin":"Celestial Water","Clothing":"WeAreOG Purple","Hat":"Ginger Mullet","Accessories":"Crystal Orb","Mouth":"Whistle","Eyes":"Pink Round"}},"3529":{"name":"OGenie 3529","traits":{"Background":"Purple","Skin":"Mars","Clothing":"Navy Track Jacket","Hat":"Coppice Hat","Accessories":"OG Element","Mouth":"Black Mo","Eyes":"Cooked"}},"3530":{"name":"OGenie 3530","traits":{"Background":"Olive Green","Skin":"Balor","Clothing":"Black Suit","Hat":"Fade","Accessories":"Water Fist","Mouth":"Whistle","Eyes":"Black Wayfarer"}},"3531":{"name":"OGenie 3531","traits":{"Background":"Stone","Skin":"Pan","Clothing":"OGT Retro Track","Hat":"Punk Green","Mouth":"Toothpick","Eyes":"Transparent Wayfarer"}},"3532":{"name":"OGenie 3532","traits":{"Background":"Red","Skin":"Glaucus","Clothing":"Dark Grey Hoodie","Hat":"Yellow Beanie","Accessories":"Storm Fist","Mouth":"Shmoke","Eyes":"Bored"}},"3533":{"name":"OGenie 3533","traits":{"Background":"Purple","Skin":"OG Element Tattoo","Clothing":"WeAreOGT White","Hat":"OGT White Trucker","Accessories":"Katana Gold","Mouth":"Stubble Shmoke","Eyes":"Cooked"}},"3534":{"name":"OGenie 3534","traits":{"Background":"Fog","Skin":"Golden Ra","Clothing":"PS Purple & OG Green","Hat":"Black Visor","Mouth":"Ginger Beard","Eyes":"Black Pitviper","Accessories":"Gold Loop"}},"3535":{"name":"OGenie 3535","traits":{"Background":"Lavender","Skin":"Pluto","Clothing":"WeAreOG Black","Hat":"Trumpie","Accessories":"G-Pods","Mouth":"RollUp","Eyes":"Matrix"}},"3536":{"name":"OGenie 3536","traits":{"Background":"Lavender","Skin":"Amaterasu","Clothing":"Ripped Tank Top","Hat":"Grey Kasa","Accessories":"Broken Cue","Mouth":"Cigar","Eyes":"Reading Round White"}},"3537":{"name":"OGenie 3537","traits":{"Background":"Concrete","Skin":"Mars","Clothing":"Silver OGT Chain & Black Shirt","Hat":"Red Balaclava","Accessories":"Gold Bracelet & Ring","Mouth":"Shmoke","Eyes":"Cooked"}},"3538":{"name":"OGenie 3538","traits":{"Background":"Concrete","Skin":"Hina","Clothing":"Black T Gold OGT Chain","Hat":"Punk Pink","Accessories":"Thunder Lord","Mouth":"Ohhh","Eyes":"Turtle Wayfarer"}},"3539":{"name":"OGenie 3539","traits":{"Background":"Fossil","Skin":"Pluto Blue Tattoo","Clothing":"Coppice Sweatshirt White","Hat":"BW Cap OG Green","Accessories":"Coffee OGm","Mouth":"You What!","Eyes":"Black Pitviper"}},"3540":{"name":"OGenie 3540","traits":{"Background":"Lavender","head-gear":"G Crown","Skin":"Devine Earth","Clothing":"PS Beige","Mouth":"Blonde Mo","Eyes":"Turtle Wayfarer"}},"3541":{"name":"OGenie 3541","traits":{"Background":"OG Green","Skin":"Jord","Clothing":"PS Purple","Hat":"Fire Bun","Accessories":"Transparent Bat","Mouth":"Ohhh","Eyes":"Cartoon"}},"3542":{"name":"OGenie 3542","traits":{"Background":"Dark Purple","Skin":"Golden Ra","Clothing":"Special: Ollie's Hoodie","Hat":"OGT White Trucker","Accessories":"Gold Bracelet & Ring","Mouth":"Ginger Mo","Eyes":"Hollow Black"}},"3543":{"name":"OGenie 3543","traits":{"Background":"Ash","Skin":"Celestial Cosmos","Clothing":"PS Purple","Hat":"Fedora","Mouth":"Stubble Shmoke","Eyes":"Tech Specs"}},"3544":{"name":"OGenie 3544","traits":{"Background":"Dark Purple","Skin":"Raijin","Clothing":"Silver OGT Chain & Black Shirt","Hat":"Curly Blonde","Mouth":"RollUp","Eyes":"Reading Round"}},"3545":{"name":"OGenie 3545","traits":{"Background":"Red","Skin":"Pan","Clothing":"OG Jersey","Hat":"Black Hat","Accessories":"Broken Cue","Mouth":"Ginger Beard","Eyes":"Reading Round White"}},"3546":{"name":"OGenie 3546","traits":{"Background":"Tortilla","Skin":"Jord","Clothing":"Leather Jacket","Hat":"Blue Bandana","Accessories":"Pizza","Mouth":"Rainbow Grin","Eyes":"Round Black"}},"3547":{"name":"OGenie 3547","traits":{"Background":"Dusty Pink","Skin":"Pluto","Clothing":"WeAreOG Purple","Hat":"BW Cap OG Green","Accessories":"On the Rocks","Mouth":"Yeeaa","Eyes":"Source Overflow Black"}},"3548":{"name":"OGenie 3548","traits":{"Background":"Slate","Skin":"Balor Tattoo","Clothing":"Brown Cord Jacket","Hat":"Blue Bandana","Mouth":"Ohhh","Eyes":"Turtle Wayfarer"}},"3549":{"name":"OGenie 3549","traits":{"Background":"Lavender","Skin":"Devine Fire","Clothing":"OG Green Stripe","Hat":"Blond Fade","Accessories":"Gold Stud","Mouth":"Whistle","Eyes":"Reading Round White"}},"3550":{"name":"OGenie 3550","traits":{"Background":"Fog","Skin":"Pluto","Clothing":"OG Jersey Dark","Hat":"Black Quiff","Mouth":"Grey Beard","Eyes":"Transparent Wayfarer"}},"3551":{"name":"OGenie 3551","traits":{"Background":"Dusty Pink","Skin":"Pan","Clothing":"OG Green Stripe","Hat":"MNGA","Mouth":"G Smile","Eyes":"Black & Brown Wayfarer","Accessories":"Gold Loop"}},"3552":{"name":"OGenie 3552","traits":{"Background":"Slate","Skin":"Idube","Clothing":"PS Purple & OG Green","Hat":"Clear Bandana","Mouth":"Brown Mo","Eyes":"3D Glasses"}},"3553":{"name":"OGenie 3553","traits":{"Background":"Steel Blue","Skin":"Devine Fire","Clothing":"PS Beige","Hat":"Turquoise Mullet","Accessories":"Gold Stud","Mouth":"Shmoke","Eyes":"Tech Specs"}},"3554":{"name":"OGenie 3554","traits":{"Background":"Dusty Pink","Skin":"Aurora","Clothing":"OGT Black Track","Hat":"Black Bandana","Accessories":"Gamer","Mouth":"Black Mo","Eyes":"Black Pitviper"}},"3555":{"name":"OGenie 3555","traits":{"Background":"Lavender","Skin":"Devine Fire","Clothing":"OGT Black Track","Mouth":"Black Mo","Eyes":"Turtle Wayfarer"}},"3556":{"name":"OGenie 3556","traits":{"Background":"Concrete","Skin":"Glaucus Tattoo","Clothing":"Flannel Dark Red","Hat":"Black Hat","Accessories":"Transparent Axe","Mouth":"Toothpick","Eyes":"Meme"}},"3557":{"name":"OGenie 3557","traits":{"Background":"Concrete","Skin":"Balor Tattoo","Clothing":"Grey Suit Black Tie","Hat":"Rose Dust Mullet","Accessories":"Diamond Fist","Mouth":"Ginger Mo","Eyes":"Round Black"}},"3558":{"name":"OGenie 3558","traits":{"Background":"Lavender","Skin":"Tartarus","Clothing":"Red Leather Jacket","Hat":"Blonde Mullet","Mouth":"Rainbow Grin","Eyes":"Bubblegum Pitvipers"}},"3559":{"name":"OGenie 3559","traits":{"Background":"Slate","Skin":"Seshat","Clothing":"OG Green T","Hat":"Black Quiff","Mouth":"Grey Beard","Eyes":"White Visor Beam"}},"3560":{"name":"OGenie 3560","traits":{"Background":"Ash","Skin":"Glaucus","Clothing":"Silver OGT Chain & Black Shirt","Hat":"Green Splash","Mouth":"Brown Mo","Eyes":"Round Black"}},"3561":{"name":"OGenie 3561","traits":{"Background":"Slate","Skin":"Glaucus","Clothing":"Tweed Suit","Hat":"Trumpie","Accessories":"Paint Brush","Mouth":"Gold Grin","Eyes":"White Visor Beam"}},"3562":{"name":"OGenie 3562","traits":{"Background":"Lavender","Skin":"Devine Fire","Clothing":"OG-Unit Vest","Hat":"Red Bandana","Accessories":"Diamond Fist","Mouth":"Whistle","Eyes":"Cooked"}},"3563":{"name":"OGenie 3563","traits":{"Background":"Ash","Skin":"Pan Tattoo","Clothing":"Brown Puffer","Hat":"Hot Pink Fade","Mouth":"Shmoke","Eyes":"Storm"}},"3564":{"name":"OGenie 3564","traits":{"Background":"Lavender","Skin":"Aurora","Clothing":"Shirt & Vest","Hat":"Blond Bandana","Mouth":"Toothpick","Eyes":"OG Wayfarer"}},"3565":{"name":"OGenie 3565","traits":{"Background":"Steel Blue","Skin":"Raijin","Clothing":"OG Green Stripe","Hat":"Blonde Quiff","Accessories":"Double Gold Loop","Mouth":"Black Beard","Eyes":"Top G Gold"}},"3566":{"name":"OGenie 3566","traits":{"Background":"OG Green","Skin":"Devine Fire","Clothing":"PS Green Flowers","Hat":"Brown Quiff","Accessories":"Earth Element","Mouth":"You What!","Eyes":"Reading Round"}},"3567":{"name":"OGenie 3567","traits":{"Background":"Steel Blue","Skin":"Pluto","Clothing":"OG Jersey Red","Hat":"Curly Blonde","Accessories":"Flower Power","Mouth":"G Smile","Eyes":"Cartoon"}},"3568":{"name":"OGenie 3568","traits":{"Background":"Dusty Blue","Skin":"Sunrise Hina","Clothing":"Dark Grey Hoodie","Hat":"Purple Splash","Mouth":"Ginger Beard","Eyes":"OG Round"}},"3569":{"name":"OGenie 3569","traits":{"Background":"Slate","Skin":"Tartarus","Clothing":"Prison T","Hat":"OGT White Trucker","Accessories":"Black Bat","Mouth":"Grin","Eyes":"Top G Black"}},"3570":{"name":"OGenie 3570","traits":{"Background":"Slate","Skin":"Seshat","Clothing":"Olive Jacket","Hat":"Camo Helmet","Accessories":"Coffee Mug","Mouth":"Ginger Beard","Eyes":"Reading Round"}},"3571":{"name":"OGenie 3571","traits":{"Background":"Steel Blue","Skin":"Apollo","Clothing":"PS Green Flowers","Hat":"Punk Green","Mouth":"Stubble Shmoke","Eyes":"OG Round"}},"3572":{"name":"OGenie 3572","traits":{"Background":"Fossil","Skin":"Celestial Fire","Clothing":"Gold Chain & Black T","Hat":"Yellow Beanie","Mouth":"Grey Beard","Eyes":"Black Pitviper"}},"3573":{"name":"OGenie 3573","traits":{"Background":"Dusty Pink","Skin":"Mars","Clothing":"Special: Tycoon Tux","Hat":"Punk Blonde","Mouth":"Ginger Mo","Eyes":"Reading Round White"}},"3574":{"name":"OGenie 3574","traits":{"Background":"Ash","Skin":"Bast","Clothing":"Coppice Sweatshirt White","Hat":"Black Beanie","Accessories":"Gold Bracelet & Ring","Mouth":"G Smile","Eyes":"Bored"}},"3575":{"name":"OGenie 3575","traits":{"Background":"Concrete","Skin":"Seshat","Clothing":"Black Puffer","Hat":"Coppice Hat","Accessories":"Gold Ring & Bracelet","Mouth":"Toothpick","Eyes":"Transparent Pitvipers"}},"3576":{"name":"OGenie 3576","traits":{"Background":"Feudal","Skin":"Glaucus","Clothing":"Black T Gold OGT Chain","Hat":"Wreth","Mouth":"Gold Grin","Eyes":"Top G Gold"}},"3577":{"name":"OGenie 3577","traits":{"Background":"Concrete","Skin":"Devine Fire","Clothing":"Black Puffer","Hat":"Biker Helmet Black","Mouth":"You What!","Eyes":"Hollow White","Accessories":"Punk Stud"}},"3578":{"name":"OGenie 3578","traits":{"Background":"Hazy Blue","Skin":"Celestial Water","Clothing":"Flannel OG Green","Hat":"Fade","Accessories":"Double Gold Loop","Mouth":"Yeeaa","Eyes":"Eye Patch"}},"3579":{"name":"OGenie 3579","traits":{"Background":"Concrete","Skin":"Jord","Clothing":"Olive Jacket","Hat":"Grey Kasa","Accessories":"Thunder Lord","Mouth":"Blonde Mo","Eyes":"Hollow Black"}},"3580":{"name":"OGenie 3580","traits":{"Background":"Lavender","Skin":"OG Element Tattoo","Clothing":"Black Camo Jacket","Hat":"Black Quiff","Mouth":"Blonde Mo","Eyes":"Turtle Wayfarer","Accessories":"G-Pods"}},"3581":{"name":"OGenie 3581","traits":{"Background":"Fog","Skin":"Celestial Tectonic","Clothing":"Special: Lazy Shirt","Hat":"Ancient Helmet","Accessories":"Water Element","Mouth":"Grey Beard","Eyes":"Eyes White"}},"3582":{"name":"OGenie 3582","traits":{"Background":"Concrete","Skin":"Pluto","Clothing":"Special: A Hoodish Bear","Hat":"Black Kasa","Accessories":"G-Pods","Mouth":"Grin","Eyes":"Hollow Black"}},"3583":{"name":"OGenie 3583","traits":{"Background":"Dusty Blue","Skin":"Bast","Clothing":"WeAreOGT White","Hat":"Peaky Black","Mouth":"Brown Mo","Eyes":"Black Wayfarer"}},"3584":{"name":"OGenie 3584","traits":{"Background":"Hazy Blue","Skin":"Celestial Eternity","Clothing":"Tweed Suit","Hat":"Fade","Accessories":"Katana Gold","Mouth":"Ginger Beard","Eyes":"OG Round"}},"3585":{"name":"OGenie 3585","traits":{"Background":"Hazy Blue","Skin":"Glaucus","Clothing":"OGT Retro Track","Hat":"Red Balaclava","Accessories":"Glove Right","Mouth":"Grin","Eyes":"OG Round"}},"3586":{"name":"OGenie 3586","traits":{"Background":"Concrete","Skin":"Pan","Clothing":"Army Jacket","Hat":"Clear Bandana","Mouth":"Ohhh","Eyes":"Blue Visor Beam","Accessories":"Gold Loop"}},"3587":{"name":"OGenie 3587","traits":{"Background":"Lavender","Skin":"Tartarus","Clothing":"WeAreOGT White","Accessories":"Gold Loop","Mouth":"Whistle","Eyes":"Pink Round"}},"3588":{"name":"OGenie 3588","traits":{"Background":"Slate","Skin":"Balor Tattoo","Clothing":"Black Hoodie","Hat":"Grey Kasa","Mouth":"Grin","Eyes":"Black Pitviper"}},"3589":{"name":"OGenie 3589","traits":{"Background":"Red","Skin":"Hina","Clothing":"Black Suit","Hat":"Punk Dark","Accessories":"Gold Bat","Mouth":"Ginger Mo","Eyes":"Hollow White"}},"3590":{"name":"OGenie 3590","traits":{"Background":"Steel Blue","Skin":"Air White Tattoo","Clothing":"Blue Stripe","Hat":"Grey Balaclava","Mouth":"Gold Grin","Eyes":"Source Overflow OG"}},"3591":{"name":"OGenie 3591","traits":{"Background":"Lavender","Skin":"Pluto","Clothing":"OG Jersey Dark","Hat":"Curly Blonde","Accessories":"Punk Stud","Mouth":"Grin","Eyes":"Pink Round"}},"3592":{"name":"OGenie 3592","traits":{"Background":"Stone","Skin":"Glaucus","Clothing":"Coppice Sweatshirt White","Hat":"MNGA","Mouth":"Ginger Mo","Eyes":"Top G Gold"}},"3593":{"name":"OGenie 3593","traits":{"Background":"Fog","Skin":"Raijin","Clothing":"Flannel Dark Red","Hat":"Wreth","Accessories":"Storm Control","Mouth":"Black Beard","Eyes":"Bubblegum Pitvipers"}},"3594":{"name":"OGenie 3594","traits":{"Background":"Fossil","head-gear":"Gold Halo","Skin":"Jord","Clothing":"Biker Vest","Hat":"Peaky Brown","Accessories":"Transparent Bat","Mouth":"Grey Beard","Eyes":"Reading Round"}},"3595":{"name":"OGenie 3595","traits":{"Background":"Lavender","Skin":"Water Tattoo","Clothing":"WeAreOGT White","Hat":"Blonde Mullet","Mouth":"Brown Mo","Eyes":"Turtle Wayfarer"}},"3596":{"name":"OGenie 3596","traits":{"Background":"Olive Green","Skin":"Apollo","Clothing":"JPD","Hat":"Red Beanie","Accessories":"Broken Cue","Mouth":"Ohhh","Eyes":"Monocle OG"}},"3597":{"name":"OGenie 3597","traits":{"Background":"Steel Blue","Skin":"Hina","Clothing":"Retro Track Black","Hat":"Punk Blonde","Accessories":"Diamond Stud","Mouth":"Ginger Beard","Eyes":"Eye Patch"}},"3598":{"name":"OGenie 3598","traits":{"Background":"Purple","Skin":"Raijin","Clothing":"Gold Chain & Black T","Hat":"Pompadour","Mouth":"Black Mo","Eyes":"Eyes White"}},"3599":{"name":"OGenie 3599","traits":{"Background":"Dusty Pink","Skin":"Celestial Earth","Clothing":"Black Bomber","Hat":"Ancient Helmet","Mouth":"Yeeaa","Eyes":"Clubmaster Silver","Accessories":"Gold Loop"}},"3600":{"name":"OGenie 3600","traits":{"Background":"Red","Skin":"Pluto","Clothing":"OG Jersey","Hat":"Pink Splash","Accessories":"Earth Element","Mouth":"Black Beard","Eyes":"Storm"}},"3601":{"name":"OGenie 3601","traits":{"Background":"Dark Purple","Skin":"Hina","Clothing":"Flannel Dark Red","Hat":"Pink Bandana","Mouth":"Toothpick","Eyes":"Eye Patch"}},"3602":{"name":"OGenie 3602","traits":{"Background":"Fog","Skin":"Sunrise Jord","Clothing":"Blue Stripe","Hat":"Curly Blonde","Mouth":"Ginger Beard","Eyes":"Black Wayfarer"}},"3603":{"name":"OGenie 3603","traits":{"Background":"Steel Blue","Skin":"Luna","Clothing":"OG Green Stripe","Hat":"Air Hair","Accessories":"Transparent Skateboard","Mouth":"G Smile","Eyes":"Cartoon"}},"3604":{"name":"OGenie 3604","traits":{"Background":"Fossil","Skin":"Luna","Clothing":"OGT Retro Track","Hat":"Air Hair","Mouth":"Brown Mo","Eyes":"Red Visor Beam"}},"3605":{"name":"OGenie 3605","traits":{"Background":"Dusty Blue","Skin":"Pluto Dark Tattoo","Clothing":"OGT Retro Track","Hat":"Captain","Accessories":"Gold Bracelet & Ring","Mouth":"You What!","Eyes":"Transparent Wayfarer"}},"3606":{"name":"OGenie 3606","traits":{"Background":"Hazy Blue","head-gear":"Gold Halo","Skin":"Hina","Clothing":"JPD","Hat":"Hot Pink Fade","Accessories":"Diamond Hand","Mouth":"Ginger Beard","Eyes":"Tech Specs"}},"3607":{"name":"OGenie 3607","traits":{"Background":"Stone","Skin":"Luna","Clothing":"OG Green Hoodie","Hat":"Bucket Hat Black","Accessories":"Diamond Stud","Mouth":"Toothpick","Eyes":"Top G Black"}},"3608":{"name":"OGenie 3608","traits":{"Background":"Fossil","Skin":"Tartarus","Clothing":"Navy Track Jacket","Hat":"OG Green Fade","Mouth":"Ohhh","Eyes":"Storm","Accessories":"Gold Stud"}},"3609":{"name":"OGenie 3609","traits":{"Background":"Fog","Skin":"Bast","Clothing":"Brown Cord Jacket","Hat":"Air Hair","Mouth":"Brown Mo","Eyes":"Black Wayfarer","Accessories":"Gold Loop"}},"3610":{"name":"OGenie 3610","traits":{"Background":"Concrete","Skin":"Celestial Air","Clothing":"OG Green Stripe","Hat":"Blond Bandana","Mouth":"Black Beard","Eyes":"Tech Specs"}},"3611":{"name":"OGenie 3611","traits":{"Background":"Dark Purple","Skin":"Pluto","Clothing":"Special: Tycoon Tux","Hat":"OG Green Fade","Accessories":"Punk Stud","Mouth":"Yeeaa","Eyes":"Black Pitviper"}},"3612":{"name":"OGenie 3612","traits":{"Background":"Steel Blue","Skin":"Idube","Clothing":"OG Green Stripe","Hat":"Fade","Accessories":"Double Gold Loop","Mouth":"G Smile","Eyes":"Cartoon"}},"3613":{"name":"OGenie 3613","traits":{"Background":"Dusty Blue","Skin":"Glaucus","Clothing":"White Shirt OG Green Suit","Hat":"Blond Quiff","Accessories":"Water Element","Mouth":"You What!","Eyes":"Clubmaster Gold"}},"3614":{"name":"OGenie 3614","traits":{"Background":"Concrete","Skin":"Flora","Clothing":"White T Gold Chain","Hat":"Dark Quiff","Mouth":"Toothpick","Eyes":"Cartoon"}},"3615":{"name":"OGenie 3615","traits":{"Background":"Dark Purple","Skin":"Amaterasu","Clothing":"Silver OGT Chain","Hat":"Ancient Helmet","Mouth":"Stubble Shmoke","Eyes":"OG Element Visor Beam"}},"3616":{"name":"OGenie 3616","traits":{"Background":"Purple","Skin":"Jord","Clothing":"Brown Cord Jacket","Hat":"Ginger Mullet","Accessories":"Gold Axe","Mouth":"Cigar","Eyes":"Hollow Black"}},"3617":{"name":"OGenie 3617","traits":{"Background":"Slate","Skin":"Seshat","Clothing":"Black Denim Jacket","Hat":"B&W Visor","Mouth":"Whistle","Eyes":"Tech Specs"}},"3618":{"name":"OGenie 3618","traits":{"Background":"Lavender","Skin":"Mars","Clothing":"WeAreOG Black","Hat":"Clear Bandana","Mouth":"Shmoke","Eyes":"Bubblegum Pitvipers","Accessories":"Gold Stud"}},"3619":{"name":"OGenie 3619","traits":{"Background":"Concrete","Skin":"Devine Fire","Clothing":"PS Beige","Accessories":"Paint Brush","Mouth":"Blonde Mo","Eyes":"Turtle Wayfarer"}},"3620":{"name":"OGenie 3620","traits":{"Background":"Slate","Skin":"Mars","Clothing":"Army Jacket","Hat":"Yellow Beanie","Accessories":"Crystal Orb","Mouth":"Black Mo","Eyes":"Transparent Wayfarer"}},"3621":{"name":"OGenie 3621","traits":{"Background":"Dark Purple","Skin":"Idube","Clothing":"Grey Hoodie","Hat":"Green Visor","Mouth":"Ginger Beard","Eyes":"Cartoon"}},"3622":{"name":"OGenie 3622","traits":{"Background":"Red","Skin":"Water Tattoo","Clothing":"Blue Denim Jacket","Hat":"Olive Helmet","Mouth":"Ginger Beard","Eyes":"OG Wayfarer"}},"3623":{"name":"OGenie 3623","traits":{}},"3624":{"name":"OGenie 3624","traits":{"Background":"Dark Purple","Skin":"Golden Ra","Clothing":"Camo Jacket","Hat":"Punk Dark","Mouth":"Yeeaa","Eyes":"Black Pitviper"}},"3625":{"name":"OGenie 3625","traits":{"Background":"Stone","Skin":"Hina","Clothing":"Black Puffer","Hat":"Locks & Comb","Accessories":"Storm Control","Mouth":"Stubble Shmoke","Eyes":"Clubmaster Silver"}},"3626":{"name":"OGenie 3626","traits":{"Background":"Fog","Skin":"Pluto","Clothing":"PS Purple & OG Green","Hat":"Olive Mullet","Mouth":"Whistle","Eyes":"OG Round"}},"3627":{"name":"OGenie 3627","traits":{"Background":"Fog","Skin":"Devine Fire","Clothing":"Blue Denim Jacket","Hat":"Olive Helmet","Mouth":"Grin","Eyes":"Black Pitviper"}},"3628":{"name":"OGenie 3628","traits":{"Background":"Lavender","Skin":"Celestial Air","Clothing":"Black Bomber","Hat":"Grey Quiff","Accessories":"Gold Bracelet & Ring","Mouth":"Shmoke","Eyes":"Black & Brown Wayfarer"}},"3629":{"name":"OGenie 3629","traits":{"Background":"Ash","Skin":"Fujin","Clothing":"Punk Leather Jacket","Hat":"Bucket Hat Olive","Mouth":"Toothpick","Eyes":"Storm"}},"3630":{"name":"OGenie 3630","traits":{"Background":"Red","Skin":"Pluto","Clothing":"PS Purple & OG Green","Accessories":"Double Gold Loop","Mouth":"Ginger Beard","Eyes":"Top G Black"}},"3631":{"name":"OGenie 3631","traits":{}},"3632":{"name":"OGenie 3632","traits":{"Background":"Concrete","Skin":"Pan","Clothing":"JPD","Hat":"Curly Blonde","Accessories":"On the Rocks","Mouth":"RollUp","Eyes":"Storm"}},"3633":{"name":"OGenie 3633","traits":{"Background":"Steel Blue","Skin":"Devine Water","Clothing":"Brown Cord Jacket","Hat":"Ancient Helmet","Accessories":"Transparent Bat","Mouth":"You What!","Eyes":"OG Round"}},"3634":{"name":"OGenie 3634","traits":{"Background":"Slate","Skin":"Golden Ra","Clothing":"OG Jersey Dark","Hat":"Earth Hair","Accessories":"Coffee OGm","Mouth":"G Smile","Eyes":"Source Overflow White"}},"3635":{"name":"OGenie 3635","traits":{"Background":"Stone","Skin":"Jord","Clothing":"OG Jersey Red","Hat":"Yellow Beanie","Mouth":"Yeeaa","Eyes":"OG Element Blast"}},"3636":{"name":"OGenie 3636","traits":{"Background":"Concrete","Skin":"Flora","Clothing":"Gold Chain","Hat":"Sushi Bandana White","Accessories":"Broken Cue","Mouth":"Yeeaa","Eyes":"Source Overflow White"}},"3637":{"name":"OGenie 3637","traits":{"Background":"Lavender","Skin":"Pan","Clothing":"Olive Jacket","Hat":"Horns","Mouth":"Toothpick","Eyes":"Cooked"}},"3638":{"name":"OGenie 3638","traits":{"Background":"Stone","Skin":"Idube","Clothing":"Camo Jacket","Hat":"Red Bandana","Mouth":"Blonde Mo","Eyes":"White Visor Beam"}},"3639":{"name":"OGenie 3639","traits":{"Background":"Fossil","Skin":"Balor","Clothing":"Black Shirt OG Green Suit","Hat":"BW Cap Red","Mouth":"Grin","Eyes":"Orange Pitvipers","Accessories":"Gold Stud"}},"3640":{"name":"OGenie 3640","traits":{"Background":"Feudal","Skin":"Pan","Clothing":"OG-Unit Vest","Hat":"BW Cap OG Green","Accessories":"Air Element","Mouth":"Rainbow Grin","Eyes":"Hollow Black"}},"3641":{"name":"OGenie 3641","traits":{"Background":"Dusty Blue","Skin":"Hina","Clothing":"WeAreOG Purple","Hat":"MNGA","Mouth":"Toothpick","Eyes":"Blue Visor Beam"}},"3642":{"name":"OGenie 3642","traits":{"Background":"OG Green","Skin":"Devine Fire","Clothing":"Brown Cord Jacket","Hat":"Brown Quiff","Mouth":"Black Mo","Eyes":"Turtle Wayfarer"}},"3643":{"name":"OGenie 3643","traits":{"Background":"Dusty Blue","Skin":"Mars","Clothing":"Camo Jacket","Hat":"Dark Quiff","Accessories":"Katana Gold","Mouth":"Brown Mo","Eyes":"Reading Round"}},"3644":{"name":"OGenie 3644","traits":{"Background":"Red","Skin":"Seshat","Clothing":"Blue Denim Jacket","Hat":"Black Hat","Accessories":"Glove Left","Mouth":"G Smile","Eyes":"Clubmaster Silver"}},"3645":{"name":"OGenie 3645","traits":{"Background":"Hazy Blue","Skin":"Pan","Clothing":"Presidential","Hat":"Black Quiff","Accessories":"Molecule Control","Mouth":"Ohhh","Eyes":"Round Black"}},"3646":{"name":"OGenie 3646","traits":{"Background":"Lavender","Skin":"Flora","Clothing":"Black Denim Jacket","Hat":"Captain","Accessories":"RayGun","Mouth":"Grey Beard","Eyes":"Bored"}},"3647":{"name":"OGenie 3647","traits":{"Background":"Lavender","Skin":"Seshat","Clothing":"OG Jersey Blue","Hat":"Peaky Brown","Mouth":"Cigar","Eyes":"Hollow White"}},"3648":{"name":"OGenie 3648","traits":{"Background":"Concrete","Skin":"Sunrise Hina","Clothing":"Punk Leather Jacket","Hat":"Fedora","Mouth":"Brown Mo","Eyes":"Hollow Black","Accessories":"Gold Stud"}},"3649":{"name":"OGenie 3649","traits":{"Background":"Dusty Blue","Skin":"Devine Fire","Clothing":"Blue Stripe","Hat":"Fade & Horns","Accessories":"Light Bulb","Mouth":"Yeeaa","Eyes":"Pink Round"}},"3650":{"name":"OGenie 3650","traits":{"Background":"Ash","Skin":"Hina","Clothing":"PS Green Flowers","Hat":"Captain","Accessories":"Glove Right","Mouth":"Grey Beard","Eyes":"Clubmaster Silver"}},"3651":{"name":"OGenie 3651","traits":{"Background":"Hazy Blue","Skin":"Bast","Clothing":"Gold Chain & Black T","Hat":"Yellow Beanie","Mouth":"Stubble Shmoke","Eyes":"Orange Pitvipers"}},"3652":{"name":"OGenie 3652","traits":{"Background":"Red","Skin":"Bast","Clothing":"White Hoodie","Hat":"Black Quiff","Mouth":"Whistle","Eyes":"Transparent Pitvipers"}},"3653":{"name":"OGenie 3653","traits":{"Background":"Lavender","Skin":"Devine Earth","Clothing":"OG Jersey","Hat":"Ginger Mullet","Mouth":"You What!","Eyes":"Cooked"}},"3654":{"name":"OGenie 3654","traits":{"Background":"Stone","Skin":"Fujin","Clothing":"RUB Responsibly T","Hat":"Grey Mullet","Accessories":"Sword","Mouth":"RollUp","Eyes":"Hollow White"}},"3655":{"name":"OGenie 3655","traits":{"Background":"OG Green","Skin":"Fujin","Clothing":"Camo Jacket","Hat":"Blue Bandana","Accessories":"Diamond Stud","Mouth":"Ohhh","Eyes":"OG Wayfarer"}},"3656":{"name":"OGenie 3656","traits":{"Background":"Red","Skin":"Hina","Clothing":"Jail T","Hat":"Olive Helmet","Mouth":"Cigar","Eyes":"Reading Round White"}},"3657":{"name":"OGenie 3657","traits":{"Background":"Lavender","Skin":"Devine Water","Clothing":"J Hoodie","Hat":"Pink Mullet","Mouth":"Ohhh","Eyes":"Reading Round White"}},"3658":{"name":"OGenie 3658","traits":{"Background":"Concrete","Skin":"Idube","Clothing":"Sweatshirt Gold OGT Chain","Hat":"Green Visor","Mouth":"Grey Beard","Eyes":"Black & Brown Wayfarer","Accessories":"Diamond Stud"}},"3659":{"name":"OGenie 3659","traits":{"Background":"Dusty Blue","Skin":"Jord","Clothing":"Silver OGT Chain & Black Shirt","Hat":"Cotton Candy Mullet","Mouth":"Black Mo","Eyes":"Reading Round"}},"3660":{"name":"OGenie 3660","traits":{"Background":"Olive Green","Skin":"Glaucus","Clothing":"OG-Unit T & Gold Chain","Hat":"Blond Bandana","Accessories":"Water Control","Mouth":"Grey Beard","Eyes":"Round Black"}},"3661":{"name":"OGenie 3661","traits":{"Background":"Hazy Blue","Skin":"Apollo","Clothing":"Grey Hoodie","Hat":"BW Cap Black","Mouth":"Black Beard","Eyes":"Black Wayfarer"}},"3662":{"name":"OGenie 3662","traits":{"Background":"Dark Purple","Skin":"Devine Water","Clothing":"Flannel OG Green","Hat":"Trumpie","Mouth":"Black Mo","Eyes":"Pink Round"}},"3663":{"name":"OGenie 3663","traits":{"Background":"Concrete","Skin":"Agassou","Clothing":"Black Puffer","Hat":"Black Mullet","Mouth":"Whistle","Eyes":"Eyes White"}},"3664":{"name":"OGenie 3664","traits":{"Background":"Fog","Skin":"Flora","Clothing":"OG Green T","Hat":"Olive Mullet","Accessories":"Fire Element","Mouth":"Blonde Mo","Eyes":"Reading Round"}},"3665":{"name":"OGenie 3665","traits":{"Background":"Ash","Skin":"Idube","Clothing":"Black Camo Jacket","Hat":"Curly Blonde","Accessories":"Gold Ring & Bracelet","Mouth":"Grin","Eyes":"Bubblegum Pitvipers"}},"3666":{"name":"OGenie 3666","traits":{"Background":"Fog","Skin":"Celestial Tectonic","Clothing":"The OG Jumper","Hat":"Punk Pink","Accessories":"Gamer","Mouth":"Brown Mo","Eyes":"Black & Brown Wayfarer"}},"3667":{"name":"OGenie 3667","traits":{"Background":"Purple","Skin":"Jord","Clothing":"Camo Jacket","Hat":"Orange Beanie","Accessories":"Baseball Glove & Gold Ball","Mouth":"Black Beard","Eyes":"OG Round"}},"3668":{"name":"OGenie 3668","traits":{"Background":"Steel Blue","Skin":"Jord","Clothing":"OG Green Stripe","Hat":"Black Beanie","Accessories":"Gold Stud","Mouth":"Ginger Beard","Eyes":"Hollow Black"}},"3669":{"name":"OGenie 3669","traits":{"Background":"Steel Blue","Skin":"Mars","Clothing":"Gradient Puffer","Hat":"Cotton Candy Mullet","Mouth":"Ginger Beard","Eyes":"Eyes White","Accessories":"Double Gold Loop"}},"3670":{"name":"OGenie 3670","traits":{"Background":"Dusty Blue","Skin":"Pan","Clothing":"Flannel Red","Hat":"Red Balaclava","Mouth":"Shmoke","Eyes":"Reading Round White"}},"3671":{"name":"OGenie 3671","traits":{"Background":"Concrete","Skin":"Golden Ra","Clothing":"Spartan Cloak","Mouth":"Blonde Mo","Eyes":"Orange Pitvipers"}},"3672":{"name":"OGenie 3672","traits":{"Background":"Slate","Skin":"Celestial Eternity","Clothing":"Army Jacket","Hat":"Fedora","Accessories":"Glove Right","Mouth":"Grin","Eyes":"Meme"}},"3673":{"name":"OGenie 3673","traits":{"Background":"Concrete","Skin":"OG Element","Clothing":"Brown Puffer","Hat":"Punk Green","Accessories":"Gold Stud","Mouth":"Grin","Eyes":"Source Overflow Black"}},"3674":{"name":"OGenie 3674","traits":{"Background":"Dark Purple","Skin":"Pan","Clothing":"Dark Grey Hoodie","Hat":"Fade","Mouth":"You What!","Eyes":"Black Pitviper","Accessories":"Punk Stud"}},"3675":{"name":"OGenie 3675","traits":{"Background":"OG Green","Skin":"OG Element Tattoo","Clothing":"RUB Responsibly T","Hat":"Fade","Mouth":"RollUp","Eyes":"Monocle OG"}},"3676":{"name":"OGenie 3676","traits":{"Background":"Slate","Skin":"Seshat","Clothing":"OG Green T","Hat":"Curly Dark","Mouth":"Yeeaa","Eyes":"Eyes White"}},"3677":{"name":"OGenie 3677","traits":{"Background":"Dusty Blue","Skin":"Devine Water","Clothing":"Shirt & Vest","Hat":"Camo Helmet","Accessories":"Gamer","Mouth":"Cigar","Eyes":"Orange Pitvipers"}},"3678":{"name":"OGenie 3678","traits":{"Background":"Fossil","Skin":"Pluto","Clothing":"Grey Suit Black Tie","Hat":"Pink Mullet","Accessories":"Molecule Control","Mouth":"Grin","Eyes":"Reading Round"}},"3679":{"name":"OGenie 3679","traits":{"Background":"Concrete","Skin":"OG Element","Clothing":"PS Beige","Hat":"Special: A FreaknHeadPiece","Accessories":"Black Bat","Mouth":"Black Beard","Eyes":"Source Overflow Black"}},"3680":{"name":"OGenie 3680","traits":{"Background":"Concrete","Skin":"Glaucus","Clothing":"Punk Leather Jacket","Hat":"Pink Splash","Mouth":"Yeeaa","Eyes":"Cartoon"}},"3681":{"name":"OGenie 3681","traits":{"Background":"Concrete","Skin":"Luna","Clothing":"WeAreOG Black","Hat":"Olive Mullet","Accessories":"Transparent Skateboard","Mouth":"Grey Beard","Eyes":"Meme"}},"3682":{"name":"OGenie 3682","traits":{"Background":"OG Green","Skin":"Balor","Clothing":"Retro Track Purple","Hat":"Curly Dark","Accessories":"Gold Ring & Bracelet","Mouth":"Yeeaa","Eyes":"Meme"}},"3683":{"name":"OGenie 3683","traits":{"Background":"Lavender","Skin":"Flora","Clothing":"Black Hoodie","Hat":"Red Beanie","Mouth":"Toothpick","Eyes":"Pink Round"}},"3684":{"name":"OGenie 3684","traits":{"Background":"Olive Green","Skin":"Mars","Clothing":"Blue Stripe","Hat":"Blond Fade","Accessories":"Sword","Mouth":"Whistle","Eyes":"Matrix"}},"3685":{"name":"OGenie 3685","traits":{"Background":"Fog","Skin":"Celestial Cosmos","Clothing":"Red Leather Jacket","Hat":"Punk Green","Accessories":"Special: LTFree","Mouth":"Grey Beard","Eyes":"Meme"}},"3686":{"name":"OGenie 3686","traits":{"Background":"Purple","Skin":"Devine Fire","Clothing":"Red Track","Hat":"BW Cap Red","Mouth":"Shmoke","Eyes":"Meme"}},"3687":{"name":"OGenie 3687","traits":{"Background":"Dark Purple","Skin":"Pan","Clothing":"Black T Gold OGT Chain","Hat":"Black Quiff","Accessories":"Katana Gold","Mouth":"You What!","Eyes":"Red Blast"}},"3688":{"name":"OGenie 3688","traits":{"Background":"Concrete","Skin":"Jord","Clothing":"Sweatshirt Gold OGT Chain","Hat":"OG Wizard Hat","Accessories":"Flower Power","Mouth":"Yeeaa","Eyes":"Source Overflow Black"}},"3689":{"name":"OGenie 3689","traits":{"Background":"Ash","Skin":"Mars","Clothing":"PS Red","Hat":"Grey Quiff","Accessories":"Baseball Glove & Ball","Mouth":"Brown Mo","Eyes":"Reading Round White"}},"3690":{"name":"OGenie 3690","traits":{"Background":"Stone","Skin":"Celestial Water","Clothing":"White Hoodie","Hat":"OG Green Trucker","Accessories":"Silver Axe","Mouth":"You What!","Eyes":"Pink Round"}},"3691":{"name":"OGenie 3691","traits":{"Background":"Lavender","Skin":"Flora","Clothing":"OG Jersey Dark","Hat":"Dark Quiff","Mouth":"Grin","Eyes":"Top G Black"}},"3692":{"name":"OGenie 3692","traits":{"Background":"Fossil","Skin":"Pluto","Clothing":"OG-Unit Vest","Hat":"Black Kasa","Accessories":"Coffee Mug","Mouth":"Black Beard","Eyes":"Round Black"}},"3693":{"name":"OGenie 3693","traits":{"Background":"Slate","Skin":"Sunrise Hina","Clothing":"Tweed Suit","Hat":"Ginger Mullet","Accessories":"Beer Bottle","Mouth":"Cigar","Eyes":"Pink Round"}},"3694":{"name":"OGenie 3694","traits":{"Background":"Slate","Skin":"Tartarus","Clothing":"Black Bomber","Hat":"Black Quiff","Mouth":"Brown Mo","Eyes":"OG Element Blast"}},"3695":{"name":"OGenie 3695","traits":{"Background":"Concrete","Skin":"Glaucus","Clothing":"Presidential","Hat":"Genie Bun","Accessories":"Prism","Mouth":"G Smile","Eyes":"Storm"}},"3696":{"name":"OGenie 3696","traits":{"Background":"Tortilla","Skin":"Tartarus","Clothing":"Special: Space Riding Suit","Hat":"Camo Helmet","Accessories":"Water Element","Mouth":"Shmoke","Eyes":"Hollow Black"}},"3697":{"name":"OGenie 3697","traits":{"Background":"Dusty Blue","Skin":"Devine Earth","Clothing":"Coppice Sweatshirt Green","Hat":"Blue Bandana","Mouth":"Ginger Beard","Eyes":"Orange Pitvipers","Accessories":"Double Gold Loop"}},"3698":{"name":"OGenie 3698","traits":{"Background":"Lavender","Skin":"Luna","Clothing":"Retro Track Purple","Hat":"Punk Pink","Accessories":"Glove Right","Mouth":"G Smile","Eyes":"Pink Round"}},"3699":{"name":"OGenie 3699","traits":{"Background":"Fog","Skin":"Hina","Clothing":"Flannel Dark Red","Hat":"Bucket Hat Black","Mouth":"Rainbow Grin","Eyes":"Source Overflow OG"}},"3700":{"name":"OGenie 3700","traits":{"Background":"Slate","Skin":"Golden Ra","Clothing":"PS Red","Hat":"Trumpie","Mouth":"Whistle","Eyes":"OG Round","Accessories":"Diamond Stud"}},"3701":{"name":"OGenie 3701","traits":{"Background":"Ash","Skin":"Hina","Clothing":"Jail T","Hat":"Rose Dust Mullet","Accessories":"Transparent Skateboard","Mouth":"You What!","Eyes":"Clubmaster Gold"}},"3702":{"name":"OGenie 3702","traits":{"Background":"Fossil","Skin":"Glaucus","Clothing":"OG Green Hoodie","Hat":"Olive Mullet","Accessories":"Gamer","Mouth":"Cigar","Eyes":"Meme"}},"3703":{"name":"OGenie 3703","traits":{"Background":"Tortilla","Skin":"Balor Tattoo","Clothing":"Black Bomber","Hat":"Coppice Hat","Accessories":"Baseball Glove & Gold Ball","Mouth":"Grey Beard","Eyes":"Top G Black"}},"3704":{"name":"OGenie 3704","traits":{"Background":"Slate","Skin":"Glaucus","Clothing":"White Hoodie","Hat":"OG Wizard Hat","Mouth":"Shmoke","Eyes":"Black Pitviper","Accessories":"G-Pods"}},"3705":{"name":"OGenie 3705","traits":{"Background":"Steel Blue","Skin":"Pan","Clothing":"OG Green Hoodie","Hat":"Wreth","Accessories":"RayGun","Mouth":"You What!","Eyes":"Clubmaster Gold"}},"3706":{"name":"OGenie 3706","traits":{"Background":"Lavender","Skin":"Pan","Clothing":"Grey Stripe","Hat":"Green Splash","Accessories":"Gold Bat","Mouth":"Ginger Beard","Eyes":"Pink Round"}},"3707":{"name":"OGenie 3707","traits":{"Background":"Lavender","Skin":"Glaucus","Clothing":"Flannel Dark Red","Hat":"Olive Mullet","Accessories":"Punk Stud","Mouth":"Gold Grin","Eyes":"Cartoon"}},"3708":{"name":"OGenie 3708","traits":{"Background":"Stone","Skin":"Seshat","Clothing":"OG Green Stripe","Hat":"Black Hat","Mouth":"Black Mo","Eyes":"Black & Brown Wayfarer","Accessories":"Punk Stud"}},"3709":{"name":"OGenie 3709","traits":{"Background":"Dusty Pink","head-gear":"Crown","Skin":"Celestial Fire","Hat":"Blond Fade","Accessories":"Broken Cue","Mouth":"Grin","Eyes":"Eye Patch"}},"3710":{"name":"OGenie 3710","traits":{"Background":"Ash","Skin":"Amaterasu","Clothing":"Brown Puffer","Hat":"Locks & Comb","Accessories":"Punk Stud","Mouth":"Ohhh","Eyes":"Hollow White"}},"3711":{"name":"OGenie 3711","traits":{"Background":"Concrete","Skin":"Tartarus","Clothing":"Dark Grey Hoodie","Hat":"Ancient Helmet","Mouth":"Black Mo","Eyes":"Clubmaster Silver"}},"3712":{"name":"OGenie 3712","traits":{"Background":"Red","Skin":"Seshat","Clothing":"RUB Responsibly T","Hat":"Ginger Quiff","Mouth":"Grey Beard","Eyes":"Source Overflow OG","Accessories":"Double Gold Loop"}},"3713":{"name":"OGenie 3713","traits":{"Background":"Purple","Skin":"Celestial Tectonic","Clothing":"Gold Chain","Hat":"Black Beanie","Mouth":"Ginger Beard","Eyes":"Cartoon"}},"3714":{"name":"OGenie 3714","traits":{"Background":"Olive Green","Skin":"Celestial Eternity","Clothing":"WeAreOG Purple","Hat":"Ginger Quiff","Accessories":"Thunder Lord","Mouth":"Shmoke","Eyes":"Turtle Wayfarer"}},"3715":{"name":"OGenie Tectonic Titan","traits":{"OGenie Titan":"Tectonic Titan"}},"3716":{"name":"OGenie 3716","traits":{"Background":"Stone","Skin":"Agassou","Clothing":"PS Purple","Hat":"Blond Fade","Mouth":"RollUp","Eyes":"Cooked"}},"3717":{"name":"OGenie 3717","traits":{"Background":"Steel Blue","Skin":"Hina","Clothing":"Sweatshirt Gold OGT Chain","Hat":"Blond Bandana","Mouth":"Stubble Shmoke","Eyes":"Black Wayfarer"}},"3718":{"name":"OGenie 3718","traits":{"Background":"OG Green","Skin":"Idube","Clothing":"Brown Cord Jacket","Hat":"Horns","Accessories":"Gold Stud","Mouth":"Cigar","Eyes":"Eyes White"}},"3719":{"name":"OGenie 3719","traits":{"Background":"Hazy Blue","Skin":"Devine Earth","Clothing":"Black T Gold OGT Chain","Hat":"Blond Fade","Mouth":"Black Beard","Eyes":"Hollow White"}},"3720":{"name":"OGenie 3720","traits":{"Background":"Feudal","Skin":"Devine Fire","Clothing":"Red Track","Hat":"Dark Quiff","Mouth":"Whistle","Eyes":"Reading Round"}},"3721":{"name":"OGenie 3721","traits":{"Background":"Slate","Skin":"Apollo","Clothing":"Red Track","Hat":"Special: A long lost Flame","Accessories":"Diamond Fist","Mouth":"Ohhh","Eyes":"Black Pitviper"}},"3722":{"name":"OGenie 3722","traits":{"Background":"Dusty Blue","Skin":"Sunrise Jord","Clothing":"OG Green Puffer","Hat":"Pink Mullet","Accessories":"Light Bulb","Mouth":"Ohhh","Eyes":"Black Pitviper"}},"3723":{"name":"OGenie 3723","traits":{"Background":"OG Green","Skin":"Flora","Clothing":"Gold Chain & Black T","Accessories":"Special: LTFree","Mouth":"Grin","Eyes":"Reading Round"}},"3724":{"name":"OGenie 3724","traits":{"Background":"Stone","Skin":"Celestial Earth","Clothing":"Flannel Green","Hat":"Captain","Mouth":"Black Beard","Eyes":"Clubmaster Silver"}},"3725":{"name":"OGenie 3725","traits":{"Background":"Olive Green","Skin":"Celestial Tectonic","Clothing":"OG Green Stripe","Hat":"Fade & Horns","Mouth":"Yeeaa","Eyes":"Black Pitviper"}},"3726":{"name":"Multiverse OGenie - OSquig","traits":{"MV OGenie 1/1":"OSquig"}},"3727":{"name":"OGenie 3727","traits":{"Background":"Slate","Skin":"Apollo","Clothing":"Flannel Green","Hat":"Transparent Water Bandana","Mouth":"Grin","Eyes":"Black Wayfarer"}},"3728":{"name":"OGenie 3728","traits":{"Background":"OG Green","Skin":"Pan","Clothing":"Brown Cord Jacket","Hat":"Sushi Bandana Black","Accessories":"G-Pods","Mouth":"Grey Beard","Eyes":"Hollow White"}},"3729":{"name":"OGenie 3729","traits":{"Background":"Fog","Skin":"Celestial Air","Clothing":"White Hoodie","Hat":"Teal Splash","Accessories":"Punk Stud","Mouth":"Ginger Mo","Eyes":"Source Overflow White"}},"3730":{"name":"OGenie 3730","traits":{"Background":"Lavender","Skin":"Balor","Clothing":"Coppice Sweatshirt Green","Hat":"Pink Mullet","Mouth":"You What!","Eyes":"Cooked"}},"3731":{"name":"OGenie 3731","traits":{"Background":"Fossil","Skin":"Devine Water","Clothing":"Flannel Red","Hat":"OG Green Trucker","Mouth":"Black Mo","Eyes":"Source Overflow White"}},"3732":{"name":"OGenie 3732","traits":{"Background":"Stone","Skin":"Water Tattoo","Clothing":"Flannel Red","Hat":"Punk Blonde","Accessories":"Diamond Stud","Mouth":"G Smile","Eyes":"Black Wayfarer"}},"3733":{"name":"OGenie 3733","traits":{"Background":"Lavender","Skin":"Jord","Clothing":"Flannel Red","Hat":"Purple Splash","Accessories":"Fire Element","Mouth":"Rainbow Grin","Eyes":"Hollow Black"}},"3734":{"name":"OGenie 3734","traits":{"Background":"Concrete","Skin":"Pluto","Clothing":"Shirt & Vest","Hat":"Punk Dark","Mouth":"RollUp","Eyes":"Monocle OG"}},"3735":{"name":"OGenie 3735","traits":{"Background":"Dusty Blue","Skin":"Devine Earth","Clothing":"PS Green Flowers","Hat":"Coppice Hat","Mouth":"Cigar","Eyes":"Pink Round","Accessories":"G-Pods"}},"3736":{"name":"OGenie 3736","traits":{"Background":"OG Green","Skin":"Celestial Air","Clothing":"Prison T","Hat":"Captain","Accessories":"Glove Left","Mouth":"G Smile","Eyes":"Top G Green"}},"3737":{"name":"OGenie 3737","traits":{"Background":"Ash","Skin":"Agassou","Clothing":"Biker Vest","Hat":"Locks & Comb","Accessories":"Gold Loop","Mouth":"Grin","Eyes":"OMega Laser OG Element"}},"3738":{"name":"OGenie 3738","traits":{"Background":"Lavender","Skin":"Golden Ra","Clothing":"OG Jersey","Hat":"Peaky Black","Accessories":"Gamer","Mouth":"Cigar","Eyes":"Tech Specs"}},"3739":{"name":"OGenie 3739","traits":{"Background":"Slate","Skin":"Devine Water","Clothing":"Blue Denim Jacket","Hat":"Punk Dark","Accessories":"Storm Control","Mouth":"Black Mo","Eyes":"Hollow White"}},"3740":{"name":"OGenie 3740","traits":{"Background":"Dark Purple","Skin":"Agassou","Clothing":"OG Jersey Red","Hat":"Punk Green","Mouth":"You What!","Eyes":"Matrix"}},"3741":{"name":"OGenie 3741","traits":{"Background":"Red","Skin":"Seshat","Clothing":"Gold Chain & Black T","Hat":"Cotton Candy Mullet","Mouth":"Yeeaa","Eyes":"Source Overflow White"}},"3742":{"name":"OGenie 3742","traits":{"Background":"Concrete","Skin":"Hina","Clothing":"OG Jersey Blue","Hat":"Dark Quiff","Mouth":"Yeeaa","Eyes":"Source Overflow OG"}},"3743":{"name":"OGenie 3743","traits":{"Background":"Slate","Skin":"Devine Water","Clothing":"Black Camo Jacket","Hat":"Top Hat","Accessories":"Special: LTFree","Mouth":"Blonde Mo","Eyes":"Black & Brown Wayfarer"}},"3744":{"name":"OGenie 3744","traits":{"Background":"Hazy Blue","Skin":"Mars","Clothing":"OG Jersey","Hat":"Bucket Hat Black","Mouth":"Ginger Mo","Eyes":"Top G Green"}},"3745":{"name":"OGenie 3745","traits":{"Background":"Red","Skin":"Mars","Clothing":"Tweed Suit","Hat":"OG Green Beanie","Mouth":"Ginger Mo","Eyes":"Transparent Wayfarer"}},"3746":{"name":"OGenie 3746","traits":{"Background":"Dusty Pink","Skin":"Devine Earth","Clothing":"WeAreOGT White","Hat":"Black Quiff","Mouth":"Grey Beard","Eyes":"Reading Round White"}},"3747":{"name":"OGenie Eternity Titan","traits":{"OGenie Titan":"Eternity Titan"}},"3748":{"name":"Multiverse OGenie - OGC3PO","traits":{"MV OGenie 1/1":"OGC3PO"}},"3749":{"name":"OGenie 3749","traits":{"Background":"Ash","Skin":"Devine Earth","Clothing":"Brown Cord Jacket","Hat":"Genie Bun","Mouth":"Brown Mo","Eyes":"Transparent Wayfarer"}},"3750":{"name":"OGenie 3750","traits":{"Background":"Dark Purple","Skin":"Mars Tattoo","Clothing":"OG Jersey Red","Hat":"Horns","Accessories":"Fire Element","Mouth":"G Smile","Eyes":"Source Overflow White"}},"3751":{"name":"OGenie 3751","traits":{"Background":"Steel Blue","Skin":"OG Element","Clothing":"Black Hoodie","Hat":"Water Hair","Accessories":"Prism","Mouth":"Rainbow Grin","Eyes":"Eyes White"}},"3752":{"name":"OGenie 3752","traits":{"Background":"Dark Purple","Skin":"Flora","Clothing":"Gold Chain & Black T","Hat":"Punk Dark","Accessories":"Stardust","Mouth":"Grin","Eyes":"Turtle Wayfarer"}},"3753":{"name":"OGenie 3753","traits":{"Background":"Ash","Skin":"Devine Water","Clothing":"WeAreOG Black","Hat":"Grey Mullet","Accessories":"Crystal Orb","Mouth":"Grin","Eyes":"Matrix"}},"3754":{"name":"OGenie 3754","traits":{"Background":"Dark Purple","Skin":"Devine Fire","Clothing":"OGT Retro Track","Hat":"Fedora","Accessories":"Diamond Hand","Mouth":"G Smile","Eyes":"Cartoon"}},"3755":{"name":"Multiverse OGenie - OMecha Earth","traits":{"MV OGenie 1/1":"OMecha Earth"}},"3756":{"name":"OGenie 3756","traits":{"Background":"Concrete","Skin":"Glaucus","Clothing":"PS Green Flowers","Hat":"Curly Dark","Accessories":"Air Element","Mouth":"Blonde Mo","Eyes":"Top G Gold"}},"3757":{"name":"OGenie 3757","traits":{"Background":"Lavender","Skin":"Celestial Tectonic","Clothing":"Black Bomber","Hat":"Brown Quiff","Accessories":"RayGun","Mouth":"Stubble Shmoke","Eyes":"Hollow White"}},"3758":{"name":"OGenie 3758","traits":{"Background":"Steel Blue","Skin":"Luna","Clothing":"White Hoodie","Hat":"Blond Bandana","Accessories":"Gold Stud","Mouth":"Grey Beard","Eyes":"Bored"}},"3759":{"name":"OGenie 3759","traits":{"Background":"Lavender","Skin":"Celestial Fire","Clothing":"Black Hoodie","Hat":"OGT White Trucker","Accessories":"Gamer","Mouth":"Yeeaa","Eyes":"Turtle Wayfarer"}},"3760":{"name":"OGenie 3760","traits":{"Background":"Slate","Skin":"Golden Ra","Clothing":"Gradient Puffer","Hat":"OG Green Beanie","Accessories":"Punk Stud","Mouth":"Whistle","Eyes":"Reading Round"}},"3761":{"name":"OGenie 3761","traits":{"Background":"Slate","Skin":"Glaucus","Clothing":"Grey Stripe","Hat":"Black Visor","Accessories":"Glove Right","Mouth":"Grin","Eyes":"Bored"}},"3762":{"name":"OGenie 3762","traits":{"Background":"Tortilla","Skin":"Celestial Tectonic","Clothing":"Black Shirt OG Green Suit","Hat":"Transparent Wizard Horn","Mouth":"You What!","Eyes":"Cosmos Visor Beam"}},"3763":{"name":"OGenie 3763","traits":{"Background":"Slate","Skin":"Pluto","Clothing":"PS Red","Hat":"Dark Quiff","Accessories":"Gold Loop","Mouth":"G Smile","Eyes":"Black & Brown Wayfarer"}},"3764":{"name":"OGenie 3764","traits":{"Background":"Dusty Blue","Skin":"Tartarus","Clothing":"Flannel OG Green","Hat":"Blond Quiff","Mouth":"RollUp","Eyes":"Top G Black"}},"3765":{"name":"OGenie 3765","traits":{"Background":"Ash","Skin":"Pluto Blue Tattoo","Clothing":"JPD","Hat":"Wreth","Mouth":"Black Mo","Eyes":"Hollow Black"}},"3766":{"name":"OGenie 3766","traits":{"Background":"Slate","Skin":"Agassou","Clothing":"Flannel Green","Hat":"Sushi Bandana White","Accessories":"Broken Cue","Mouth":"Blonde Mo","Eyes":"Pink Round"}},"3767":{"name":"OGenie 3767","traits":{"Background":"Hazy Blue","Skin":"Sunrise Jord","Clothing":"Grey Hoodie","Hat":"Yellow Beanie","Mouth":"RollUp","Eyes":"Bored"}},"3768":{"name":"OGenie 3768","traits":{"Background":"Fossil","Skin":"Celestial Eternity","Clothing":"OG-Unit Vest","Hat":"Grey Kasa","Accessories":"Black Bat","Mouth":"Gold Grin","Eyes":"Bored"}},"3769":{"name":"OGenie 3769","traits":{"Background":"Stone","Skin":"Agassou","Clothing":"Retro Track Purple","Hat":"Bucket Hat Olive","Accessories":"RayGun","Mouth":"Black Beard","Eyes":"Top G Black"}},"3770":{"name":"OGenie 3770","traits":{"Background":"Slate","Skin":"Sunrise Balor","Clothing":"Black Denim Jacket","Hat":"Clear Bandana","Accessories":"RayGun","Mouth":"Ginger Beard","Eyes":"Clubmaster Gold"}},"3771":{"name":"OGenie 3771","traits":{"Background":"Concrete","Skin":"Flora","Clothing":"Grey Hoodie","Hat":"Pink Mullet","Mouth":"Ginger Mo","Eyes":"Top G Gold"}},"3772":{"name":"OGenie 3772","traits":{"Background":"Dark Purple","Skin":"Mars","Clothing":"Blue Denim Jacket","Hat":"Green Splash","Accessories":"Gold Ring & Bracelet","Mouth":"RollUp","Eyes":"Hollow White"}},"3773":{"name":"Multiverse OGenie - OForca","traits":{"MV OGenie 1/1":"OForca"}},"3774":{"name":"OGenie 3774","traits":{"Background":"Hazy Blue","Skin":"Devine Fire","Clothing":"Flannel Dark Red","Hat":"Black Bandana","Mouth":"Yeeaa","Eyes":"Source Overflow White"}},"3775":{"name":"OGenie 3775","traits":{"Background":"Hazy Blue","Skin":"OG Element Tattoo","Clothing":"OMG T","Hat":"Black Beanie","Accessories":"Double Gold Loop","Mouth":"Grin","Eyes":"OG Wayfarer"}},"3776":{"name":"OGenie 3776","traits":{"Background":"Lavender","Skin":"Seshat","Clothing":"White T Gold Chain","Hat":"BW Cap Red","Accessories":"Flame Control","Mouth":"Whistle","Eyes":"Eyes White"}},"3777":{"name":"OGenie 3777","traits":{"Background":"Lavender","Skin":"Devine Earth","Clothing":"WeAreOG Black","Hat":"OGT White Trucker","Mouth":"Blonde Mo","Eyes":"Top G Green"}},"3778":{"name":"OGenie 3778","traits":{"Background":"Red","Skin":"Tartarus","Clothing":"J Hoodie","Hat":"Yellow Beanie","Accessories":"Gold Axe","Mouth":"G Smile","Eyes":"Source Overflow Black"}},"3779":{"name":"OGenie 3779","traits":{"Background":"Dusty Blue","Skin":"Sunrise Balor","Clothing":"Brown Cord Jacket","Hat":"Blond Bandana","Mouth":"Black Beard","Eyes":"OG Wayfarer"}},"3780":{"name":"OGenie 3780","traits":{"Background":"Dark Purple","Skin":"Seshat","Clothing":"OGT Retro Track","Hat":"Peaky Brown","Mouth":"Ginger Mo","Eyes":"Reading Round"}},"3781":{"name":"OGenie 3781","traits":{"Background":"Fog","Skin":"Luna","Clothing":"OG Jersey Blue","Hat":"Sushi Bandana White","Accessories":"Molecule Control","Mouth":"Grin","Eyes":"Cartoon"}},"3782":{"name":"OGenie 3782","traits":{"Background":"Dark Purple","Skin":"Devine Earth","Clothing":"RUB Responsibly T","Hat":"Grey Kasa","Accessories":"Gold Loop","Mouth":"Toothpick","Eyes":"Top G Green"}},"3783":{"name":"OGenie 3783","traits":{"Background":"Dusty Blue","Skin":"Jord","Clothing":"Special: Space Riding Suit","Hat":"Black Hat","Accessories":"Gold Loop","Mouth":"Grin","Eyes":"3D Glasses"}},"3784":{"name":"Multiverse OGenie - OQuacker","traits":{"MV OGenie 1/1":"OQuacker"}},"3785":{"name":"OGenie 3785","traits":{"Background":"Dark Purple","Skin":"Pan Tattoo","Clothing":"OGT Black Track","Hat":"Turquoise Mullet","Mouth":"You What!","Eyes":"Cooked"}},"3786":{"name":"OGenie 3786","traits":{"Background":"Dusty Pink","Skin":"Devine Earth","Clothing":"Gradient Puffer","Hat":"BW Cap Red","Mouth":"Brown Mo","Eyes":"Source Overflow White","Accessories":"Punk Stud"}},"3787":{"name":"OGenie 3787","traits":{"Background":"Red","Skin":"Hina","Clothing":"Dark Grey Hoodie","Hat":"Wreth","Accessories":"Beer Bottle","Mouth":"Whistle","Eyes":"Top G Gold"}},"3788":{"name":"OGenie 3788","traits":{"Background":"Ash","Skin":"Luna","Clothing":"PS Beige","Hat":"Blonde Mullet","Mouth":"You What!","Eyes":"Meme"}},"3789":{"name":"OGenie 3789","traits":{"Background":"Lavender","Skin":"Pan","Clothing":"Army Jacket","Hat":"Blonde Quiff","Mouth":"Grey Beard","Eyes":"Eyes White"}},"3790":{"name":"OGenie 3790","traits":{"Background":"Dusty Blue","Skin":"Celestial Eternity","Clothing":"Grey Hoodie","Hat":"Earth Hair","Accessories":"Gold Bat","Mouth":"Ginger Mo","Eyes":"Black Pitviper"}},"3791":{"name":"OGenie 3791","traits":{"Background":"Ash","Skin":"Balor","Clothing":"OG Jersey Blue","Hat":"BW Cap Black & OG Green","Accessories":"Coffee OGm","Mouth":"Yeeaa","Eyes":"Tech Specs"}},"3792":{"name":"OGenie 3792","traits":{"Background":"Fossil","Skin":"Devine Earth","Clothing":"Black Denim Jacket","Hat":"Orange Beanie","Accessories":"Wooden Bat","Mouth":"Grin","Eyes":"Black & Brown Wayfarer"}},"3793":{"name":"OGenie 3793","traits":{"Background":"Lavender","Skin":"Amaterasu","Clothing":"WeAreOG Black","Hat":"Special: A long lost Flame","Mouth":"Black Beard","Eyes":"Top G Black"}},"3794":{"name":"OGenie 3794","traits":{"Background":"Lavender","Skin":"Luna","Clothing":"OG Jersey Red","Hat":"Black Quiff","Accessories":"Gamer","Mouth":"Grey Beard","Eyes":"Monocle OG"}},"3795":{"name":"OGenie 3795","traits":{"Background":"Fossil","Skin":"Mars","Clothing":"Prison T","Hat":"OG Green Beanie","Mouth":"Grey Beard","Eyes":"Black Pitviper","Accessories":"Gold Stud"}},"3796":{"name":"OGenie 3796","traits":{"Background":"Slate","Skin":"Flora","Clothing":"OG Jersey Red","Hat":"Blond Quiff","Mouth":"Stubble Shmoke","Eyes":"Bored","Accessories":"G-Pods"}},"3797":{"name":"OGenie 3797","traits":{"Background":"Olive Green","head-gear":"Smoke Halo","Skin":"Bast","Clothing":"Tweed Suit","Mouth":"Ginger Beard","Eyes":"Tech Specs"}},"3798":{"name":"OGenie 3798","traits":{"Background":"Dusty Pink","Skin":"Jord","Clothing":"Dark Grey Hoodie","Hat":"Grey Kasa","Accessories":"Coffee OGm","Mouth":"Black Mo","Eyes":"Cooked"}},"3799":{"name":"OGenie 3799","traits":{"Background":"Stone","Skin":"Pluto Blue Tattoo","Clothing":"PS Green Flowers","Hat":"OG Green Beanie","Accessories":"Katana Silver","Mouth":"Brown Mo","Eyes":"Round Black"}},"3800":{"name":"OGenie 3800","traits":{"Background":"Ash","Skin":"Mars","Clothing":"Gradient Puffer","Hat":"Grey Mullet","Mouth":"Yeeaa","Eyes":"Cooked"}},"3801":{"name":"OGenie 3801","traits":{"Background":"Fossil","Skin":"Mars","Clothing":"OG Jersey","Hat":"Ginger Curls","Accessories":"Diamond Fist","Mouth":"Yeeaa","Eyes":"OMega Laser OG Element"}},"3802":{"name":"OGenie 3802","traits":{"Background":"Slate","Skin":"Jord","Clothing":"Black Shirt OG Green Suit","Hat":"Grey Kasa","Mouth":"G Smile","Eyes":"Source Overflow White"}},"3803":{"name":"OGenie 3803","traits":{"Background":"Slate","Skin":"Mars","Hat":"Brown Quiff","Mouth":"Ohhh","Eyes":"Black & Brown Wayfarer"}},"3804":{"name":"OGenie 3804","traits":{"Background":"Hazy Blue","Skin":"Fujin","Clothing":"Coppice Sweatshirt White","Hat":"Locks & Comb","Accessories":"Baseball Glove & Ball","Mouth":"Black Mo","Eyes":"Eye Patch"}},"3805":{"name":"OGenie 3805","traits":{"Background":"Concrete","Skin":"Pan","Clothing":"OG-Unit Vest","Hat":"Water Hair","Mouth":"Toothpick","Eyes":"Blue Visor Beam"}},"3806":{"name":"OGenie 3806","traits":{"Background":"Dusty Blue","Skin":"Pluto Dark Tattoo","Clothing":"White Hoodie","Hat":"Punk Red","Mouth":"Ginger Mo","Eyes":"Eyes White"}},"3807":{"name":"OGenie 3807","traits":{"Background":"Hazy Blue","Skin":"Hina","Clothing":"OG Green Stripe","Hat":"Green Splash","Accessories":"Pizza","Mouth":"You What!","Eyes":"Black Pitviper"}},"3808":{"name":"OGenie 3808","traits":{"Background":"Tortilla","Skin":"Balor Tattoo","Clothing":"Black Shirt OG Green Suit","Mouth":"Toothpick","Eyes":"Top G Black","Accessories":"Gold Loop"}},"3809":{"name":"OGenie 3809","traits":{"Background":"Lavender","Skin":"Glaucus Tattoo","Clothing":"OG Green Stripe","Hat":"Olive Helmet","Accessories":"Prism","Mouth":"You What!","Eyes":"Source Overflow White"}},"3810":{"name":"OGenie 3810","traits":{"Background":"Olive Green","Skin":"Amaterasu","Clothing":"WeAreOG Black","Hat":"Grey Mullet","Mouth":"Yeeaa","Eyes":"OMega Laser OG Element"}},"3811":{"name":"OGenie 3811","traits":{"Background":"Lavender","Skin":"Celestial Fire","Clothing":"Black Puffer","Accessories":"Gold Loop","Mouth":"Stubble Shmoke","Eyes":"Top G Black"}},"3812":{"name":"OGenie 3812","traits":{"Background":"Red","Skin":"Tartarus","Clothing":"Grey Suit Black Tie","Hat":"Teal Splash","Mouth":"Grey Beard","Eyes":"Round Black"}},"3813":{"name":"OGenie 3813","traits":{"Background":"Dusty Pink","Skin":"Pluto Dark Tattoo","Clothing":"Olive Jacket","Hat":"Blue Bandana","Accessories":"Sword","Mouth":"Black Beard","Eyes":"Eye Patch"}},"3814":{"name":"OGenie 3814","traits":{"Background":"Lavender","head-gear":"Crown","Skin":"Fujin","Clothing":"OG Green Stripe","Hat":"Blond Quiff","Accessories":"Wooden Bat","Mouth":"Grey Beard","Eyes":"Cooked"}},"3815":{"name":"OGenie 3815","traits":{"Background":"Stone","Skin":"Jord","Clothing":"Army Jacket","Hat":"Black Quiff","Mouth":"Grey Beard","Eyes":"Hollow White","Accessories":"Gold Stud"}},"3816":{"name":"OGenie 3816","traits":{"Background":"Hazy Blue","Skin":"Flora","Clothing":"White T Gold Chain","Hat":"Wreth","Accessories":"Diamond Stud","Mouth":"Ginger Beard","Eyes":"Source Overflow White"}},"3817":{"name":"OGenie 3817","traits":{"Background":"Dusty Blue","Skin":"Jord","Clothing":"Grey Stripe","Hat":"Blond Bandana","Mouth":"Black Mo","Eyes":"OMega Laser Red"}},"3818":{"name":"OGenie 3818","traits":{"Background":"Lavender","Skin":"Glaucus","Clothing":"Shirt & Vest","Hat":"Punk Red","Accessories":"Black Bat","Mouth":"Blonde Mo","Eyes":"Meme"}},"3819":{"name":"OGenie 3819","traits":{"Background":"Fossil","Skin":"Devine Water","Clothing":"OG Jersey Blue","Hat":"BW Cap Red","Mouth":"Whistle","Eyes":"Black & Brown Wayfarer"}},"3820":{"name":"OGenie 3820","traits":{"Background":"Steel Blue","Skin":"Idube","Clothing":"PS Purple & OG Green","Hat":"Punk Blonde","Accessories":"Storm Fist","Mouth":"Ginger Beard","Eyes":"Top G Black"}},"3821":{"name":"OGenie 3821","traits":{"Background":"Purple","Skin":"Flora","Clothing":"PS Purple & OG Green","Hat":"OG Green Beanie","Accessories":"G-Pods","Mouth":"G Smile","Eyes":"Clubmaster Silver"}},"3822":{"name":"OGenie 3822","traits":{"Background":"Red","Skin":"Golden Ra","Clothing":"WeAreOGT White","Hat":"Black Kasa","Accessories":"Wooden Bat","Mouth":"You What!","Eyes":"Source Overflow Black"}},"3823":{"name":"OGenie 3823","traits":{"Background":"Slate","Skin":"Flora","Clothing":"Red Track","Hat":"Black Bandana","Accessories":"Katana Gold","Mouth":"Gold Grin","Eyes":"Cosmos Visor Beam"}},"3824":{"name":"OGenie 3824","traits":{"Background":"Olive Green","Skin":"Pan","Clothing":"Olive Jacket","Hat":"Dark Quiff","Mouth":"Grey Beard","Eyes":"Source Overflow Black"}},"3825":{"name":"OGenie 3825","traits":{"Background":"Steel Blue","Skin":"Flora","Clothing":"PS Green Flowers","Hat":"Punk Blonde","Accessories":"Beer Bottle","Mouth":"Stubble Shmoke","Eyes":"Eyes White"}},"3826":{"name":"OGenie 3826","traits":{"Background":"Steel Blue","Skin":"Celestial Eternity","Clothing":"Shirt & Vest","Hat":"Dark Quiff","Accessories":"Gamer","Mouth":"Stubble Shmoke","Eyes":"Tech Specs"}},"3827":{"name":"OGenie 3827","traits":{"Background":"Fossil","Skin":"Devine Water","Clothing":"WeAreOG Purple","Hat":"Fedora","Mouth":"Stubble Shmoke","Eyes":"OMega Laser OG Element","Accessories":"Double Gold Loop"}},"3828":{"name":"OGenie 3828","traits":{"Background":"Fossil","Skin":"Devine Fire","Clothing":"OMG T","Hat":"Fire Bun","Mouth":"Black Beard","Eyes":"Black Pitviper"}},"3829":{"name":"OGenie 3829","traits":{"Background":"Fossil","Skin":"Pan","Clothing":"OGT Gold Chain","Hat":"Fedora","Accessories":"Gold Stud","Mouth":"G Smile","Eyes":"Black Wayfarer"}},"3830":{"name":"OGenie 3830","traits":{"Background":"Stone","head-gear":"Dark Crown","Skin":"Amaterasu","Clothing":"Navy Track Jacket","Hat":"Fade","Accessories":"SC Cocktail","Mouth":"Toothpick","Eyes":"Round Black"}},"3831":{"name":"OGenie 3831","traits":{"Background":"Hazy Blue","Skin":"Luna","Clothing":"Army Jacket","Hat":"Special: Quirk Knight","Accessories":"G-Pods","Mouth":"Ginger Mo","Eyes":"Hollow Black"}},"3832":{"name":"OGenie 3832","traits":{"Background":"Stone","Skin":"Golden Ra","Clothing":"Grey Hoodie","Hat":"Teal Splash","Mouth":"Blonde Mo","Eyes":"Source Overflow OG"}},"3833":{"name":"OGenie 3833","traits":{"Background":"Slate","Skin":"Pluto Dark Tattoo","Clothing":"OMG T","Hat":"Fade","Accessories":"G-Pods","Mouth":"Rainbow Grin","Eyes":"Monocle OG"}},"3834":{"name":"OGenie 3834","traits":{"Background":"Lavender","Skin":"Celestial Eternity","Clothing":"Black Hoodie","Accessories":"Water Fist","Mouth":"G Smile","Eyes":"OMega Laser Blue"}},"3835":{"name":"OGenie 3835","traits":{"Background":"Dark Purple","Skin":"Balor","Clothing":"OG Green Puffer","Hat":"Peaky Brown","Mouth":"Grin","Eyes":"Source Overflow Black"}},"3836":{"name":"OGenie 3836","traits":{"Background":"Lavender","Skin":"Flora","Clothing":"White T Gold Chain","Hat":"BW Cap Black","Mouth":"Ohhh","Eyes":"OG Round"}},"3837":{"name":"OGenie 3837","traits":{"Background":"Concrete","Skin":"Agassou","Clothing":"OGT Retro Track","Hat":"Punk Red","Accessories":"Katana Gold","Mouth":"Shmoke","Eyes":"Black Pitviper"}},"3838":{"name":"OGenie 3838","traits":{"Background":"Steel Blue","Skin":"Glaucus Tattoo","Clothing":"Black Hoodie","Hat":"Punk Blonde","Mouth":"Toothpick","Eyes":"Reading Round","Accessories":"Punk Stud"}},"3839":{"name":"OGenie 3839","traits":{"Background":"Stone","Skin":"Tartarus","Clothing":"Coppice Sweatshirt Green","Hat":"Horns","Mouth":"Ginger Mo","Eyes":"Top G Black"}},"3840":{"name":"OGenie 3840","traits":{"Background":"Dusty Blue","Skin":"Amaterasu","Clothing":"Black Puffer","Hat":"Blonde Quiff","Accessories":"Double Gold Loop","Mouth":"You What!","Eyes":"Matrix"}},"3841":{"name":"OGenie 3841","traits":{"Background":"Steel Blue","Skin":"Bast","Clothing":"OMG T","Hat":"Grey Balaclava","Accessories":"Flower Power","Mouth":"Cigar","Eyes":"Clubmaster Silver"}},"3842":{"name":"OGenie 3842","traits":{"Background":"Slate","Skin":"Bast","Clothing":"WeAreOGT White","Hat":"Blond Quiff","Mouth":"G Smile","Eyes":"Transparent Wayfarer"}},"3843":{"name":"OGenie 3843","traits":{"Background":"Red","Skin":"Bast","Clothing":"OG Jersey Blue","Accessories":"Punk Stud","Mouth":"Black Beard","Eyes":"Pink Round"}},"3844":{"name":"OGenie 3844","traits":{"Background":"Red","Skin":"Luna","Clothing":"OG Jersey Red","Hat":"Brown Quiff","Mouth":"Cigar","Eyes":"Meme"}},"3845":{"name":"OGenie 3845","traits":{"Background":"Concrete","Skin":"Devine Earth","Clothing":"WeAreOG Black","Hat":"Black Visor","Mouth":"Toothpick","Eyes":"Clubmaster Silver"}},"3846":{"name":"OGenie 3846","traits":{"Background":"Red","Skin":"Hina","Clothing":"Blue Stripe","Hat":"Black Mullet","Accessories":"Beer Bottle","Mouth":"Brown Mo","Eyes":"Orange Pitvipers"}},"3847":{"name":"OGenie 3847","traits":{"Background":"Red","Skin":"Raijin","Clothing":"PS Green Flowers","Hat":"Hot Pink Fade","Mouth":"Black Beard","Eyes":"Eyes White"}},"3848":{"name":"OGenie 3848","traits":{"Background":"Dusty Pink","Skin":"Water Tattoo","Clothing":"OG Jersey Blue","Hat":"Dark Quiff","Mouth":"Ginger Beard","Eyes":"Reading Round"}},"3849":{"name":"OGenie 3849","traits":{"Background":"Fog","Skin":"Devine Water","Clothing":"OG Jersey Blue","Hat":"Blond Bandana","Accessories":"Punk Stud","Mouth":"Whistle","Eyes":"Clubmaster Gold"}},"3850":{"name":"OGenie 3850","traits":{"Background":"Fossil","Skin":"Pluto","Hat":"Black Quiff","Accessories":"Gold Stud","Mouth":"Toothpick","Eyes":"Matrix"}},"3851":{"name":"Multiverse OGenie - OSsos","traits":{"MV OGenie 1/1":"OSsos"}},"3852":{"name":"OGenie 3852","traits":{"Background":"Lavender","Skin":"Amaterasu","Clothing":"Flannel Dark Red","Hat":"Fire Bun","Mouth":"Black Beard","Eyes":"Hollow Black","Accessories":"Gold Loop"}},"3853":{"name":"OGenie 3853","traits":{"Background":"Hazy Blue","Skin":"Devine Fire","Clothing":"WeAreOGT White","Hat":"Fade & Horns","Mouth":"Rainbow Grin","Eyes":"Turtle Wayfarer"}},"3854":{"name":"OGenie 3854","traits":{"Background":"Concrete","Skin":"Pluto Blue Tattoo","Clothing":"OG Jersey","Hat":"Olive Helmet","Accessories":"Double Gold Loop","Mouth":"Rainbow Grin","Eyes":"Hollow Black"}},"3855":{"name":"OGenie 3855","traits":{"Background":"Hazy Blue","Skin":"Devine Water","Clothing":"Jail T","Hat":"Dark Quiff","Accessories":"G-Pods","Mouth":"Stubble Shmoke","Eyes":"Bubblegum Pitvipers"}},"3856":{"name":"OGenie 3856","traits":{"Background":"Stone","Skin":"Balor","Clothing":"OG Jersey Dark","Hat":"Rose Dust Mullet","Mouth":"Grey Beard","Eyes":"Matrix","Accessories":"Gold Stud"}},"3857":{"name":"OGenie 3857","traits":{"Background":"Tortilla","Skin":"Pan","Clothing":"OG Jersey Red","Hat":"Blond Fade","Accessories":"Molecule Control","Mouth":"Black Mo","Eyes":"Meme"}},"3858":{"name":"OGenie 3858","traits":{"Background":"Lavender","Skin":"Jord","Clothing":"White Hoodie","Hat":"Red Beanie","Mouth":"Ginger Mo","Eyes":"Blue Visor Beam","Accessories":"Gold Loop"}},"3859":{"name":"OGenie 3859","traits":{"Background":"Feudal.PNG","Skin":"Flora","Clothing":"PS Grey","Hat":"Pink Mullet","Mouth":"Yeeaa","Eyes":"Pink Round"}},"3860":{"name":"OGenie 3860","traits":{"Background":"Fossil","Skin":"Mars","Clothing":"Black Bomber","Hat":"Bucket Hat Olive","Mouth":"Ginger Beard","Eyes":"Bubblegum Pitvipers"}},"3861":{"name":"OGenie 3861","traits":{"Background":"Slate","Skin":"Raijin","Clothing":"WeAreOG Purple","Hat":"Ginger Quiff","Mouth":"Black Beard","Eyes":"Round Black"}},"3862":{"name":"OGenie 3862","traits":{"Background":"Tortilla","Skin":"Seshat","Clothing":"Flannel Red","Hat":"Ginger Quiff","Accessories":"Storm Control","Mouth":"Rainbow Grin","Eyes":"Clubmaster Silver"}},"3863":{"name":"OGenie 3863","traits":{"Background":"Lavender","Skin":"Jord","Clothing":"Black Hoodie","Hat":"Blue Splash Crew","Accessories":"SC Cocktail","Mouth":"You What!","Eyes":"Bubblegum Pitvipers"}},"3864":{"name":"OGenie 3864","traits":{"Background":"Concrete","Skin":"Jord","Clothing":"Black Bomber","Hat":"Grey Balaclava","Accessories":"Beer Bottle","Mouth":"Grin","Eyes":"Transparent Wayfarer"}},"3865":{"name":"OGenie 3865","traits":{"Background":"Stone","Skin":"Flora","Clothing":"Prison T","Hat":"Clear Bandana","Accessories":"Double Gold Loop","Mouth":"Toothpick","Eyes":"OG Wayfarer"}},"3866":{"name":"OGenie 3866","traits":{"Background":"Olive Green","Skin":"Pluto","Clothing":"OG Green T","Hat":"Turquoise Mullet","Mouth":"Grey Beard","Eyes":"Bubblegum Pitvipers"}},"3867":{"name":"OGenie 3867","traits":{"Background":"Red","Skin":"Celestial Tectonic","Clothing":"Dark Grey Hoodie","Hat":"Genie Bun","Mouth":"Grey Beard","Eyes":"Eye Patch"}},"3868":{"name":"OGenie 3868","traits":{"Background":"Steel Blue","Skin":"Jord","Clothing":"Flannel Dark Red","Hat":"Turquoise Mullet","Mouth":"Grin","Eyes":"OG Round"}},"3869":{"name":"OGenie 3869","traits":{"Background":"Ash","Skin":"Jord","Clothing":"WeAreOGT White","Hat":"Red Balaclava","Accessories":"Special: Ghost Orb","Mouth":"Yeeaa","Eyes":"Top G Green"}},"3870":{"name":"OGenie 3870","traits":{"Background":"Red","Skin":"Pan","Clothing":"OG-Unit T & Gold Chain","Hat":"Clear Bandana","Mouth":"Brown Mo","Eyes":"Source Overflow White","Accessories":"Gold Loop"}},"3871":{"name":"OGenie 3871","traits":{"Background":"Red","Skin":"Devine Fire","Clothing":"WeAreOGT White","Hat":"Bucket Hat Black","Mouth":"Ginger Mo","Eyes":"Source Overflow Black"}},"3872":{"name":"OGenie 3872","traits":{"Background":"Red","Skin":"Jord","Clothing":"Flannel OG Green","Hat":"BW Cap Red","Accessories":"G-Pods","Mouth":"Blonde Mo","Eyes":"Eyes White"}},"3873":{"name":"OGenie 3873","traits":{"Background":"Red","Skin":"Pluto Dark Tattoo","Clothing":"Grey Suit Black Tie","Hat":"Ginger Mullet","Mouth":"Ginger Beard","Eyes":"Hollow Black"}},"3874":{"name":"OGenie 3874","traits":{"Background":"Slate","Skin":"Luna","Clothing":"Brown Cord Jacket","Hat":"Fedora","Mouth":"Black Mo","Eyes":"OG Round"}},"3875":{"name":"OGenie 3875","traits":{"Background":"Lavender","Skin":"Mars","Clothing":"Red Shozoku","Hat":"Horns","Accessories":"Baseball Glove & Ball","Mouth":"Stubble Shmoke","Eyes":"Clubmaster Gold"}},"3876":{"name":"OGenie 3876","traits":{"Background":"Stone","Skin":"Glaucus Tattoo","Clothing":"Grey Stripe","Hat":"Hot Pink Fade","Mouth":"Grin","Eyes":"Transparent Pitvipers","Accessories":"Gold Stud"}},"3877":{"name":"OGenie 3877","traits":{"Background":"Dusty Blue","Skin":"Seshat","Clothing":"PS Green Flowers","Hat":"Grey Mullet","Accessories":"Storm Fist","Mouth":"Stubble Shmoke","Eyes":"OG Wayfarer"}},"3878":{"name":"OGenie 3878","traits":{"Background":"Feudal","Skin":"Pluto Blue Tattoo","Clothing":"Spartan Cloak","Hat":"Grey Quiff","Accessories":"Punk Stud","Mouth":"Black Beard","Eyes":"Bubblegum Pitvipers"}},"3879":{"name":"OGenie 3879","traits":{"Background":"Fossil","Skin":"Fujin","Clothing":"Black T Gold OGT Chain","Hat":"Ginger Mullet","Mouth":"Grey Beard","Eyes":"Black Pitviper","Accessories":"Double Gold Loop"}},"3880":{"name":"OGenie 3880","traits":{"Background":"Fossil","Skin":"Seshat","Clothing":"Grey Stripe","Hat":"Fade & Horns","Accessories":"Gold Bracelet & Ring","Mouth":"Blonde Mo","Eyes":"Pink Round"}},"3881":{"name":"OGenie 3881","traits":{"Background":"Purple","Skin":"Flora","Hat":"Black Kasa","Accessories":"Katana Gold","Mouth":"Black Mo","Eyes":"Clubmaster Silver"}},"3882":{"name":"OGenie 3882","traits":{"Background":"Steel Blue","Skin":"Devine Earth","Clothing":"Black Shirt OG Green Suit","Hat":"Olive Mullet","Mouth":"Grey Beard","Eyes":"Black Wayfarer"}},"3883":{"name":"OGenie 3883","traits":{"Background":"Dark Purple","Skin":"Raijin","Clothing":"Black Hoodie","Hat":"Blond Fade","Accessories":"Gold Loop","Mouth":"Yeeaa","Eyes":"Black Wayfarer"}},"3884":{"name":"OGenie 3884","traits":{"Background":"Concrete","Skin":"Agassou","Clothing":"Olive Jacket","Hat":"Red Beanie","Mouth":"Ohhh","Eyes":"Storm","Accessories":"Punk Stud"}},"3885":{"name":"OGenie 3885","traits":{"Background":"Red","Skin":"Flora","Clothing":"Grey Hoodie","Hat":"Olive Mullet","Accessories":"Gold Loop","Mouth":"Ginger Beard","Eyes":"Cartoon"}},"3886":{"name":"OGenie 3886","traits":{"Background":"Dusty Pink","Skin":"Mars","Clothing":"Sweatshirt Gold OGT Chain","Hat":"Black Hat","Accessories":"Diamond Stud","Mouth":"Grey Beard","Eyes":"Meme"}},"3887":{"name":"OGenie 3887","traits":{"Background":"Lavender","Skin":"Glaucus Tattoo","Clothing":"Black Suit","Hat":"Yellow Beanie","Mouth":"Yeeaa","Eyes":"Clubmaster Silver"}},"3888":{"name":"OGenie 3888","traits":{"Background":"Red","Skin":"Pluto Dark Tattoo","Clothing":"Sweatshirt Gold OGT Chain","Hat":"Ancient Helmet","Mouth":"Grey Beard","Eyes":"Pink Round"}},"3889":{"name":"OGenie 3889","traits":{"Background":"Fog","Skin":"Luna","Clothing":"OG Jersey Red","Hat":"OGT White Trucker","Mouth":"Ginger Beard","Eyes":"Hollow White"}},"3890":{"name":"OGenie 3890","traits":{"Background":"Ash","Skin":"Balor","Clothing":"Black Bomber","Hat":"Black Kasa","Accessories":"Molecule Control","Mouth":"Ginger Beard","Eyes":"Top G Black"}},"3891":{"name":"OGenie 3891","traits":{"Background":"Fog","Skin":"Balor OG Tattoo","Clothing":"Biker Vest","Hat":"Blond Bandana","Accessories":"Broken Cue","Mouth":"G Smile","Eyes":"Bored"}},"3892":{"name":"OGenie 3892","traits":{"Background":"OG Green","Skin":"Glaucus","Hat":"Punk Blonde","Accessories":"Gold Stud","Mouth":"G Smile","Eyes":"OG Round"}},"3893":{"name":"OGenie 3893","traits":{"Background":"Stone","Skin":"Luna","Clothing":"Sweatshirt Gold OGT Chain","Hat":"Captain","Mouth":"Grin","Eyes":"Orange Pitvipers"}},"3894":{"name":"OGenie 3894","traits":{"Background":"Steel Blue","Skin":"Celestial Cosmos","Clothing":"OGT Black Track","Hat":"Fade","Mouth":"Black Mo","Eyes":"Source Overflow OG"}},"3895":{"name":"Multiverse OGenie - OSkelly","traits":{"MV OGenie 1/1":"OSkelly"}},"3896":{"name":"OGenie 3896","traits":{"Background":"Steel Blue","Skin":"Pan","Clothing":"Gold Chain","Hat":"Blond Bandana","Mouth":"G Smile","Eyes":"Top G Black"}},"3897":{"name":"OGenie 3897","traits":{"Background":"Dark Purple","Skin":"Devine Fire","Clothing":"Flannel Green","Hat":"Punk Blonde","Mouth":"You What!","Eyes":"Top G Gold"}},"3898":{"name":"OGenie 3898","traits":{"Background":"Dusty Blue","Skin":"Pan","Clothing":"WeAreOG Black","Hat":"Grey Mullet","Mouth":"Grin","Eyes":"Top G Gold"}},"3899":{"name":"OGenie 3899","traits":{"Background":"Fog","Skin":"Sunrise Hina","Clothing":"Grey Hoodie","Hat":"Grey Quiff","Mouth":"Grey Beard","Eyes":"Hollow White"}},"3900":{"name":"OGenie 3900","traits":{"Background":"Purple","Skin":"Bast","Clothing":"OG Jersey Dark","Hat":"Purple Splash","Mouth":"Brown Mo","Eyes":"Orange Pitvipers"}},"3901":{"name":"OGenie 3901","traits":{"Background":"Olive Green","Skin":"Hina","Clothing":"Dark Grey Hoodie","Hat":"Grey Mullet","Accessories":"Wooden Bat","Mouth":"Ohhh","Eyes":"Black Pitviper"}},"3902":{"name":"OGenie 3902","traits":{"Background":"Hazy Blue","Skin":"Pluto Blue Tattoo","Clothing":"Black Hoodie","Hat":"Blond Bandana","Mouth":"Toothpick","Eyes":"Eye Patch"}},"3903":{"name":"OGenie 3903","traits":{"Background":"Feudal","Skin":"Golden Ra","Clothing":"Blue Denim Jacket","Hat":"Fedora","Mouth":"Ginger Mo","Eyes":"Source Overflow OG"}},"3904":{"name":"OGenie 3904","traits":{"Background":"Fog","Skin":"Celestial Earth","Clothing":"PS Purple & OG Green","Hat":"Teal Splash","Accessories":"Double Gold Loop","Mouth":"Ginger Beard","Eyes":"Top G Green"}},"3905":{"name":"OGenie 3905","traits":{"Background":"Stone","Skin":"Glaucus Tattoo","Clothing":"OG Jersey Red","Hat":"Pink Bandana","Mouth":"Toothpick","Eyes":"Black Pitviper"}},"3906":{"name":"OGenie 3906","traits":{"Background":"Ash","Skin":"Seshat","Clothing":"Black T Gold OGT Chain","Hat":"Black Kasa","Accessories":"Gold Loop","Mouth":"Grin","Eyes":"Eye Patch"}},"3907":{"name":"OGenie 3907","traits":{"Background":"Lavender","Skin":"Pluto Dark Tattoo","Clothing":"PS Beige","Hat":"Wreth","Accessories":"Gold Loop","Mouth":"Gold Grin","Eyes":"Eye Patch"}},"3908":{"name":"OGenie 3908","traits":{"Background":"Purple","Skin":"Jord","Clothing":"PS Green Flowers","Hat":"Coppice Hat","Mouth":"Blonde Mo","Eyes":"Pink Round"}},"3909":{"name":"OGenie 3909","traits":{"Background":"Stone","Skin":"Devine Earth","Clothing":"OG Green Stripe","Hat":"Blond Bandana","Mouth":"You What!","Eyes":"Matrix"}},"3910":{"name":"OGenie 3910","traits":{"Background":"Purple","Skin":"Agassou","Clothing":"Black Shirt OG Green Suit","Hat":"Punk Pink","Accessories":"SC Cocktail","Mouth":"Toothpick","Eyes":"Orange Pitvipers"}},"3911":{"name":"OGenie 3911","traits":{"Background":"Lavender","Skin":"Flora","Clothing":"RUB Responsibly T","Hat":"Black Beanie","Accessories":"Flame Control","Mouth":"You What!","Eyes":"Round Black"}},"3912":{"name":"OGenie 3912","traits":{"Background":"Steel Blue","Skin":"Devine Fire","Clothing":"Red Leather Jacket","Hat":"Black Bandana","Accessories":"Earth Element","Mouth":"Rainbow Grin","Eyes":"Matrix"}},"3913":{"name":"OGenie 3913","traits":{"Background":"Concrete","Skin":"Devine Fire","Clothing":"OGT Retro Track","Hat":"Punk Pink","Accessories":"Coffee Mug","Mouth":"You What!","Eyes":"Black Wayfarer"}},"3914":{"name":"OGenie 3914","traits":{"Background":"Slate","Skin":"Devine Water","Clothing":"Biker Vest","Hat":"OG Green Fade","Accessories":"Gold Ring & Bracelet","Mouth":"Grin","Eyes":"OMega Laser OG Element"}},"3915":{"name":"OGenie 3915","traits":{"Background":"Hazy Blue","Skin":"Devine Water","Hat":"Locks & Comb","Accessories":"Storm Fist","Mouth":"G Smile","Eyes":"Bored"}},"3916":{"name":"OGenie 3916","traits":{"Background":"Ash","Skin":"Seshat","Clothing":"Black Hoodie","Hat":"OG Green Balaclava","Accessories":"Baseball Glove & Ball","Mouth":"Yeeaa","Eyes":"Eye Patch"}},"3917":{"name":"OGenie 3917","traits":{"Background":"Lavender","Skin":"Glaucus","Clothing":"Gold Chain","Hat":"Punk Green","Accessories":"Transparent Bat","Mouth":"Ohhh","Eyes":"3D Glasses"}},"3918":{"name":"OGenie 3918","traits":{"Background":"Tortilla","Skin":"Pan","Clothing":"Retro Track Purple","Hat":"Punk Pink","Accessories":"Flower Power","Mouth":"Brown Mo","Eyes":"Turtle Wayfarer"}},"3919":{"name":"OGenie 3919","traits":{"Background":"Dark Purple","Skin":"OG Element Tattoo","Clothing":"OG Jersey Blue","Hat":"OG Green Trucker","Accessories":"Pizza","Mouth":"G Smile","Eyes":"Eyes White"}},"3920":{"name":"OGenie 3920","traits":{"Background":"Ash","Skin":"Celestial Cosmos","Clothing":"PS Beige","Hat":"Blonde Quiff","Accessories":"Coffee Mug","Mouth":"Grey Beard","Eyes":"Hollow White"}},"3921":{"name":"OGenie 3921","traits":{"Background":"Dark Purple","Skin":"Celestial Earth","Clothing":"Blue Stripe","Hat":"Punk Pink","Mouth":"You What!","Eyes":"Round Black","Accessories":"Diamond Stud"}},"3922":{"name":"OGenie 3922","traits":{"Background":"Hazy Blue","Skin":"Golden Ra","Clothing":"Gold Chain & Black T","Hat":"Black Bandana","Mouth":"Black Beard","Eyes":"Eye Patch"}},"3923":{"name":"OGenie 3923","traits":{"Background":"Fossil","Skin":"Seshat","Clothing":"Red Leather Jacket","Hat":"OGT White Trucker","Mouth":"Yeeaa","Eyes":"Eyes White","Accessories":"Double Gold Loop"}},"3924":{"name":"OGenie 3924","traits":{"Background":"Tortilla","Skin":"Mars","Clothing":"Dark Grey Hoodie","Hat":"Wizard Hat","Mouth":"Black Beard","Eyes":"Source Overflow Black"}},"3925":{"name":"OGenie 3925","traits":{"Background":"Dark Purple","Skin":"Golden Ra","Clothing":"Black Camo Jacket","Hat":"Punk Pink","Mouth":"Toothpick","Eyes":"Turtle Wayfarer"}},"3926":{"name":"OGenie 3926","traits":{"Background":"Stone","Skin":"Flora","Clothing":"Black Bomber","Hat":"OG Green Beanie","Mouth":"Black Beard","Eyes":"Turtle Wayfarer","Accessories":"Diamond Stud"}},"3927":{"name":"OGenie 3927","traits":{"Background":"Stone","Skin":"Devine Fire","Clothing":"PS Grey","Hat":"Cotton Candy Mullet","Mouth":"You What!","Eyes":"Source Overflow White"}},"3928":{"name":"OGenie 3928","traits":{"Background":"Ash","Skin":"Mars","Clothing":"Camo Jacket","Hat":"Fade","Mouth":"Grin","Eyes":"Reading Round"}},"3929":{"name":"OGenie 3929","traits":{"Background":"Ash","Skin":"Balor","Clothing":"Dark Grey Hoodie","Hat":"Red Beanie","Mouth":"Grey Beard","Eyes":"Reading Round White"}},"3930":{"name":"OGenie 3930","traits":{"Background":"OG Green","Skin":"Tartarus","Clothing":"Silver OGT Chain & Black Shirt","Hat":"Dark Quiff","Mouth":"Rainbow Grin","Eyes":"Hollow Black","Accessories":"Gold Loop"}},"3931":{"name":"OGenie 3931","traits":{"Background":"Hazy Blue","Skin":"Amaterasu","Clothing":"PS Purple","Hat":"Rose Dust Mullet","Mouth":"Shmoke","Eyes":"Hollow Black","Accessories":"Gold Stud"}},"3932":{"name":"OGenie 3932","traits":{"Background":"Fossil","Skin":"Bast","Clothing":"WeAreOGT White","Hat":"Green Visor","Mouth":"Shmoke","Eyes":"Eyes White"}},"3933":{"name":"OGenie 3933","traits":{"Background":"Dusty Blue","Skin":"Air Black Tattoo","Clothing":"Grey Stripe","Hat":"Clear Bandana","Accessories":"Transparent Axe","Mouth":"Ginger Beard","Eyes":"Clubmaster Silver"}},"3934":{"name":"OGenie 3934","traits":{"Background":"Concrete","Skin":"Pluto","Clothing":"Camo Jacket","Hat":"Blue Bandana","Accessories":"Wooden Bat","Mouth":"Brown Mo","Eyes":"Black Wayfarer"}},"3935":{"name":"OGenie 3935","traits":{"Background":"Hazy Blue","Skin":"Devine Earth","Clothing":"OG Jersey Blue","Hat":"Sushi Bandana Black","Mouth":"Ohhh","Eyes":"Turtle Wayfarer"}},"3936":{"name":"OGenie 3936","traits":{"Background":"Steel Blue","Skin":"Luna","Clothing":"Punk Leather Jacket","Hat":"Blue Bandana","Mouth":"Black Beard","Eyes":"Top G Gold"}},"3937":{"name":"OGenie 3937","traits":{"Background":"Dark Purple","head-gear":"Gold Halo","Skin":"Jord","Clothing":"Army Jacket","Hat":"Hot Pink Fade","Mouth":"Yeeaa","Eyes":"Clubmaster Silver","Accessories":"Diamond Stud"}},"3938":{"name":"OGenie 3938","traits":{"Background":"Tortilla","Skin":"Celestial Eternity","Clothing":"WeAreOGT White","Hat":"Pink Mullet","Mouth":"Blonde Mo","Eyes":"Eyes White","Accessories":"Gold Stud"}},"3939":{"name":"OGenie 3939","traits":{"Background":"Dusty Pink","Skin":"Mars","Clothing":"Special: Space Riding Suit","Hat":"Purple Splash","Accessories":"Broken Cue","Mouth":"Ohhh","Eyes":"Bored"}},"3940":{"name":"OGenie 3940","traits":{"Background":"Concrete","Skin":"Fire Tattoo","Clothing":"Flannel Green","Hat":"Punk Dark","Accessories":"Pizza","Mouth":"Ginger Mo","Eyes":"Bored"}},"3941":{"name":"OGenie 3941","traits":{"Background":"Steel Blue","Skin":"Flora","Clothing":"Leather Jacket","Hat":"Locks & Comb","Mouth":"RollUp","Eyes":"Clubmaster Gold","Accessories":"Punk Stud"}},"3942":{"name":"OGenie 3942","traits":{"Background":"Dusty Pink","Skin":"Celestial Fire","Hat":"Green Visor","Mouth":"Stubble Shmoke","Eyes":"Matrix","Accessories":"Gold Stud"}},"3943":{"name":"OGenie 3943","traits":{"Background":"Ash","Skin":"Devine Water","Clothing":"Flannel Red","Hat":"BW Cap Black & OG Green","Mouth":"Brown Mo","Eyes":"Clubmaster Gold"}},"3944":{"name":"OGenie 3944","traits":{"Background":"Purple","Skin":"OG Element Tattoo","Clothing":"Black Denim Jacket","Hat":"Yellow Beanie","Accessories":"Baseball Glove & Ball","Mouth":"Toothpick","Eyes":"Reading Round White"}},"3945":{"name":"OGenie 3945","traits":{"Background":"Tortilla","Skin":"Amaterasu","Clothing":"Flannel Red","Hat":"OGT White Trucker","Mouth":"Rainbow Grin","Eyes":"Turtle Wayfarer"}},"3946":{"name":"OGenie 3946","traits":{"Background":"Lavender","Skin":"Jord","Clothing":"Dark Grey Hoodie","Hat":"Blond Fade","Mouth":"RollUp","Eyes":"Pink Round"}},"3947":{"name":"Multiverse OGenie - OMecha Thunder","traits":{"MV OGenie 1/1":"OMecha Thunder"}},"3948":{"name":"OGenie 3948","traits":{"Background":"Lavender","Skin":"Mars","Clothing":"Flannel Dark Red","Hat":"Dark Quiff","Accessories":"Fire Element","Mouth":"Toothpick","Eyes":"Meme"}},"3949":{"name":"OGenie 3949","traits":{"Background":"Dark Purple","Skin":"Water Tattoo","Clothing":"Blue Denim Jacket","Hat":"Bucket Hat Olive","Accessories":"G-Pods","Mouth":"Black Beard","Eyes":"Eyes White"}},"3950":{"name":"OGenie 3950","traits":{"Background":"Dusty Blue","Skin":"Seshat","Clothing":"The OG Jumper","Hat":"Sushi Bandana White","Accessories":"Transparent Bat","Mouth":"Ohhh","Eyes":"Clubmaster Gold"}},"3951":{"name":"OGenie 3951","traits":{"Background":"Concrete","Skin":"Devine Earth","Clothing":"OG Green Puffer","Hat":"Pompadour","Accessories":"Diamond Stud","Mouth":"Gold Grin","Eyes":"Transparent Wayfarer"}},"3952":{"name":"Multiverse OGenie - OKek","traits":{"MV OGenie 1/1":"OKek"}},"3953":{"name":"OGenie 3953","traits":{"Background":"Ash","Skin":"Tartarus","Clothing":"Black & OG Green Shozoku","Hat":"Grey Kasa","Mouth":"Stubble Shmoke","Eyes":"OG Round","Accessories":"Punk Stud"}},"3954":{"name":"OGenie 3954","traits":{"Background":"Tortilla","Skin":"OG Element Tattoo","Clothing":"Prison T","Mouth":"Ginger Mo","Eyes":"Hollow Black","Accessories":"Punk Stud"}},"3955":{"name":"OGenie 3955","traits":{"Background":"Hazy Blue","Skin":"OG Element Tattoo","Clothing":"Brown Cord Jacket","Hat":"Genie Bun","Accessories":"Flower Power","Mouth":"Black Beard","Eyes":"Matrix"}},"3956":{"name":"OGenie 3956","traits":{"Background":"Stone","Skin":"Pan","Clothing":"Grey Hoodie","Hat":"Purple Splash","Mouth":"RollUp","Eyes":"Cooked"}},"3957":{"name":"OGenie 3957","traits":{"Background":"Lavender","Skin":"Seshat","Clothing":"OG-Unit T & Gold Chain","Hat":"Black Visor","Accessories":"Coffee Mug","Mouth":"Stubble Shmoke","Eyes":"Source Overflow White"}},"3958":{"name":"OGenie 3958","traits":{"Background":"Feudal","head-gear":"Gold Halo","Skin":"Amaterasu","Clothing":"Flannel Green","Hat":"Fade","Mouth":"Ginger Mo","Eyes":"Tech Specs"}},"3959":{"name":"OGenie 3959","traits":{"Background":"Steel Blue","Skin":"Idube","Hat":"Fedora","Accessories":"Thunder Lord","Mouth":"Ginger Beard","Eyes":"Bubblegum Pitvipers"}},"3960":{"name":"OGenie 3960","traits":{"Background":"Dark Purple","Skin":"Glaucus","Clothing":"WeAreOG Black","Hat":"Green Splash","Mouth":"Yeeaa","Eyes":"Eye Patch"}},"3961":{"name":"OGenie 3961","traits":{"Background":"Ash","Skin":"Jord","Clothing":"PS Purple","Hat":"Black Visor","Mouth":"Brown Mo","Eyes":"Transparent Wayfarer"}},"3962":{"name":"Multiverse OGenie - OMecha Water","traits":{"MV OGenie 1/1":"OMecha Water"}},"3963":{"name":"OGenie 3963","traits":{"Background":"Stone","Skin":"Fujin","Clothing":"B&W Stripe","Hat":"Punk Green","Accessories":"Pizza","Mouth":"Cigar","Eyes":"Cooked"}},"3964":{"name":"Multiverse OGenie - OBunz","traits":{"MV OGenie 1/1":"OBunz"}},"3965":{"name":"OGenie 3965","traits":{"Background":"Fog","Skin":"Pan Tattoo","Clothing":"Gold Chain & Black T","Hat":"Punk Dark","Accessories":"Storm Control","Mouth":"Yeeaa","Eyes":"Top G Black"}},"3966":{"name":"OGenie 3966","traits":{"Background":"Concrete","Skin":"Flora","Clothing":"Presidential","Hat":"Bucket Hat Olive","Mouth":"Grin","Eyes":"Meme","Accessories":"Gold Stud"}},"3967":{"name":"OGenie 3967","traits":{"Background":"Lavender","Skin":"Amaterasu","Clothing":"OGT Black Track","Hat":"Black Quiff","Mouth":"Grin","Eyes":"Black & Brown Wayfarer"}},"3968":{"name":"OGenie 3968","traits":{"Background":"Stone","Skin":"Sunrise Jord","Clothing":"Prison T","Hat":"Orange Beanie","Accessories":"Molecule Control","Mouth":"Whistle","Eyes":"Bored"}},"3969":{"name":"OGenie 3969","traits":{"Background":"Hazy Blue","Skin":"OG Element","Clothing":"Red Track","Hat":"Trumpie","Accessories":"Coffee OGm","Mouth":"G Smile","Eyes":"Top G Green"}},"3970":{"name":"OGenie 3970","traits":{"Background":"Fog","Skin":"Flora","Clothing":"Army Jacket","Hat":"Camo Helmet","Accessories":"Silver Axe","Mouth":"Rainbow Grin","Eyes":"Hollow White"}},"3971":{"name":"OGenie 3971","traits":{"Background":"Stone","Skin":"Water Tattoo","Clothing":"Army Jacket","Hat":"Wizard Hat","Accessories":"Punk Stud","Mouth":"Grin","Eyes":"Cooked"}},"3972":{"name":"OGenie 3972","traits":{"Background":"Slate","Skin":"Mars","Clothing":"Black Suit","Hat":"Blond Quiff","Accessories":"Gamer","Mouth":"Stubble Shmoke","Eyes":"Eyes White"}},"3973":{"name":"OGenie 3973","traits":{"Background":"Hazy Blue","Skin":"Golden Ra","Clothing":"OGT Gold Chain","Hat":"Grey Balaclava","Mouth":"Whistle","Eyes":"Round Black"}},"3974":{"name":"OGenie 3974","traits":{"Background":"OG Green","Skin":"Luna","Clothing":"Gold Chain","Hat":"Pink Mullet","Mouth":"RollUp","Eyes":"Orange Pitvipers"}},"3975":{"name":"OGenie 3975","traits":{"Background":"Stone","Skin":"Bast","Clothing":"Olive Jacket","Hat":"Trumpie","Mouth":"Ohhh","Eyes":"Eyes White"}},"3976":{"name":"OGenie 3976","traits":{"Background":"Dark Purple","Skin":"Luna","Clothing":"Black Camo Jacket","Hat":"Camo Helmet","Accessories":"G-Pods","Mouth":"Blonde Mo","Eyes":"Top G Gold"}},"3977":{"name":"OGenie 3977","traits":{"Background":"Concrete","Skin":"Pan Tattoo","Clothing":"PS Grey","Hat":"Blonde Quiff","Mouth":"Toothpick","Eyes":"Top G Gold"}},"3978":{"name":"OGenie 3978","traits":{"Background":"Tortilla","Skin":"Golden Ra","Clothing":"OGT Gold Chain","Hat":"BW Cap Black & OG Green","Accessories":"SC Cocktail","Mouth":"Grin","Eyes":"Cooked"}},"3979":{"name":"OGenie 3979","traits":{"Background":"Dusty Pink","Skin":"Celestial Cosmos","Clothing":"OG Jersey Dark","Hat":"Purple Splash","Accessories":"Gamer","Mouth":"Black Mo","Eyes":"Tech Specs"}},"3980":{"name":"OGenie 3980","traits":{"Background":"Ash","Skin":"Raijin","Clothing":"Blue Stripe","Hat":"Sushi Bandana Black","Mouth":"G Smile","Eyes":"Clubmaster Gold"}},"3981":{"name":"OGenie 3981","traits":{"Background":"Concrete","Skin":"Pluto","Clothing":"PS Beige","Hat":"Blond Bandana","Mouth":"Ohhh","Eyes":"Black Wayfarer"}},"3982":{"name":"OGenie 3982","traits":{"Background":"Stone","Skin":"Celestial Eternity","Clothing":"Navy Track Jacket","Hat":"Air Hair","Accessories":"Glove Right","Mouth":"RollUp","Eyes":"Matrix"}},"3983":{"name":"OGenie 3983","traits":{"Background":"Slate","Skin":"Bast","Clothing":"PS Grey","Hat":"Olive Mullet","Mouth":"Toothpick","Eyes":"Storm"}},"3984":{"name":"OGenie 3984","traits":{"Background":"Dusty Pink","Skin":"Mars Tattoo","Clothing":"Black T Gold OGT Chain","Hat":"Air Hair","Accessories":"Earth Element","Mouth":"Shmoke","Eyes":"Transparent Wayfarer"}},"3985":{"name":"OGenie 3985","traits":{"Background":"Red","Skin":"Pluto","Clothing":"White Hoodie","Hat":"Red Bandana","Mouth":"G Smile","Eyes":"Cooked"}},"3986":{"name":"OGenie 3986","traits":{"Background":"Stone","Skin":"Devine Earth","Clothing":"Army Jacket","Hat":"MNGA","Mouth":"Grin","Eyes":"Eyes White"}},"3987":{"name":"OGenie 3987","traits":{"Background":"Ash","Skin":"Glaucus","Clothing":"Sweatshirt Gold OGT Chain","Hat":"Black Quiff","Mouth":"RollUp","Eyes":"Hollow White"}},"3988":{"name":"OGenie 3988","traits":{"Background":"Purple","Skin":"Pan","Hat":"Black Beanie","Mouth":"Toothpick","Eyes":"Clubmaster Silver"}},"3989":{"name":"OGenie 3989","traits":{"Background":"Red","Skin":"Flora","Clothing":"Flannel OG Green","Hat":"Camo Helmet","Mouth":"Ginger Beard","Eyes":"Hollow White"}},"3990":{"name":"OGenie 3990","traits":{"Background":"Red","Skin":"Hina","Clothing":"White T Gold Chain","Hat":"Top Hat","Accessories":"Gold Loop","Mouth":"G Smile","Eyes":"Matrix"}},"3991":{"name":"OGenie 3991","traits":{"Background":"Ash","Skin":"Glaucus","Clothing":"B&W Stripe","Hat":"Bucket Hat Black","Mouth":"Grey Beard","Eyes":"OG Wayfarer"}},"3992":{"name":"OGenie 3992","traits":{"Background":"Olive Green","Skin":"Glaucus","Clothing":"OMG T","Hat":"Black Mullet","Mouth":"Black Beard","Eyes":"Orange Pitvipers"}},"3993":{"name":"OGenie 3993","traits":{"Background":"Stone","Skin":"Bast","Clothing":"Silver OGT Chain & Black Shirt","Hat":"Sushi Bandana White","Mouth":"You What!","Eyes":"Red Visor Beam"}},"3994":{"name":"OGenie 3994","traits":{"Background":"Concrete","Skin":"Pluto Blue Tattoo","Clothing":"Coppice Sweatshirt White","Hat":"Cotton Candy Mullet","Mouth":"Yeeaa","Eyes":"Turtle Wayfarer"}},"3995":{"name":"OGenie 3995","traits":{"Background":"Steel Blue","Skin":"OG Element","Clothing":"OGT Retro Track","Hat":"Trumpie","Mouth":"Yeeaa","Eyes":"Clubmaster Silver","Accessories":"G-Pods"}},"3996":{"name":"OGenie 3996","traits":{"Background":"Dusty Pink","Skin":"Amaterasu","Clothing":"JPD","Hat":"Ginger Quiff","Accessories":"Glove Left","Mouth":"G Smile","Eyes":"Hollow Black"}},"3997":{"name":"OGenie 3997","traits":{"Background":"Stone","Skin":"Devine Earth","Clothing":"Camo Jacket","Hat":"Grey Mullet","Accessories":"Storm Fist","Mouth":"Grin","Eyes":"Cartoon"}},"3998":{"name":"OGenie 3998","traits":{"Background":"Hazy Blue","Skin":"Bast","Clothing":"Black Denim Jacket","Hat":"OG Wizard Hat","Mouth":"Black Beard","Eyes":"Eye Patch"}},"3999":{"name":"Multiverse OGenie - OScrib","traits":{"MV OGenie 1/1":"OScrib"}},"4000":{"name":"OGenie 4000","traits":{"Background":"Red","Skin":"Mars","Clothing":"Black Suit","Hat":"Pink Bandana","Mouth":"Whistle","Eyes":"Meme"}}}
