{"1001":{"name":"DoodRilla #1001","traits":{"Background":"Aquamarine","Skin":"Brown","Clothing":"Sailor","Mouth":"Tongue","Eyes":"Bored","Hat":"Commie","Trait Count":"6"}},"1002":{"name":"DoodRilla #1002","traits":{"Background":"Army Green","Skin":"Brown","Clothing":"Admirals Coat","Mouth":"Unshaven Party Horn","Eyes":"Angry","Hat":"Seaman Hat","Trait Count":"6"}},"1003":{"name":"DoodRilla #1003","traits":{"Background":"Yellow","Skin":"Black","Clothing":"Tie Dye","Mouth":"Bored","Eyes":"Angry","Hat":"Bandana Blue","Trait Count":"6"}},"1004":{"name":"DoodRilla #1004","traits":{"Background":"Army Green","Skin":"DMT","Clothing":"DoodRilla T","Mouth":"Grin","Eyes":"Dead","Hat":"Beanie","Trait Count":"6"}},"1005":{"name":"DoodRilla #1005","traits":{"Background":"Aquamarine","Skin":"Pink","Clothing":"Tuxedo T","Mouth":"Grin","Eyes":"Bored","Hat":"Irish Boho","Trait Count":"6"}},"1006":{"name":"DoodRilla #1006","traits":{"Background":"Purple","Skin":"Brown","Clothing":"Black T","Mouth":"Spliff","Earrings":"Gold Hoop","Eyes":"Bloodshot","Hat":"Halo","Trait Count":"7"}},"1007":{"name":"DoodRilla #1007","traits":{"Background":"Yellow","Skin":"Trippy","Clothing":"Ape T","Mouth":"Spliff","Eyes":"Dead","Hat":"Vietnam Era Helmet","Trait Count":"6"}},"1008":{"name":"DoodRilla #1008","traits":{"Background":"Orange","Skin":"Dark Brown","Clothing":"Lab Coat","Mouth":"Unshaven Spliff","Earrings":"Silver Hoop","Eyes":"Hypnotized","Hat":"Black Hat","Trait Count":"7"}},"1009":{"name":"DoodRilla #1009","traits":{"Background":"Grey","Skin":"Dark Brown","Clothing":"Leather Jacket","Mouth":"Bored","Earrings":"Silver Stud","Eyes":"Bored","Hat":"Sea Captain Hat","Trait Count":"7"}},"1010":{"name":"DoodRilla #1010","traits":{"Background":"Ape Blue","Skin":"Cream","Clothing":"Bone Necklace","Mouth":"Phoneme L","Eyes":"Bored","Hat":"S&M Hat","Trait Count":"6"}},"1011":{"name":"DoodRilla #1011","traits":{"Background":"New Punk Blue","Skin":"Red","Clothing":"Sailor","Mouth":"Tongue","Eyes":"Bored","Hat":"Prussian Helmet","Trait Count":"6"}},"1012":{"name":"DoodRilla #1012","traits":{"Background":"Yellow","Skin":"Brown","Clothing":"Turtle Neck","Mouth":"Spliff","Eyes":"3D","Hat":"Irish Boho","Trait Count":"6"}},"1013":{"name":"DoodRilla #1013","traits":{"Background":"Aquamarine","Skin":"Brown","Clothing":"Ape T Red","Mouth":"Party Horn","Eyes":"Angry","Hat":"Cowboy Hat","Trait Count":"6"}},"1014":{"name":"DoodRilla #1014","traits":{"Background":"New Punk Blue","Skin":"Cheetah","Clothing":"Biker","Mouth":"Phoneme Vuh","Eyes":"Bloodshot","Hat":"Bunny Ears","Trait Count":"6"}},"1015":{"name":"DoodRilla #1015","traits":{"Background":"Blue","Skin":"Black","Clothing":"Hawaiian","Mouth":"Unshaven Spliff","Earrings":"Silver Stud","Eyes":"Angry","Hat":"Army Hat","Trait Count":"7"}},"1016":{"name":"DoodRilla #1016","traits":{"Background":"Army Green","Skin":"Tan","Clothing":"Service","Mouth":"Jovial","Earrings":"Silver Stud","Eyes":"Bored","Hat":"Service","Trait Count":"7"}},"1017":{"name":"DoodRilla #1017","traits":{"Background":"Army Green","Skin":"Blue","Clothing":"Hip Hop","Mouth":"Spliff","Eyes":"Bored","Hat":"Laurel Wreath","Trait Count":"6"}},"1018":{"name":"DoodRilla #1018","traits":{"Background":"Yellow","Skin":"Dark Brown","Mouth":"Bored","Earrings":"Silver Hoop","Eyes":"Bloodshot","Hat":"Safari","Trait Count":"6"}},"1019":{"name":"DoodRilla #1019","traits":{"Background":"Orange","Skin":"Brown","Clothing":"Turtle Neck","Mouth":"Phoneme L","Earrings":"Diamond Stud","Eyes":"Wide Eyed","Hat":"Bunny Ears","Trait Count":"7"}},"1020":{"name":"DoodRilla #1020","traits":{"Background":"Orange","Skin":"Zombie","Clothing":"Turtle Neck","Mouth":"Unshaven Bored","Eyes":"Bored","Hat":"Police Motorcycle Helmet","Trait Count":"6"}},"1021":{"name":"DoodRilla #1021","traits":{"Background":"New Punk Blue","Skin":"Grey","Clothing":"Kings Robe","Mouth":"Bored","Eyes":"Crazy","Hat":"S&M Hat","Overlay":"Crazy","Trait Count":"7"}},"1022":{"name":"DoodRilla #1022","traits":{"Background":"Orange","Skin":"Dark Brown","Clothing":"Lab Coat","Mouth":"Discomfort","Eyes":"Bored","Hat":"Fisherman Hat","Trait Count":"6"}},"1023":{"name":"DoodRilla #1023","traits":{"Background":"Purple","Skin":"Dark Brown","Clothing":"Service","Mouth":"Unshaven Bored","Earrings":"Silver Hoop","Eyes":"Blindfold","Hat":"Service","Trait Count":"7"}},"1024":{"name":"DoodRilla #1024","traits":{"Background":"Purple","Skin":"Golden Brown","Clothing":"Navy Striped","Mouth":"Bored","Eyes":"Scumbag","Hat":"Seaman Hat","Trait Count":"6"}},"1025":{"name":"DoodRilla #1025","traits":{"Background":"Aquamarine","Skin":"Brown","Mouth":"Grin","Eyes":"Sad","Trait Count":"4"}},"1026":{"name":"DoodRilla #1026","traits":{"Background":"Blue","Skin":"Blue","Clothing":"Caveman Pelt","Mouth":"Unshaven Bored","Earrings":"Silver Stud","Eyes":"Robot","Hat":"Trippy Captains Hat","Trait Count":"7"}},"1027":{"name":"DoodRilla #1027","traits":{"Background":"Ape Blue","Skin":"Cheetah","Clothing":"Pimp Coat","Mouth":"Bored","Eyes":"Coins","Hat":"Stuntman","Trait Count":"6"}},"1028":{"name":"DoodRilla #1028","traits":{"Background":"Grey","Skin":"DMT","Clothing":"Lab Coat","Mouth":"Grin","Eyes":"Scumbag","Hat":"Sea Captain Hat","Trait Count":"6"}},"1029":{"name":"DoodRilla #1029","traits":{"Background":"Purple","Skin":"Brown","Clothing":"Cowboy Shirt","Mouth":"Unshaven Bored","Earrings":"Silver Hoop","Eyes":"Coins","Hat":"BAYC","Trait Count":"7"}},"1030":{"name":"DoodRilla #1030","traits":{"Background":"Yellow","Skin":"Tan","Mouth":"Phoneme 000","Eyes":"Bored","Hat":"Cowboy Hat","Trait Count":"5"}},"1031":{"name":"DoodRilla #1031","traits":{"Background":"Ape Blue","Skin":"Black","Clothing":"Work Vest","Mouth":"Unshaven Bored","Eyes":"Crazy","Hat":"Sushi Chef","Trait Count":"6"}},"1032":{"name":"DoodRilla #1032","traits":{"Background":"Yellow","Skin":"Black","Clothing":"Bone Necklace","Mouth":"Diamond Grill","Eyes":"Closed","Hat":"Fisherman Hat","Trait Count":"6"}},"1033":{"name":"DoodRilla #1033","traits":{"Background":"Purple","Skin":"Golden Brown","Clothing":"Stunt Jacket","Mouth":"Phoneme Wah","Eyes":"Coins","Hat":"APE Blue Hat","Trait Count":"6"}},"1034":{"name":"DoodRilla #1034","traits":{"Background":"Purple","Skin":"Robot","Clothing":"Cowboy Shirt","Mouth":"Rainbow Grill","Eyes":"3D","Hat":"Irish Boho","Trait Count":"6"}},"1035":{"name":"DoodRilla #1035","traits":{"Background":"Orange","Skin":"Black","Clothing":"Sleeveless Logo","Mouth":"Bubblegum","Earrings":"Gold Hoop","Eyes":"Coins","Hat":"Sea Captain Hat","Trait Count":"7"}},"1036":{"name":"DoodRilla #1036","traits":{"Background":"Aquamarine","Skin":"Dark Brown","Clothing":"Work Vest","Mouth":"Bubblegum","Earrings":"Silver Hoop","Eyes":"Wide Eyed","Hat":"Seaman Hat","Trait Count":"7"}},"1037":{"name":"DoodRilla #1037","traits":{"Background":"New Punk Blue","Skin":"Brown","Clothing":"Turtle Neck","Mouth":"Grin","Earrings":"Silver Stud","Eyes":"Coins","Trait Count":"6"}},"1038":{"name":"DoodRilla #1038","traits":{"Background":"Army Green","Skin":"Brown","Clothing":"Ape T","Mouth":"Jovial","Earrings":"Gold Hoop","Eyes":"Angry","Hat":"Horns","Trait Count":"7"}},"1039":{"name":"DoodRilla #1039","traits":{"Skin":"Cheetah","Clothing":"Striped T","Mouth":"Unshaven Spliff","Earrings":"Silver Stud","Eyes":"Patch","Hat":"Fez","Trait Count":"6"}},"1040":{"name":"DoodRilla #1040","traits":{"Background":"Blue","Skin":"Golden Brown","Clothing":"Black Holes T","Mouth":"Dumbfounded","Eyes":"Patch","Hat":"Spinner Hat","Trait Count":"6"}},"1041":{"name":"DoodRilla #1041","traits":{"Background":"Orange","Skin":"White","Clothing":"Ape T Red","Mouth":"Unshaven Bored","Earrings":"Silver Hoop","Eyes":"Robot","Hat":"Halo","Trait Count":"7"}},"1042":{"name":"DoodRilla #1042","traits":{"Skin":"Tan","Clothing":"Guaya","Mouth":"Spliff","Earrings":"Silver Hoop","Eyes":"Zombie","Hat":"Red Hat","Trait Count":"6"}},"1043":{"name":"DoodRilla #1043","traits":{"Background":"Blue","Skin":"Blue","Clothing":"Nam Jacket","Mouth":"Phoneme 000","Eyes":"Bored","Hat":"S&M Hat","Trait Count":"6"}},"1044":{"name":"DoodRilla #1044","traits":{"Background":"Yellow","Skin":"Brown","Clothing":"Black T","Mouth":"Bored","Eyes":"Shades","Hat":"Beanie","Trait Count":"6"}},"1045":{"name":"DoodRilla #1045","traits":{"Background":"Purple","Skin":"Dark Brown","Clothing":"Puffy Vest","Mouth":"Spliff","Eyes":"Blue Beams","Hat":"Army Hat","Overlay":"BEAMS","Trait Count":"7"}},"1046":{"name":"DoodRilla #1046","traits":{"Background":"Purple","Skin":"Robot","Clothing":"APE Blue Tux","Mouth":"Bored","Eyes":"Robot","Hat":"Police Motorcycle Helmet","Trait Count":"6"}},"1047":{"name":"DoodRilla #1047","traits":{"Background":"Yellow","Skin":"Brown","Clothing":"Navy Striped","Mouth":"Jovial","Eyes":"Bored","Hat":"Sushi Chef","Trait Count":"6"}},"1048":{"name":"DoodRilla #1048","traits":{"Background":"Grey","Skin":"Brown","Clothing":"Stunt Jacket","Mouth":"Diamond Grill","Earrings":"Silver Stud","Eyes":"Blue Beams","Hat":"Flipped Brim","Overlay":"BEAMS","Trait Count":"8"}},"1049":{"name":"DoodRilla #1049","traits":{"Background":"Ape Blue","Skin":"Golden Brown","Clothing":"Striped T","Mouth":"Unshaven Bored","Eyes":"Crazy","Hat":"Bowler","Trait Count":"6"}},"1050":{"name":"DoodRilla #1050","traits":{"Background":"Blue","Skin":"Brown","Mouth":"Grin","Eyes":"Robot","Hat":"APE Blue Bowler","Trait Count":"5"}},"1051":{"name":"DoodRilla #1051","traits":{"Background":"Yellow","Skin":"Cream","Clothing":"Bone Necklace","Mouth":"Grin","Eyes":"Dead","Hat":"BAYC","Trait Count":"6"}},"1052":{"name":"DoodRilla #1052","traits":{"Background":"Purple","Skin":"Golden Brown","Clothing":"Hawaiian","Mouth":"Unshaven Spliff","Eyes":"Coins","Hat":"Fisherman Hat","Trait Count":"6"}},"1053":{"name":"DoodRilla #1053","traits":{"Background":"Blue","Skin":"Red","Clothing":"Pimp Coat","Mouth":"Phoneme Vuh","Eyes":"Closed","Hat":"Safari","Trait Count":"6"}},"1054":{"name":"DoodRilla #1054","traits":{"Background":"Blue","Skin":"Dark Brown","Clothing":"Nam Jacket","Mouth":"Gold Grill","Eyes":"Sad","Hat":"Vietnam Era Helmet","Trait Count":"6"}},"1055":{"name":"DoodRilla #1055","traits":{"Background":"Yellow","Skin":"Dark Brown","Clothing":"Striped T","Mouth":"Bored","Eyes":"Bloodshot","Hat":"Party Hat 2","Trait Count":"6"}},"1056":{"name":"DoodRilla #1056","traits":{"Background":"New Punk Blue","Skin":"Black","Clothing":"Nana Suit","Mouth":"Grin","Earrings":"Gold Hoop","Eyes":"Bored","Trait Count":"6"}},"1057":{"name":"DoodRilla #1057","traits":{"Background":"Ape Blue","Skin":"Black","Clothing":"Sleeveless","Mouth":"Discomfort","Earrings":"Silver Hoop","Eyes":"Heart","Hat":"Girl Hair Short","Trait Count":"7"}},"1058":{"name":"DoodRilla #1058","traits":{"Background":"Yellow","Skin":"Brown","Clothing":"Blue Dress","Mouth":"Unshaven Bored","Eyes":"Bored","Hat":"Fisherman Hat","Trait Count":"6"}},"1059":{"name":"DoodRilla #1059","traits":{"Background":"Purple","Skin":"Black","Clothing":"Smoking Jacket","Mouth":"Phoneme Oh","Eyes":"3D","Hat":"Commie","Trait Count":"6"}},"1060":{"name":"DoodRilla #1060","traits":{"Background":"Grey","Skin":"Golden Brown","Clothing":"Tanktop","Mouth":"Jovial","Eyes":"Holographic","Trait Count":"5"}},"1061":{"name":"DoodRilla #1061","traits":{"Background":"Grey","Skin":"Black","Clothing":"Work Vest","Mouth":"Tongue","Eyes":"Bored","Hat":"WW2 Pilot","Trait Count":"6"}},"1062":{"name":"DoodRilla #1062","traits":{"Background":"Blue","Skin":"Black","Clothing":"Striped T","Mouth":"Party Horn","Eyes":"Bored","Hat":"Irish Boho","Trait Count":"6"}},"1063":{"name":"DoodRilla #1063","traits":{"Background":"Purple","Skin":"Cheetah","Clothing":"Admirals Coat","Mouth":"Phoneme Oh","Eyes":"Hypnotized","Hat":"Seaman Hat","Trait Count":"6"}},"1064":{"name":"DoodRilla #1064","traits":{"Background":"Blue","Skin":"Pink","Clothing":"Lumberjack","Mouth":"Dumbfounded","Earrings":"Gold Hoop","Eyes":"Coins","Hat":"Sea Captain Hat","Trait Count":"7"}},"1065":{"name":"DoodRilla #1065","traits":{"Background":"Purple","Skin":"Dark Brown","Clothing":"Ape T Red","Mouth":"Spliff","Earrings":"Silver Stud","Eyes":"Angry","Trait Count":"6"}},"1066":{"name":"DoodRilla #1066","traits":{"Background":"Purple","Skin":"White","Clothing":"Prom Dress","Mouth":"Phoneme 000","Eyes":"Heart","Hat":"APE Blue Hat","Trait Count":"6"}},"1067":{"name":"DoodRilla #1067","traits":{"Background":"Blue","Skin":"Dark Brown","Clothing":"Rainbow Suspenders","Mouth":"Discomfort","Eyes":"Wide Eyed","Hat":"Seaman Hat","Trait Count":"6"}},"1068":{"name":"DoodRilla #1068","traits":{"Background":"Orange","Skin":"Blue","Clothing":"Sailor","Mouth":"Spliff","Eyes":"Wide Eyed","Hat":"Bowler","Trait Count":"6"}},"1069":{"name":"DoodRilla #1069","traits":{"Background":"Army Green","Skin":"Black","Clothing":"Turtle Neck","Mouth":"Tongue","Eyes":"Sleepy","Hat":"Baby Bonnet","Trait Count":"6"}},"1070":{"name":"DoodRilla #1070","traits":{"Background":"Blue","Skin":"Tan","Clothing":"Toga","Mouth":"Bored","Eyes":"Angry","Hat":"Army Hat","Trait Count":"6"}},"1071":{"name":"DoodRilla #1071","traits":{"Background":"Grey","Skin":"Robot","Clothing":"Tie Dye","Mouth":"Bored","Earrings":"Silver Stud","Eyes":"Bored","Hat":"Party Hat 1","Trait Count":"7"}},"1072":{"name":"DoodRilla #1072","traits":{"Background":"Grey","Skin":"Black","Clothing":"Tie Dye","Mouth":"Discomfort","Earrings":"Gold Stud","Eyes":"Wide Eyed","Hat":"Police Motorcycle Helmet","Trait Count":"7"}},"1073":{"name":"DoodRilla #1073","traits":{"Background":"Purple","Skin":"Pink","Clothing":"Black Holes T","Mouth":"Bored","Earrings":"Gold Hoop","Eyes":"Bloodshot","Hat":"Halo","Trait Count":"7"}},"1074":{"name":"DoodRilla #1074","traits":{"Background":"Purple","Skin":"Zombie","Mouth":"Spliff","Eyes":"Bloodshot","Hat":"Kings Crown","Trait Count":"5"}},"1075":{"name":"DoodRilla #1075","traits":{"Background":"Orange","Skin":"Tan","Clothing":"Lab Coat","Mouth":"Unshaven Bored","Earrings":"Silver Hoop","Eyes":"Crazy","Hat":"Beanie","Trait Count":"7"}},"1076":{"name":"DoodRilla #1076","traits":{"Background":"New Punk Blue","Skin":"Blue","Clothing":"Sleeveless","Mouth":"Bored","Eyes":"Robot","Hat":"APE Blue Bowler","Trait Count":"6"}},"1077":{"name":"DoodRilla #1077","traits":{"Background":"Orange","Skin":"Pink","Clothing":"Lumberjack","Mouth":"Bored","Earrings":"Gold Hoop","Eyes":"Crazy","Hat":"S&M Hat","Overlay":"Crazy","Trait Count":"8"}},"1078":{"name":"DoodRilla #1078","traits":{"Background":"Aquamarine","Skin":"Black","Clothing":"Prisoner","Mouth":"Unshaven Bored","Eyes":"Closed","Hat":"S&M Hat","Trait Count":"6"}},"1079":{"name":"DoodRilla #1079","traits":{"Background":"Grey","Skin":"Cheetah","Clothing":"Tanktop","Mouth":"Phoneme Oh","Earrings":"Diamond Stud","Eyes":"Bloodshot","Hat":"Beanie","Trait Count":"7"}},"1080":{"name":"DoodRilla #1080","traits":{"Background":"Yellow","Skin":"Brown","Clothing":"Hawaiian","Mouth":"Bored","Eyes":"Hypnotized","Hat":"Short Mohawk","Trait Count":"6"}},"1081":{"name":"DoodRilla #1081","traits":{"Background":"Blue","Skin":"Cheetah","Clothing":"Biker","Mouth":"Phoneme Vuh","Eyes":"3D","Hat":"Fez","Trait Count":"6"}},"1082":{"name":"DoodRilla #1082","traits":{"Background":"Purple","Skin":"Tan","Clothing":"Stunt Jacket","Mouth":"Bored","Eyes":"Hypnotized","Hat":"Fisherman Hat","Trait Count":"6"}},"1083":{"name":"DoodRilla #1083","traits":{"Background":"Aquamarine","Skin":"Robot","Clothing":"Stunt Jacket","Mouth":"Unshaven Spliff","Eyes":"3D","Trait Count":"5"}},"1084":{"name":"DoodRilla #1084","traits":{"Background":"Orange","Skin":"Cheetah","Clothing":"Striped T","Mouth":"Bored","Earrings":"Cross","Eyes":"Bored","Hat":"Beanie","Trait Count":"7"}},"1085":{"name":"DoodRilla #1085","traits":{"Background":"Army Green","Skin":"Blue","Clothing":"Tanktop","Mouth":"Bored","Earrings":"Diamond Stud","Eyes":"3D","Hat":"WW2 Pilot","Trait Count":"7"}},"1086":{"name":"DoodRilla #1086","traits":{"Background":"Aquamarine","Skin":"Pink","Clothing":"Nam Jacket","Mouth":"Unshaven Cigar","Eyes":"Closed","Hat":"Cowboy Hat","Trait Count":"6"}},"1087":{"name":"DoodRilla #1087","traits":{"Background":"Purple","Skin":"Black","Clothing":"Biker","Mouth":"Bored","Earrings":"Silver Hoop","Eyes":"Laser","Trait Count":"6"}},"1088":{"name":"DoodRilla #1088","traits":{"Skin":"Golden Brown","Clothing":"Sailor","Mouth":"Small Grin","Eyes":"Shades","Hat":"Laurel Wreath","Overlay":"Shades","Trait Count":"6"}},"1089":{"name":"DoodRilla #1089","traits":{"Background":"Purple","Skin":"Brown","Clothing":"Navy Striped","Mouth":"Unshaven Bored","Eyes":"Heart","Hat":"Commie","Trait Count":"6"}},"1090":{"name":"DoodRilla #1090","traits":{"Background":"Yellow","Skin":"Cheetah","Clothing":"Hawaiian","Mouth":"Unshaven Spliff","Earrings":"Silver Stud","Eyes":"Dead","Hat":"Beanie","Trait Count":"7"}},"1091":{"name":"DoodRilla #1091","traits":{"Background":"Yellow","Skin":"Brown","Mouth":"Bored","Earrings":"Silver Stud","Eyes":"Closed","Hat":"Seaman Hat","Trait Count":"6"}},"1092":{"name":"DoodRilla #1092","traits":{"Background":"Yellow","Skin":"Brown","Clothing":"Striped T","Mouth":"Rage","Earrings":"Silver Stud","Eyes":"Coins","Hat":"Commie","Trait Count":"7"}},"1093":{"name":"DoodRilla #1093","traits":{"Background":"Army Green","Skin":"Blue","Clothing":"Bone Necklace","Mouth":"Small Grin","Eyes":"Sleepy","Hat":"Fisherman Hat","Trait Count":"6"}},"1094":{"name":"DoodRilla #1094","traits":{"Background":"Ape Blue","Skin":"Blue","Clothing":"Puffy Vest","Mouth":"Jovial","Eyes":"Crazy","Hat":"Fez","Trait Count":"6"}},"1095":{"name":"DoodRilla #1095","traits":{"Background":"Grey","Skin":"Blue","Clothing":"Hip Hop","Mouth":"Phoneme 000","Eyes":"Bored","Hat":"Sea Captain Hat","Trait Count":"6"}},"1096":{"name":"DoodRilla #1096","traits":{"Background":"New Punk Blue","Skin":"Black","Clothing":"Stunt Jacket","Mouth":"Grin","Earrings":"Gold Stud","Eyes":"Bored","Hat":"Stuntman","Trait Count":"7"}},"1097":{"name":"DoodRilla #1097","traits":{"Background":"Grey","Skin":"Cream","Mouth":"Unshaven Spliff","Eyes":"Scumbag","Hat":"Army Hat","Trait Count":"5"}},"1098":{"name":"DoodRilla #1098","traits":{"Background":"New Punk Blue","Skin":"Blue","Clothing":"APE Blue Tux","Mouth":"Jovial","Eyes":"Robot","Hat":"Beanie","Trait Count":"6"}},"1099":{"name":"DoodRilla #1099","traits":{"Background":"Grey","Skin":"Cheetah","Clothing":"Black T","Mouth":"Dumbfounded","Eyes":"Crazy","Hat":"Safari","Overlay":"Crazy","Trait Count":"7"}},"1100":{"name":"DoodRilla #1100","traits":{"Background":"New Punk Blue","Skin":"Brown","Mouth":"Bored","Eyes":"Coins","Hat":"Army Hat","Trait Count":"5"}},"1101":{"name":"DoodRilla #1101","traits":{"Background":"Blue","Skin":"White","Clothing":"Navy Striped","Mouth":"Jovial","Eyes":"Hypnotized","Hat":"Fez","Trait Count":"6"}},"1102":{"name":"DoodRilla #1102","traits":{"Background":"Army Green","Skin":"Golden Brown","Clothing":"Caveman Pelt","Mouth":"Dumbfounded","Eyes":"Bored","Hat":"Beanie","Trait Count":"6"}},"1103":{"name":"DoodRilla #1103","traits":{"Background":"Yellow","Skin":"Brown","Clothing":"Bandolier","Mouth":"Unshaven Bored","Eyes":"Closed","Hat":"Irish Boho","Trait Count":"6"}},"1104":{"name":"DoodRilla #1104","traits":{"Background":"Aquamarine","Skin":"Cheetah","Clothing":"Navy Striped","Mouth":"Phoneme Vuh","Earrings":"Silver Hoop","Eyes":"Bloodshot","Hat":"APE Blue Hat","Trait Count":"7"}},"1105":{"name":"DoodRilla #1105","traits":{"Background":"Ape Blue","Skin":"Zombie","Clothing":"Bone Necklace","Mouth":"Diamond Grill","Eyes":"Closed","Hat":"Bowler","Trait Count":"6"}},"1106":{"name":"DoodRilla #1106","traits":{"Background":"Orange","Skin":"Brown","Clothing":"Bone T","Mouth":"Unshaven Cigar","Eyes":"Heart","Hat":"Girl Hair Short","Trait Count":"6"}},"1107":{"name":"DoodRilla #1107","traits":{"Background":"Orange","Skin":"Tan","Clothing":"Toga","Mouth":"Rage","Eyes":"Bored","Hat":"Fez","Trait Count":"6"}},"1108":{"name":"DoodRilla #1108","traits":{"Background":"Purple","Skin":"Brown","Clothing":"Sailor","Mouth":"Phoneme Oh","Eyes":"Bored","Hat":"Commie","Trait Count":"6"}},"1109":{"name":"DoodRilla #1109","traits":{"Background":"Army Green","Skin":"Cream","Mouth":"Bored","Earrings":"Silver Hoop","Eyes":"Zombie","Hat":"Black Hat","Trait Count":"6"}},"1110":{"name":"DoodRilla #1110","traits":{"Background":"New Punk Blue","Skin":"Red","Clothing":"Cowboy Shirt","Mouth":"Stoge","Eyes":"Cyborg","Hat":"Fez","Trait Count":"6"}},"1111":{"name":"DoodRilla #1111","traits":{"Background":"Ape Blue","Skin":"Dark Brown","Mouth":"Phoneme Oh","Eyes":"Sad","Hat":"Army Hat","Trait Count":"5"}},"1112":{"name":"DoodRilla #1112","traits":{"Background":"Yellow","Skin":"Robot","Clothing":"Stunt Jacket","Mouth":"Bored","Eyes":"3D","Hat":"Fisherman Hat","Trait Count":"6"}},"1113":{"name":"DoodRilla #1113","traits":{"Background":"Grey","Skin":"Grey","Clothing":"Service","Mouth":"Unshaven Bubblegum","Earrings":"Silver Stud","Eyes":"Crazy","Hat":"Service","Overlay":"Crazy","Trait Count":"8"}},"1114":{"name":"DoodRilla #1114","traits":{"Background":"Army Green","Skin":"Pink","Clothing":"Kings Robe","Mouth":"Unshaven Spliff","Eyes":"Sad","Hat":"Cowboy Hat","Trait Count":"6"}},"1115":{"name":"DoodRilla #1115","traits":{"Background":"Purple","Skin":"Pink","Clothing":"Kings Robe","Mouth":"Unshaven Bored","Eyes":"Dead","Hat":"S&M Hat","Trait Count":"6"}},"1116":{"name":"DoodRilla #1116","traits":{"Background":"Blue","Skin":"Black","Clothing":"Sleeveless Logo","Mouth":"Unshaven Spliff","Eyes":"Zombie","Hat":"Service","Trait Count":"6"}},"1117":{"name":"DoodRilla #1117","traits":{"Background":"Purple","Skin":"Brown","Mouth":"Phoneme 000","Earrings":"Gold Hoop","Eyes":"Cyborg","Hat":"Horns","Trait Count":"6"}},"1118":{"name":"DoodRilla #1118","traits":{"Background":"Aquamarine","Skin":"Dark Brown","Clothing":"Sailor","Mouth":"Spliff","Earrings":"Gold Hoop","Eyes":"Blindfold","Hat":"Halo","Trait Count":"7"}},"1119":{"name":"DoodRilla #1119","traits":{"Background":"New Punk Blue","Skin":"Dark Brown","Clothing":"Sleeveless","Mouth":"Dumbfounded","Earrings":"Silver Hoop","Eyes":"Hypnotized","Hat":"Commie","Trait Count":"7"}},"1120":{"name":"DoodRilla #1120","traits":{"Background":"Aquamarine","Skin":"Dark Brown","Clothing":"Smoking Jacket","Mouth":"Bored","Eyes":"Blindfold","Hat":"Cowboy Hat","Trait Count":"6"}},"1121":{"name":"DoodRilla #1121","traits":{"Background":"Aquamarine","Skin":"Golden Brown","Clothing":"Tie Dye","Mouth":"Dumbfounded","Eyes":"Wide Eyed","Hat":"Commie","Trait Count":"6"}},"1122":{"name":"DoodRilla #1122","traits":{"Background":"Purple","Skin":"Zombie","Clothing":"Guaya","Mouth":"Unshaven Bored","Eyes":"Robot","Hat":"Safari","Trait Count":"6"}},"1123":{"name":"DoodRilla #1123","traits":{"Background":"Blue","Skin":"Trippy","Clothing":"Bone Necklace","Mouth":"Phoneme 000","Eyes":"Bored","Hat":"Sea Captain Hat","Trait Count":"6"}},"1124":{"name":"DoodRilla #1124","traits":{"Background":"New Punk Blue","Skin":"Black","Clothing":"Punk Jacket","Mouth":"Tongue","Eyes":"Bored","Hat":"Beanie","Trait Count":"6"}},"1125":{"name":"DoodRilla #1125","traits":{"Background":"Purple","Skin":"Black","Clothing":"Ape T","Mouth":"Spliff","Eyes":"Patch","Hat":"Bowler","Trait Count":"6"}},"1126":{"name":"DoodRilla #1126","traits":{"Background":"Ape Blue","Skin":"Dark Brown","Clothing":"Hip Hop","Mouth":"Grin","Eyes":"Bloodshot","Hat":"Horns","Trait Count":"6"}},"1127":{"name":"DoodRilla #1127","traits":{"Background":"Army Green","Skin":"Death Bot","Clothing":"Cowboy Shirt","Mouth":"Tongue","Earrings":"Silver Hoop","Eyes":"Bored","Hat":"Red Hat","Trait Count":"7"}},"1128":{"name":"DoodRilla #1128","traits":{"Background":"New Punk Blue","Skin":"Noise","Clothing":"Hawaiian","Mouth":"Discomfort","Eyes":"Sleepy","Hat":"Vietnam Era Helmet","Trait Count":"6"}},"1129":{"name":"DoodRilla #1129","traits":{"Background":"Orange","Skin":"Death Bot","Clothing":"Black T","Mouth":"Grin","Eyes":"Closed","Hat":"Service","Trait Count":"6"}},"1130":{"name":"DoodRilla #1130","traits":{"Background":"New Punk Blue","Skin":"Dark Brown","Clothing":"Bone T","Mouth":"Grin","Earrings":"Silver Hoop","Eyes":"Sleepy","Hat":"Safari","Trait Count":"7"}},"1131":{"name":"DoodRilla #1131","traits":{"Background":"Grey","Skin":"Cream","Clothing":"Bandolier","Mouth":"Small Grin","Eyes":"Blue Beams","Hat":"Vietnam Era Helmet","Overlay":"BEAMS","Trait Count":"7"}},"1132":{"name":"DoodRilla #1132","traits":{"Background":"Aquamarine","Skin":"Brown","Clothing":"Lab Coat","Mouth":"Phoneme 000","Eyes":"Bloodshot","Hat":"Stuntman","Trait Count":"6"}},"1133":{"name":"DoodRilla #1133","traits":{"Background":"New Punk Blue","Skin":"Black","Clothing":"Toga","Mouth":"Bored","Earrings":"Gold Hoop","Eyes":"Dead","Hat":"Fisherman Hat","Trait Count":"7"}},"1134":{"name":"DoodRilla #1134","traits":{"Background":"Army Green","Skin":"Black","Clothing":"Black T","Mouth":"Grin","Eyes":"Dead","Hat":"Vietnam Era Helmet","Trait Count":"6"}},"1135":{"name":"DoodRilla #1135","traits":{"Background":"New Punk Blue","Skin":"Black","Clothing":"Turtle Neck","Mouth":"Discomfort","Earrings":"Silver Stud","Eyes":"Bored","Hat":"Seaman Hat","Trait Count":"7"}},"1136":{"name":"DoodRilla #1136","traits":{"Background":"Ape Blue","Skin":"Dark Brown","Clothing":"Admirals Coat","Mouth":"Jovial","Earrings":"Gold Hoop","Eyes":"Coins","Hat":"Seaman Hat","Trait Count":"7"}},"1137":{"name":"DoodRilla #1137","traits":{"Background":"Aquamarine","Skin":"Black","Clothing":"Bone T","Mouth":"Spliff","Earrings":"Silver Stud","Eyes":"Bloodshot","Hat":"Beanie","Trait Count":"7"}},"1138":{"name":"DoodRilla #1138","traits":{"Background":"Grey","Skin":"Dark Brown","Clothing":"Tanktop","Mouth":"Discomfort","Eyes":"Bloodshot","Hat":"Irish Boho","Trait Count":"6"}},"1139":{"name":"DoodRilla #1139","traits":{"Background":"Blue","Skin":"Black","Clothing":"Sailor","Mouth":"Dumbfounded","Earrings":"Gold Stud","Eyes":"Heart","Hat":"Police Motorcycle Helmet","Trait Count":"7"}},"1140":{"name":"DoodRilla #1140","traits":{"Background":"Purple","Skin":"White","Clothing":"Leather Jacket","Mouth":"Unshaven Spliff","Eyes":"Closed","Hat":"Halo","Trait Count":"6"}},"1141":{"name":"DoodRilla #1141","traits":{"Background":"Yellow","Skin":"Brown","Clothing":"Navy Striped","Mouth":"Pipe","Eyes":"Bored","Hat":"Laurel Wreath","Trait Count":"6"}},"1142":{"name":"DoodRilla #1142","traits":{"Background":"Army Green","Skin":"Pink","Mouth":"Bubblegum","Eyes":"Bloodshot","Hat":"Bandana Blue","Trait Count":"5"}},"1143":{"name":"DoodRilla #1143","traits":{"Background":"Blue","Skin":"Dark Brown","Clothing":"Hawaiian","Mouth":"Phoneme 000","Earrings":"Gold Stud","Eyes":"Crazy","Hat":"Party Hat 2","Trait Count":"7"}},"1144":{"name":"DoodRilla #1144","traits":{"Background":"Blue","Skin":"Golden Brown","Clothing":"Biker","Mouth":"Grin","Eyes":"Bloodshot","Hat":"Halo","Trait Count":"6"}},"1145":{"name":"DoodRilla #1145","traits":{"Background":"Blue","Skin":"Brown","Clothing":"Sailor","Mouth":"Unshaven Bored","Eyes":"Wide Eyed","Hat":"Commie","Trait Count":"6"}},"1146":{"name":"DoodRilla #1146","traits":{"Background":"New Punk Blue","Skin":"Dark Brown","Clothing":"Service","Mouth":"Rage","Earrings":"Silver Hoop","Eyes":"Bored","Hat":"Girl Hair Pink","Trait Count":"7"}},"1147":{"name":"DoodRilla #1147","traits":{"Background":"Purple","Skin":"Brown","Clothing":"Blue Dress","Mouth":"Diamond Grill","Eyes":"Wide Eyed","Hat":"Seaman Hat","Trait Count":"6"}},"1148":{"name":"DoodRilla #1148","traits":{"Background":"Aquamarine","Skin":"Robot","Clothing":"Toga","Mouth":"Dumbfounded","Eyes":"Robot","Hat":"Fisherman Hat","Trait Count":"6"}},"1149":{"name":"DoodRilla #1149","traits":{"Background":"Purple","Skin":"Dark Brown","Clothing":"Service","Mouth":"Grin","Eyes":"Blindfold","Hat":"Service","Trait Count":"6"}},"1150":{"name":"DoodRilla #1150","traits":{"Background":"Aquamarine","Skin":"Cream","Clothing":"Pimp Coat","Mouth":"Phoneme 000","Eyes":"Wide Eyed","Hat":"Short Mohawk","Trait Count":"6"}},"1151":{"name":"DoodRilla #1151","traits":{"Background":"Grey","Skin":"Dark Brown","Clothing":"Bone Necklace","Mouth":"Unshaven Dagger","Eyes":"Wide Eyed","Hat":"Beanie","Trait Count":"6"}},"1152":{"name":"DoodRilla #1152","traits":{"Background":"Aquamarine","Skin":"Cream","Clothing":"Nam Jacket","Mouth":"Unshaven Bored","Earrings":"Silver Stud","Eyes":"Sleepy","Hat":"Girl Hair Short","Trait Count":"7"}},"1153":{"name":"DoodRilla #1153","traits":{"Background":"Yellow","Skin":"Cream","Clothing":"Smoking Jacket","Mouth":"Unshaven Bored","Eyes":"Sleepy","Hat":"APE Blue Hat","Trait Count":"6"}},"1154":{"name":"DoodRilla #1154","traits":{"Background":"Yellow","Skin":"Cheetah","Mouth":"Unshaven Dagger","Eyes":"Bloodshot","Hat":"Police Motorcycle Helmet","Trait Count":"5"}},"1155":{"name":"DoodRilla #1155","traits":{"Background":"New Punk Blue","Skin":"Dark Brown","Clothing":"Tanktop","Mouth":"Phoneme Oh","Eyes":"Bloodshot","Hat":"Commie","Trait Count":"6"}},"1156":{"name":"DoodRilla #1156","traits":{"Background":"Aquamarine","Skin":"Tan","Clothing":"Bandolier","Mouth":"Bored","Eyes":"Scumbag","Hat":"Army Hat","Trait Count":"6"}},"1157":{"name":"DoodRilla #1157","traits":{"Background":"Purple","Skin":"Pink","Clothing":"Tuxedo","Mouth":"Stoge","Eyes":"Patch","Hat":"Seaman Hat","Trait Count":"6"}},"1158":{"name":"DoodRilla #1158","traits":{"Skin":"Black","Clothing":"Striped T","Mouth":"Bored","Eyes":"Wide Eyed","Hat":"Police Motorcycle Helmet","Trait Count":"5"}},"1159":{"name":"DoodRilla #1159","traits":{"Background":"Army Green","Skin":"Red","Clothing":"Lumberjack","Mouth":"Rage","Eyes":"Coins","Hat":"Party Hat 2","Trait Count":"6"}},"1160":{"name":"DoodRilla #1160","traits":{"Background":"Ape Blue","Skin":"Dark Brown","Clothing":"Bone T","Mouth":"Bored","Eyes":"Blindfold","Hat":"Beanie","Trait Count":"6"}},"1161":{"name":"DoodRilla #1161","traits":{"Background":"Orange","Skin":"Red","Clothing":"Guaya","Mouth":"Jovial","Eyes":"Bored","Hat":"Faux Hawk","Trait Count":"6"}},"1162":{"name":"DoodRilla #1162","traits":{"Background":"Army Green","Skin":"Cheetah","Clothing":"Sailor","Mouth":"Phoneme 000","Eyes":"Shades","Hat":"Army Hat","Trait Count":"6"}},"1163":{"name":"DoodRilla #1163","traits":{"Background":"Ape Blue","Skin":"Cream","Clothing":"Navy Striped","Mouth":"Unshaven Bored","Eyes":"Heart","Hat":"Party Hat 1","Trait Count":"6"}},"1164":{"name":"DoodRilla #1164","traits":{"Background":"Grey","Skin":"DMT","Mouth":"Grin","Earrings":"Silver Stud","Eyes":"Dead","Hat":"Sushi Chef","Trait Count":"6"}},"1165":{"name":"DoodRilla #1165","traits":{"Background":"Purple","Skin":"Brown","Mouth":"Phoneme L","Eyes":"Sleepy","Hat":"Fisherman Hat","Trait Count":"5"}},"1166":{"name":"DoodRilla #1166","traits":{"Background":"Blue","Skin":"Death Bot","Clothing":"Caveman Pelt","Mouth":"Spliff","Earrings":"Silver Stud","Eyes":"Bored","Hat":"Sea Captain Hat","Trait Count":"7"}},"1167":{"name":"DoodRilla #1167","traits":{"Background":"Army Green","Skin":"Black","Clothing":"Nam Jacket","Mouth":"Spliff","Eyes":"Crazy","Hat":"Vietnam Era Helmet","Overlay":"Crazy","Trait Count":"7"}},"1168":{"name":"DoodRilla #1168","traits":{"Background":"Blue","Skin":"Cream","Clothing":"Toga","Mouth":"Phoneme Vuh","Earrings":"Silver Hoop","Eyes":"Shades","Hat":"Stuntman","Trait Count":"7"}},"1169":{"name":"DoodRilla #1169","traits":{"Background":"Purple","Skin":"Dark Brown","Mouth":"Spliff","Earrings":"Silver Hoop","Eyes":"Shades","Hat":"Commie","Trait Count":"6"}},"1170":{"name":"DoodRilla #1170","traits":{"Background":"Orange","Skin":"Black","Clothing":"Rainbow Suspenders","Mouth":"Rage","Eyes":"Sad","Hat":"Bowler","Trait Count":"6"}},"1171":{"name":"DoodRilla #1171","traits":{"Background":"Grey","Skin":"Cheetah","Clothing":"Lumberjack","Mouth":"Phoneme Vuh","Eyes":"Coins","Hat":"Bunny Ears","Trait Count":"6"}},"1172":{"name":"DoodRilla #1172","traits":{"Background":"Army Green","Skin":"Zombie","Mouth":"Bored","Earrings":"Silver Stud","Eyes":"Zombie","Hat":"Stuntman","Trait Count":"6"}},"1173":{"name":"DoodRilla #1173","traits":{"Background":"Grey","Skin":"White","Mouth":"Unshaven Cigar","Eyes":"Crazy","Trait Count":"4"}},"1174":{"name":"DoodRilla #1174","traits":{"Background":"Purple","Skin":"Tan","Clothing":"Smoking Jacket","Mouth":"Phoneme L","Earrings":"Silver Hoop","Eyes":"Sleepy","Hat":"Halo","Trait Count":"7"}},"1175":{"name":"DoodRilla #1175","traits":{"Background":"Ape Blue","Skin":"Brown","Clothing":"Blue Dress","Mouth":"Phoneme Wah","Earrings":"Gold Stud","Eyes":"Holographic","Hat":"Army Hat","Trait Count":"7"}},"1176":{"name":"DoodRilla #1176","traits":{"Background":"Orange","Skin":"Brown","Clothing":"Hip Hop","Mouth":"Diamond Grill","Eyes":"Dead","Hat":"Halo","Trait Count":"6"}},"1177":{"name":"DoodRilla #1177","traits":{"Background":"Purple","Skin":"White","Clothing":"Navy Striped","Mouth":"Bubblegum","Eyes":"Holographic","Hat":"Fez","Trait Count":"6"}},"1178":{"name":"DoodRilla #1178","traits":{"Background":"Army Green","Skin":"Trippy","Clothing":"Striped T","Mouth":"Phoneme 000","Eyes":"Sad","Hat":"Baby Bonnet","Trait Count":"6"}},"1179":{"name":"DoodRilla #1179","traits":{"Background":"Blue","Skin":"Golden Brown","Mouth":"Spliff","Eyes":"Coins","Hat":"Flipped Brim","Trait Count":"5"}},"1180":{"name":"DoodRilla #1180","traits":{"Background":"Yellow","Skin":"Pink","Clothing":"Guaya","Mouth":"Phoneme Oh","Eyes":"Coins","Hat":"Police Motorcycle Helmet","Trait Count":"6"}},"1181":{"name":"DoodRilla #1181","traits":{"Background":"Army Green","Skin":"Grey","Clothing":"Service","Mouth":"Bored","Eyes":"Heart","Hat":"Service","Trait Count":"6"}},"1182":{"name":"DoodRilla #1182","traits":{"Background":"Yellow","Skin":"Brown","Clothing":"Guaya","Mouth":"Unshaven Bored","Eyes":"Closed","Hat":"Vietnam Era Helmet","Trait Count":"6"}},"1183":{"name":"DoodRilla #1183","traits":{"Background":"Blue","Skin":"Brown","Clothing":"Ape T","Mouth":"Bored","Eyes":"Sad","Hat":"Horns","Trait Count":"6"}},"1184":{"name":"DoodRilla #1184","traits":{"Background":"New Punk Blue","Skin":"Trippy","Clothing":"Sailor","Mouth":"Dumbfounded","Earrings":"Cross","Eyes":"Crazy","Hat":"Halo","Trait Count":"7"}},"1185":{"name":"DoodRilla #1185","traits":{"Background":"Purple","Skin":"Pink","Clothing":"Bone Necklace","Mouth":"Small Grin","Eyes":"Shades","Hat":"Cowboy Hat","Trait Count":"6"}},"1186":{"name":"DoodRilla #1186","traits":{"Background":"Grey","Skin":"Zombie","Clothing":"Sailor","Mouth":"Unshaven Kazoo","Earrings":"Silver Stud","Eyes":"Robot","Hat":"Halo","Trait Count":"7"}},"1187":{"name":"DoodRilla #1187","traits":{"Background":"Army Green","Skin":"Robot","Clothing":"Hip Hop","Mouth":"Unshaven Bored","Eyes":"3D","Hat":"Cowboy Hat","Trait Count":"6"}},"1188":{"name":"DoodRilla #1188","traits":{"Background":"Army Green","Skin":"Black","Clothing":"Work Vest","Mouth":"Bored","Eyes":"Scumbag","Hat":"S&M Hat","Trait Count":"6"}},"1189":{"name":"DoodRilla #1189","traits":{"Background":"Purple","Skin":"Cream","Clothing":"Smoking Jacket","Mouth":"Bored","Eyes":"Heart","Hat":"Party Hat 1","Trait Count":"6"}},"1190":{"name":"DoodRilla #1190","traits":{"Background":"Army Green","Skin":"Tan","Mouth":"Phoneme L","Eyes":"Heart","Trait Count":"4"}},"1191":{"name":"DoodRilla #1191","traits":{"Background":"Purple","Skin":"Golden Brown","Clothing":"Bone T","Mouth":"Unshaven Spliff","Eyes":"Dead","Hat":"Red Hat","Trait Count":"6"}},"1192":{"name":"DoodRilla #1192","traits":{"Background":"Grey","Skin":"Red","Clothing":"Lumberjack","Mouth":"Kazoo","Eyes":"Robot","Hat":"Flipped Brim","Trait Count":"6"}},"1193":{"name":"DoodRilla #1193","traits":{"Background":"New Punk Blue","Skin":"Dark Brown","Clothing":"Hawaiian","Mouth":"Bored","Earrings":"Silver Stud","Eyes":"Sleepy","Hat":"Black Hat","Trait Count":"7"}},"1194":{"name":"DoodRilla #1194","traits":{"Background":"Purple","Skin":"Golden Brown","Clothing":"Lumberjack","Mouth":"Unshaven Bored","Eyes":"Robot","Hat":"Seaman Hat","Trait Count":"6"}},"1195":{"name":"DoodRilla #1195","traits":{"Background":"Ape Blue","Skin":"Cheetah","Clothing":"Prom Dress","Mouth":"Phoneme 000","Eyes":"Hypnotized","Hat":"Bowler","Trait Count":"6"}},"1196":{"name":"DoodRilla #1196","traits":{"Background":"Grey","Skin":"Dark Brown","Clothing":"Tuxedo T","Mouth":"Dumbfounded","Eyes":"Laser","Hat":"Girl Hair Short","Overlay":"Laser","Trait Count":"7"}},"1197":{"name":"DoodRilla #1197","traits":{"Background":"Ape Blue","Skin":"Golden Brown","Clothing":"Guaya","Mouth":"Gold Grill","Earrings":"Silver Hoop","Eyes":"Patch","Hat":"Party Hat 1","Trait Count":"7"}},"1198":{"name":"DoodRilla #1198","traits":{"Background":"Yellow","Skin":"Grey","Clothing":"Prisoner","Mouth":"Bored","Eyes":"Scumbag","Hat":"Fez","Trait Count":"6"}},"1199":{"name":"DoodRilla #1199","traits":{"Background":"Grey","Skin":"Red","Clothing":"Hawaiian","Mouth":"Jovial","Eyes":"Angry","Hat":"Baby Bonnet","Trait Count":"6"}},"1200":{"name":"DoodRilla #1200","traits":{"Background":"Yellow","Skin":"DMT","Clothing":"Leather Jacket","Mouth":"Bored","Eyes":"Hypnotized","Hat":"Sea Captain Hat","Trait Count":"6"}},"1201":{"name":"DoodRilla #1201","traits":{"Background":"New Punk Blue","Skin":"Robot","Clothing":"Board and Hungry","Mouth":"Unshaven Bored","Earrings":"Silver Stud","Eyes":"Bored","Hat":"Girl Hair Short","Trait Count":"7"}},"1202":{"name":"DoodRilla #1202","traits":{"Background":"Army Green","Skin":"Dark Brown","Clothing":"Navy Striped","Mouth":"Rage","Earrings":"Silver Stud","Eyes":"Closed","Hat":"Commie","Trait Count":"7"}},"1203":{"name":"DoodRilla #1203","traits":{"Background":"Aquamarine","Skin":"DMT","Clothing":"Caveman Pelt","Mouth":"Unshaven Spliff","Eyes":"Sad","Hat":"Party Hat 2","Trait Count":"6"}},"1204":{"name":"DoodRilla #1204","traits":{"Background":"Blue","Skin":"Cream","Clothing":"Punk Jacket","Mouth":"Spliff","Earrings":"Silver Hoop","Eyes":"Cyborg","Hat":"Service","Trait Count":"7"}},"1205":{"name":"DoodRilla #1205","traits":{"Background":"Purple","Skin":"Cream","Clothing":"Biker","Mouth":"Unshaven Bored","Eyes":"Closed","Hat":"Seaman Hat","Trait Count":"6"}},"1206":{"name":"DoodRilla #1206","traits":{"Background":"Orange","Skin":"Brown","Clothing":"Tuxedo T","Mouth":"Bored","Eyes":"Bored","Hat":"Party Hat 2","Trait Count":"6"}},"1207":{"name":"DoodRilla #1207","traits":{"Background":"Grey","Skin":"Pink","Clothing":"Guaya","Mouth":"Bored","Eyes":"Wide Eyed","Hat":"Cowboy Hat","Trait Count":"6"}},"1208":{"name":"DoodRilla #1208","traits":{"Background":"Grey","Skin":"Cream","Clothing":"Lab Coat","Mouth":"Tongue","Eyes":"Crazy","Trait Count":"5"}},"1209":{"name":"DoodRilla #1209","traits":{"Background":"New Punk Blue","Skin":"Brown","Clothing":"Admirals Coat","Mouth":"Bored","Eyes":"Bored","Trait Count":"5"}},"1210":{"name":"DoodRilla #1210","traits":{"Background":"Yellow","Skin":"Cream","Mouth":"Spliff","Earrings":"Gold Hoop","Eyes":"Wide Eyed","Hat":"Seaman Hat","Trait Count":"6"}},"1211":{"name":"DoodRilla #1211","traits":{"Background":"New Punk Blue","Skin":"Robot","Clothing":"Bone T","Mouth":"Unshaven Bored","Eyes":"Sad","Hat":"Flipped Brim","Trait Count":"6"}},"1212":{"name":"DoodRilla #1212","traits":{"Background":"Orange","Skin":"Cheetah","Clothing":"Puffy Vest","Mouth":"Phoneme 000","Eyes":"Patch","Hat":"Bunny Ears","Trait Count":"6"}},"1213":{"name":"DoodRilla #1213","traits":{"Skin":"Tan","Clothing":"Admirals Coat","Mouth":"Kazoo","Eyes":"Crazy","Trait Count":"4"}},"1214":{"name":"DoodRilla #1214","traits":{"Background":"Grey","Skin":"Dark Brown","Clothing":"Tuxedo T","Mouth":"Bored","Earrings":"Silver Hoop","Eyes":"Zombie","Hat":"Girl Hair Pink","Trait Count":"7"}},"1215":{"name":"DoodRilla #1215","traits":{"Background":"Ape Blue","Skin":"Golden Brown","Clothing":"Striped T","Mouth":"Bubblegum","Earrings":"Silver Stud","Eyes":"Crazy","Hat":"Bowler","Trait Count":"7"}},"1216":{"name":"DoodRilla #1216","traits":{"Background":"Army Green","Skin":"Cheetah","Clothing":"Sailor","Mouth":"Small Grin","Eyes":"Angry","Trait Count":"5"}},"1217":{"name":"DoodRilla #1217","traits":{"Background":"Blue","Skin":"Brown","Clothing":"Ape T","Mouth":"Unshaven Bored","Eyes":"Shades","Hat":"Faux Hawk","Trait Count":"6"}},"1218":{"name":"DoodRilla #1218","traits":{"Background":"Aquamarine","Skin":"Golden Brown","Clothing":"Black T","Mouth":"Bored","Earrings":"Silver Stud","Eyes":"Crazy","Hat":"Irish Boho","Overlay":"Crazy","Trait Count":"8"}},"1219":{"name":"DoodRilla #1219","traits":{"Background":"Blue","Skin":"Golden Brown","Mouth":"Phoneme Vuh","Earrings":"Gold Stud","Eyes":"Shades","Hat":"Commie","Trait Count":"6"}},"1220":{"name":"DoodRilla #1220","traits":{"Background":"Aquamarine","Skin":"Red","Clothing":"Work Vest","Mouth":"Unshaven Bubblegum","Eyes":"Sleepy","Hat":"Fisherman Hat","Trait Count":"6"}},"1221":{"name":"DoodRilla #1221","traits":{"Background":"Purple","Skin":"Black","Clothing":"Toga","Mouth":"Bored","Eyes":"Dead","Hat":"Service","Trait Count":"6"}},"1222":{"name":"DoodRilla #1222","traits":{"Background":"Orange","Skin":"Zombie","Clothing":"Bone Necklace","Mouth":"Phoneme 000","Eyes":"Sleepy","Hat":"Bunny Ears","Trait Count":"6"}},"1223":{"name":"DoodRilla #1223","traits":{"Background":"Yellow","Skin":"Red","Clothing":"Leather Jacket","Mouth":"Small Grin","Eyes":"Holographic","Hat":"Sea Captain Hat","Trait Count":"6"}},"1224":{"name":"DoodRilla #1224","traits":{"Background":"Purple","Skin":"Brown","Clothing":"Nana Suit","Mouth":"Bored","Earrings":"Gold Stud","Eyes":"Closed","Trait Count":"6"}},"1225":{"name":"DoodRilla #1225","traits":{"Skin":"Cheetah","Clothing":"Nam Jacket","Mouth":"Unshaven Bored","Earrings":"Silver Hoop","Eyes":"Sad","Hat":"Trippy Captains Hat","Trait Count":"6"}},"1226":{"name":"DoodRilla #1226","traits":{"Background":"Army Green","Skin":"Dark Brown","Clothing":"Space Suit","Mouth":"Rage","Eyes":"Bored","Hat":"Bunny Ears","Trait Count":"6"}},"1227":{"name":"DoodRilla #1227","traits":{"Background":"Purple","Skin":"Tan","Clothing":"Cowboy Shirt","Mouth":"Bored","Earrings":"Silver Stud","Eyes":"Bloodshot","Hat":"Prussian Helmet","Trait Count":"7"}},"1228":{"name":"DoodRilla #1228","traits":{"Background":"Grey","Skin":"Black","Mouth":"Dumbfounded","Eyes":"Bloodshot","Hat":"Prussian Helmet","Trait Count":"5"}},"1229":{"name":"DoodRilla #1229","traits":{"Background":"Yellow","Skin":"Brown","Clothing":"Striped T","Mouth":"Grin","Eyes":"Crazy","Hat":"Bored And Hungry","Overlay":"Crazy","Trait Count":"7"}},"1230":{"name":"DoodRilla #1230","traits":{"Background":"Yellow","Skin":"Golden Brown","Clothing":"Toga","Mouth":"Rage","Eyes":"Sad","Hat":"Army Hat","Trait Count":"6"}},"1231":{"name":"DoodRilla #1231","traits":{"Background":"Orange","Skin":"Gold","Clothing":"Tuxedo","Mouth":"Small Grin","Eyes":"Sleepy","Hat":"Halo","Trait Count":"6"}},"1232":{"name":"DoodRilla #1232","traits":{"Background":"Orange","Skin":"Golden Brown","Clothing":"Lumberjack","Mouth":"Jovial","Earrings":"Cross","Eyes":"Sleepy","Hat":"Service","Trait Count":"7"}},"1233":{"name":"DoodRilla #1233","traits":{"Background":"Orange","Skin":"Dark Brown","Clothing":"Puffy Vest","Mouth":"Grin","Earrings":"Diamond Stud","Eyes":"Sleepy","Hat":"Sushi Chef","Trait Count":"7"}},"1234":{"name":"DoodRilla #1234","traits":{"Background":"Grey","Skin":"Red","Clothing":"Striped T","Mouth":"Dumbfounded","Eyes":"Bloodshot","Hat":"Bunny Ears","Trait Count":"6"}},"1235":{"name":"DoodRilla #1235","traits":{"Background":"New Punk Blue","Skin":"Death Bot","Clothing":"Sleeveless Logo","Mouth":"Dumbfounded","Eyes":"Bloodshot","Hat":"Sea Captain Hat","Trait Count":"6"}},"1236":{"name":"DoodRilla #1236","traits":{"Background":"Army Green","Skin":"Black","Clothing":"Puffy Vest","Mouth":"Dumbfounded","Earrings":"Silver Stud","Eyes":"Bloodshot","Hat":"Seaman Hat","Trait Count":"7"}},"1237":{"name":"DoodRilla #1237","traits":{"Background":"Aquamarine","Skin":"Brown","Clothing":"Tweed Suit","Mouth":"Bored","Eyes":"Closed","Hat":"Kings Crown","Trait Count":"6"}},"1238":{"name":"DoodRilla #1238","traits":{"Background":"Purple","Skin":"Tan","Mouth":"Unshaven Bored","Earrings":"Silver Hoop","Eyes":"Zombie","Hat":"Girl Hair Short","Trait Count":"6"}},"1239":{"name":"DoodRilla #1239","traits":{"Background":"Purple","Skin":"Robot","Clothing":"Bandolier","Mouth":"Unshaven Bored","Eyes":"Bored","Hat":"Bandana Blue","Trait Count":"6"}},"1240":{"name":"DoodRilla #1240","traits":{"Background":"Grey","Skin":"Brown","Clothing":"Tie Dye","Mouth":"Unshaven Spliff","Eyes":"Angry","Hat":"Bowler","Trait Count":"6"}},"1241":{"name":"DoodRilla #1241","traits":{"Background":"Blue","Skin":"Pink","Clothing":"Nam Jacket","Mouth":"Spliff","Eyes":"Coins","Hat":"Trippy Captains Hat","Trait Count":"6"}},"1242":{"name":"DoodRilla #1242","traits":{"Background":"Aquamarine","Skin":"Pink","Clothing":"Sleeveless Logo","Mouth":"Tongue","Eyes":"Wide Eyed","Hat":"Sea Captain Hat","Trait Count":"6"}},"1243":{"name":"DoodRilla #1243","traits":{"Background":"Purple","Skin":"Dark Brown","Clothing":"Nam Jacket","Mouth":"Bored","Earrings":"Diamond Stud","Eyes":"Blindfold","Hat":"Bunny Ears","Trait Count":"7"}},"1244":{"name":"DoodRilla #1244","traits":{"Background":"New Punk Blue","Skin":"Death Bot","Clothing":"Tanktop","Mouth":"Dagger","Earrings":"Cross","Eyes":"Crazy","Hat":"Halo","Trait Count":"7"}},"1245":{"name":"DoodRilla #1245","traits":{"Background":"Aquamarine","Skin":"Tan","Clothing":"Nam Jacket","Mouth":"Unshaven Spliff","Eyes":"Bloodshot","Hat":"Girl Hair Short","Trait Count":"6"}},"1246":{"name":"DoodRilla #1246","traits":{"Background":"Purple","Skin":"Brown","Clothing":"Hawaiian","Mouth":"Phoneme Wah","Eyes":"Sleepy","Hat":"Black Hat","Trait Count":"6"}},"1247":{"name":"DoodRilla #1247","traits":{"Background":"Aquamarine","Skin":"Pink","Clothing":"Bone Necklace","Mouth":"Bored","Eyes":"Coins","Trait Count":"5"}},"1248":{"name":"DoodRilla #1248","traits":{"Background":"Blue","Skin":"Grey","Clothing":"Smoking Jacket","Mouth":"Unshaven Kazoo","Eyes":"Blindfold","Hat":"Horns","Trait Count":"6"}},"1249":{"name":"DoodRilla #1249","traits":{"Background":"Yellow","Skin":"Trippy","Mouth":"Dumbfounded","Earrings":"Silver Hoop","Eyes":"3D","Hat":"Irish Boho","Trait Count":"6"}},"1250":{"name":"DoodRilla #1250","traits":{"Background":"Grey","Skin":"Brown","Clothing":"Tuxedo T","Mouth":"Discomfort","Eyes":"Sad","Hat":"Vietnam Era Helmet","Trait Count":"6"}},"1251":{"name":"DoodRilla #1251","traits":{"Background":"Yellow","Skin":"Pink","Clothing":"Lumberjack","Mouth":"Tongue","Eyes":"Coins","Hat":"Beanie","Trait Count":"6"}},"1252":{"name":"DoodRilla #1252","traits":{"Background":"Aquamarine","Skin":"Dark Brown","Clothing":"Nam Jacket","Mouth":"Dumbfounded","Eyes":"Bored","Hat":"Kings Crown","Trait Count":"6"}},"1253":{"name":"DoodRilla #1253","traits":{"Background":"Yellow","Skin":"Death Bot","Clothing":"Admirals Coat","Mouth":"Grin","Eyes":"Crazy","Hat":"Short Mohawk","Trait Count":"6"}},"1254":{"name":"DoodRilla #1254","traits":{"Background":"Orange","Skin":"Robot","Clothing":"Biker","Mouth":"Phoneme Vuh","Eyes":"Wide Eyed","Hat":"Fez","Trait Count":"6"}},"1255":{"name":"DoodRilla #1255","traits":{"Background":"Yellow","Skin":"Golden Brown","Clothing":"Punk Jacket","Mouth":"Phoneme L","Eyes":"Closed","Hat":"Safari","Trait Count":"6"}},"1256":{"name":"DoodRilla #1256","traits":{"Background":"Aquamarine","Skin":"Blue","Mouth":"Bored","Eyes":"Bloodshot","Hat":"Service","Trait Count":"5"}},"1257":{"name":"DoodRilla #1257","traits":{"Background":"Aquamarine","Skin":"Tan","Clothing":"APE Blue Tux","Mouth":"Unshaven Bored","Earrings":"Silver Hoop","Eyes":"Wide Eyed","Hat":"Army Hat","Trait Count":"7"}},"1258":{"name":"DoodRilla #1258","traits":{"Background":"Orange","Skin":"Red","Clothing":"Hawaiian","Mouth":"Bubblegum","Earrings":"Silver Hoop","Eyes":"Zombie","Hat":"Fisherman Hat","Trait Count":"7"}},"1259":{"name":"DoodRilla #1259","traits":{"Skin":"Brown","Clothing":"Nam Jacket","Mouth":"Unshaven Bored","Eyes":"Sad","Hat":"APE Blue Band Bowler","Trait Count":"5"}},"1260":{"name":"DoodRilla #1260","traits":{"Background":"Orange","Skin":"Zombie","Clothing":"Striped T","Mouth":"Grin","Earrings":"Silver Hoop","Eyes":"Zombie","Hat":"Short Mohawk","Trait Count":"7"}},"1261":{"name":"DoodRilla #1261","traits":{"Background":"New Punk Blue","Skin":"Brown","Clothing":"Tweed Suit","Mouth":"Discomfort","Eyes":"Sleepy","Hat":"Halo","Trait Count":"6"}},"1262":{"name":"DoodRilla #1262","traits":{"Background":"Aquamarine","Skin":"Black","Clothing":"Tie Dye","Mouth":"Spliff","Earrings":"Diamond Stud","Eyes":"Bloodshot","Hat":"Baby Bonnet","Trait Count":"7"}},"1263":{"name":"DoodRilla #1263","traits":{"Background":"Orange","Skin":"White","Clothing":"Sleeveless Logo","Mouth":"Unshaven Bored","Eyes":"Sleepy","Hat":"Army Hat","Trait Count":"6"}},"1264":{"name":"DoodRilla #1264","traits":{"Background":"Aquamarine","Skin":"Grey","Clothing":"Tweed Suit","Mouth":"Unshaven Bored","Eyes":"Holographic","Hat":"Beanie","Trait Count":"6"}},"1265":{"name":"DoodRilla #1265","traits":{"Background":"Army Green","Skin":"Cream","Clothing":"Hawaiian","Mouth":"Bored","Eyes":"Bored","Hat":"Commie","Trait Count":"6"}},"1266":{"name":"DoodRilla #1266","traits":{"Background":"Blue","Skin":"Dark Brown","Clothing":"Bone T","Mouth":"Bored","Eyes":"Patch","Trait Count":"5"}},"1267":{"name":"DoodRilla #1267","traits":{"Background":"Purple","Skin":"Blue","Clothing":"Guaya","Mouth":"Bored","Eyes":"Coins","Hat":"Fez","Trait Count":"6"}},"1268":{"name":"DoodRilla #1268","traits":{"Background":"Orange","Skin":"Cheetah","Clothing":"Tuxedo T","Mouth":"Bored","Eyes":"Scumbag","Trait Count":"5"}},"1269":{"name":"DoodRilla #1269","traits":{"Background":"Purple","Skin":"Brown","Clothing":"Ape T Red","Mouth":"Discomfort","Earrings":"Gold Hoop","Eyes":"Bored","Hat":"Bandana Blue","Trait Count":"7"}},"1270":{"name":"DoodRilla #1270","traits":{"Background":"Aquamarine","Skin":"Grey","Clothing":"Work Vest","Mouth":"Unshaven Bored","Eyes":"Wide Eyed","Hat":"Service","Trait Count":"6"}},"1271":{"name":"DoodRilla #1271","traits":{"Background":"Orange","Skin":"Cream","Clothing":"Tie Dye","Mouth":"Unshaven Bored","Eyes":"Crazy","Hat":"Party Hat 1","Trait Count":"6"}},"1272":{"name":"DoodRilla #1272","traits":{"Background":"Grey","Skin":"Golden Brown","Clothing":"Lumberjack","Mouth":"Unshaven Spliff","Eyes":"Angry","Hat":"Baby Bonnet","Trait Count":"6"}},"1273":{"name":"DoodRilla #1273","traits":{"Background":"New Punk Blue","Skin":"Dark Brown","Clothing":"Rainbow Suspenders","Mouth":"Unshaven Bored","Eyes":"Wide Eyed","Hat":"Fez","Trait Count":"6"}},"1274":{"name":"DoodRilla #1274","traits":{"Background":"New Punk Blue","Skin":"Pink","Clothing":"Prom Dress","Mouth":"Pipe","Eyes":"Wide Eyed","Hat":"Short Mohawk","Trait Count":"6"}},"1275":{"name":"DoodRilla #1275","traits":{"Background":"Orange","Skin":"Brown","Clothing":"Toga","Mouth":"Unshaven Spliff","Eyes":"Angry","Hat":"Short Mohawk","Trait Count":"6"}},"1276":{"name":"DoodRilla #1276","traits":{"Background":"Yellow","Skin":"Dark Brown","Clothing":"Caveman Pelt","Mouth":"Grin","Earrings":"Diamond Stud","Eyes":"Closed","Hat":"Prussian Helmet","Trait Count":"7"}},"1277":{"name":"DoodRilla #1277","traits":{"Background":"Purple","Skin":"Tan","Clothing":"Turtle Neck","Mouth":"Bored","Eyes":"Shades","Hat":"Fez","Trait Count":"6"}},"1278":{"name":"DoodRilla #1278","traits":{"Background":"Grey","Skin":"White","Clothing":"Striped T","Mouth":"Grin","Eyes":"Closed","Hat":"Beanie","Trait Count":"6"}},"1279":{"name":"DoodRilla #1279","traits":{"Background":"Aquamarine","Skin":"Pink","Clothing":"Cowboy Shirt","Mouth":"Bored","Eyes":"Closed","Hat":"Commie","Trait Count":"6"}},"1280":{"name":"DoodRilla #1280","traits":{"Background":"Blue","Skin":"Robot","Mouth":"Bored","Earrings":"Silver Hoop","Eyes":"Sleepy","Hat":"Halo","Trait Count":"6"}},"1281":{"name":"DoodRilla #1281","traits":{"Background":"Blue","Skin":"Black","Clothing":"Tuxedo","Mouth":"Bored","Eyes":"Patch","Hat":"Fisherman Hat","Trait Count":"6"}},"1282":{"name":"DoodRilla #1282","traits":{"Background":"Ape Blue","Skin":"Tan","Clothing":"Navy Striped","Mouth":"Spliff","Eyes":"Bored","Hat":"Sea Captain Hat","Trait Count":"6"}},"1283":{"name":"DoodRilla #1283","traits":{"Background":"Purple","Skin":"Black","Clothing":"Navy Striped","Mouth":"Phoneme Vuh","Eyes":"Blindfold","Hat":"Flipped Brim","Trait Count":"6"}},"1284":{"name":"DoodRilla #1284","traits":{"Background":"Purple","Skin":"Cream","Clothing":"Hawaiian","Mouth":"Bored","Eyes":"Closed","Hat":"Trippy Captains Hat","Trait Count":"6"}},"1285":{"name":"DoodRilla #1285","traits":{"Background":"Blue","Skin":"Cream","Clothing":"Prisoner","Mouth":"Dumbfounded","Earrings":"Cross","Eyes":"Coins","Hat":"Cowboy Hat","Trait Count":"7"}},"1286":{"name":"DoodRilla #1286","traits":{"Background":"Orange","Skin":"Black","Clothing":"Tuxedo","Mouth":"Gold Grill","Eyes":"Bored","Hat":"Short Mohawk","Trait Count":"6"}},"1287":{"name":"DoodRilla #1287","traits":{"Background":"Grey","Skin":"Noise","Clothing":"Bone Necklace","Mouth":"Phoneme Vuh","Earrings":"Silver Stud","Eyes":"Closed","Hat":"Trippy Captains Hat","Trait Count":"7"}},"1288":{"name":"DoodRilla #1288","traits":{"Background":"Yellow","Skin":"Brown","Clothing":"Black T","Mouth":"Unshaven Bored","Earrings":"Gold Stud","Eyes":"Bloodshot","Trait Count":"6"}},"1289":{"name":"DoodRilla #1289","traits":{"Background":"Blue","Skin":"Dark Brown","Clothing":"Tie Dye","Mouth":"Jovial","Earrings":"Silver Hoop","Eyes":"Closed","Hat":"Seaman Hat","Trait Count":"7"}},"1290":{"name":"DoodRilla #1290","traits":{"Background":"Blue","Skin":"Blue","Clothing":"Sailor","Mouth":"Unshaven Pizza","Earrings":"Gold Hoop","Eyes":"Holographic","Hat":"S&M Hat","Trait Count":"7"}},"1291":{"name":"DoodRilla #1291","traits":{"Background":"Purple","Skin":"Black","Clothing":"Nam Jacket","Mouth":"Party Horn","Eyes":"Blindfold","Hat":"Red Hat","Trait Count":"6"}},"1292":{"name":"DoodRilla #1292","traits":{"Background":"Aquamarine","Skin":"Grey","Clothing":"Sailor","Mouth":"Phoneme 000","Eyes":"Bored","Hat":"Girl Hair Short","Trait Count":"6"}},"1293":{"name":"DoodRilla #1293","traits":{"Background":"Yellow","Skin":"Black","Clothing":"Leather Jacket","Mouth":"Dumbfounded","Eyes":"Wide Eyed","Hat":"Army Hat","Trait Count":"6"}},"1294":{"name":"DoodRilla #1294","traits":{"Background":"Grey","Skin":"Golden Brown","Clothing":"Leather Jacket","Mouth":"Bored","Earrings":"Gold Stud","Eyes":"Bored","Hat":"Beanie","Trait Count":"7"}},"1295":{"name":"DoodRilla #1295","traits":{"Background":"Blue","Skin":"Black","Clothing":"Tuxedo T","Mouth":"Small Grin","Eyes":"Bloodshot","Hat":"Seaman Hat","Trait Count":"6"}},"1296":{"name":"DoodRilla #1296","traits":{"Background":"New Punk Blue","Skin":"White","Clothing":"Tanktop","Mouth":"Grin","Eyes":"Blindfold","Hat":"Halo","Trait Count":"6"}},"1297":{"name":"DoodRilla #1297","traits":{"Background":"Ape Blue","Skin":"Red","Mouth":"Phoneme Oh","Earrings":"Silver Stud","Eyes":"Crazy","Hat":"Army Hat","Overlay":"Crazy","Trait Count":"7"}},"1298":{"name":"DoodRilla #1298","traits":{"Background":"Yellow","Skin":"Dark Brown","Clothing":"Sailor","Mouth":"Phoneme Wah","Eyes":"Sad","Hat":"Party Hat 1","Trait Count":"6"}},"1299":{"name":"DoodRilla #1299","traits":{"Background":"Yellow","Skin":"Brown","Mouth":"Party Horn","Earrings":"Silver Hoop","Eyes":"Closed","Trait Count":"5"}},"1300":{"name":"DoodRilla #1300","traits":{"Background":"Purple","Skin":"DMT","Clothing":"Ape T Red","Mouth":"Kazoo","Eyes":"Angry","Hat":"Red Hat","Trait Count":"6"}},"1301":{"name":"DoodRilla #1301","traits":{"Background":"Purple","Skin":"Tan","Clothing":"Hawaiian","Mouth":"Unshaven Bored","Earrings":"Silver Stud","Eyes":"Bored","Hat":"Horns","Trait Count":"7"}},"1302":{"name":"DoodRilla #1302","traits":{"Background":"Army Green","Skin":"Tan","Clothing":"Tuxedo T","Mouth":"Spliff","Eyes":"Scumbag","Hat":"Beanie","Trait Count":"6"}},"1303":{"name":"DoodRilla #1303","traits":{"Background":"Army Green","Skin":"Tan","Clothing":"Sailor","Mouth":"Tongue","Eyes":"Hypnotized","Hat":"Party Hat 1","Trait Count":"6"}},"1304":{"name":"DoodRilla #1304","traits":{"Background":"Army Green","Skin":"Tan","Clothing":"Blue Dress","Mouth":"Bored","Earrings":"Silver Hoop","Eyes":"Coins","Hat":"Sushi Chef","Trait Count":"7"}},"1305":{"name":"DoodRilla #1305","traits":{"Background":"Purple","Skin":"Cream","Clothing":"Striped T","Mouth":"Unshaven Spliff","Eyes":"Sleepy","Trait Count":"5"}},"1306":{"name":"DoodRilla #1306","traits":{"Background":"Grey","Skin":"Black","Clothing":"Biker","Mouth":"Bored","Earrings":"Silver Hoop","Eyes":"Closed","Hat":"S&M Hat","Trait Count":"7"}},"1307":{"name":"DoodRilla #1307","traits":{"Background":"Aquamarine","Skin":"Cream","Clothing":"Ape T","Mouth":"Bored","Eyes":"Shades","Hat":"Faux Hawk","Trait Count":"6"}},"1308":{"name":"DoodRilla #1308","traits":{"Background":"Blue","Skin":"Dark Brown","Clothing":"Stunt Jacket","Mouth":"Grin","Earrings":"Silver Stud","Eyes":"Sleepy","Trait Count":"6"}},"1309":{"name":"DoodRilla #1309","traits":{"Background":"Yellow","Skin":"Cream","Clothing":"Service","Mouth":"Phoneme L","Earrings":"Silver Hoop","Eyes":"Robot","Hat":"Service","Trait Count":"7"}},"1310":{"name":"DoodRilla #1310","traits":{"Background":"New Punk Blue","Skin":"DMT","Clothing":"Stunt Jacket","Mouth":"Pipe","Eyes":"Heart","Hat":"Bandana Blue","Trait Count":"6"}},"1311":{"name":"DoodRilla #1311","traits":{"Background":"New Punk Blue","Skin":"Black","Mouth":"Small Grin","Earrings":"Silver Stud","Eyes":"Bored","Hat":"Sushi Chef","Trait Count":"6"}},"1312":{"name":"DoodRilla #1312","traits":{"Background":"Purple","Skin":"DMT","Clothing":"Smoking Jacket","Mouth":"Unshaven Bored","Earrings":"Silver Stud","Eyes":"Bored","Hat":"Prussian Helmet","Trait Count":"7"}},"1313":{"name":"DoodRilla #1313","traits":{"Background":"Yellow","Skin":"Grey","Clothing":"Tanktop","Mouth":"Phoneme Vuh","Eyes":"Sleepy","Trait Count":"5"}},"1314":{"name":"DoodRilla #1314","traits":{"Background":"Army Green","Skin":"Golden Brown","Clothing":"Tuxedo T","Mouth":"Jovial","Eyes":"Heart","Hat":"Sea Captain Hat","Trait Count":"6"}},"1315":{"name":"DoodRilla #1315","traits":{"Background":"Blue","Skin":"White","Clothing":"Sailor","Mouth":"Grin","Earrings":"Gold Stud","Eyes":"3D","Hat":"Cowboy Hat","Trait Count":"7"}},"1316":{"name":"DoodRilla #1316","traits":{"Background":"Grey","Skin":"Pink","Clothing":"Sleeveless Logo","Mouth":"Small Grin","Eyes":"Sad","Hat":"Horns","Trait Count":"6"}},"1317":{"name":"DoodRilla #1317","traits":{"Background":"Ape Blue","Skin":"Red","Clothing":"Stunt Jacket","Mouth":"Dumbfounded","Eyes":"Crazy","Hat":"Bunny Ears","Trait Count":"6"}},"1318":{"name":"DoodRilla #1318","traits":{"Background":"Blue","Skin":"Black","Mouth":"Unshaven Bored","Eyes":"Bored","Hat":"Sushi Chef","Trait Count":"5"}},"1319":{"name":"DoodRilla #1319","traits":{"Background":"Purple","Skin":"Red","Clothing":"Nam Jacket","Mouth":"Unshaven Spliff","Eyes":"Shades","Hat":"Spinner Hat","Trait Count":"6"}},"1320":{"name":"DoodRilla #1320","traits":{"Background":"Orange","Skin":"Robot","Clothing":"Prom Dress","Mouth":"Unshaven Bored","Eyes":"Bloodshot","Hat":"Irish Boho","Trait Count":"6"}},"1321":{"name":"DoodRilla #1321","traits":{"Background":"Ape Blue","Skin":"Dark Brown","Clothing":"Admirals Coat","Mouth":"Grin","Eyes":"Bloodshot","Hat":"Commie","Trait Count":"6"}},"1322":{"name":"DoodRilla #1322","traits":{"Background":"Yellow","Skin":"Zombie","Clothing":"Hawaiian","Mouth":"Phoneme Oh","Eyes":"Closed","Hat":"Short Mohawk","Trait Count":"6"}},"1323":{"name":"DoodRilla #1323","traits":{"Background":"Grey","Skin":"Red","Clothing":"Blue Dress","Mouth":"Unshaven Cigar","Eyes":"Bored","Hat":"Seaman Hat","Trait Count":"6"}},"1324":{"name":"DoodRilla #1324","traits":{"Background":"Orange","Skin":"Zombie","Clothing":"Prisoner","Mouth":"Dumbfounded","Eyes":"Wide Eyed","Hat":"Vietnam Era Helmet","Trait Count":"6"}},"1325":{"name":"DoodRilla #1325","traits":{"Background":"Army Green","Skin":"White","Clothing":"Turtle Neck","Mouth":"Phoneme L","Eyes":"Bloodshot","Hat":"Commie","Trait Count":"6"}},"1326":{"name":"DoodRilla #1326","traits":{"Background":"Grey","Skin":"Black","Clothing":"Smoking Jacket","Mouth":"Unshaven Spliff","Eyes":"Sleepy","Hat":"Irish Boho","Trait Count":"6"}},"1327":{"name":"DoodRilla #1327","traits":{"Skin":"Cream","Clothing":"Nam Jacket","Mouth":"Bored","Earrings":"Silver Hoop","Eyes":"Bloodshot","Hat":"Bowler","Trait Count":"6"}},"1328":{"name":"DoodRilla #1328","traits":{"Background":"Army Green","Skin":"Dark Brown","Mouth":"Unshaven Bored","Eyes":"Hypnotized","Hat":"Short Mohawk","Trait Count":"5"}},"1329":{"name":"DoodRilla #1329","traits":{"Background":"Grey","Skin":"Red","Clothing":"Striped T","Mouth":"Unshaven Bored","Earrings":"Silver Hoop","Eyes":"Heart","Hat":"Beanie","Trait Count":"7"}},"1330":{"name":"DoodRilla #1330","traits":{"Background":"Ape Blue","Skin":"Brown","Clothing":"Bone Necklace","Mouth":"Bored","Eyes":"Bored","Hat":"Sea Captain Hat","Trait Count":"6"}},"1331":{"name":"DoodRilla #1331","traits":{"Background":"Aquamarine","Skin":"Golden Brown","Clothing":"Rainbow Suspenders","Mouth":"Jovial","Earrings":"Silver Hoop","Eyes":"Bored","Hat":"Kings Crown","Trait Count":"7"}},"1332":{"name":"DoodRilla #1332","traits":{"Background":"Ape Blue","Skin":"Tan","Clothing":"Caveman Pelt","Mouth":"Spliff","Eyes":"Crazy","Hat":"Cowboy Hat","Trait Count":"6"}},"1333":{"name":"DoodRilla #1333","traits":{"Background":"Purple","Skin":"Dark Brown","Clothing":"Bone Necklace","Mouth":"Spliff","Eyes":"Sad","Trait Count":"5"}},"1334":{"name":"DoodRilla #1334","traits":{"Background":"Yellow","Skin":"Red","Clothing":"Nam Jacket","Mouth":"Unshaven Bored","Earrings":"Cross","Eyes":"Bored","Hat":"Flipped Brim","Trait Count":"7"}},"1335":{"name":"DoodRilla #1335","traits":{"Background":"New Punk Blue","Skin":"Tan","Clothing":"Hip Hop","Mouth":"Phoneme 000","Eyes":"Coins","Hat":"Service","Trait Count":"6"}},"1336":{"name":"DoodRilla #1336","traits":{"Background":"Army Green","Skin":"Black","Clothing":"Blue Dress","Mouth":"Bored","Eyes":"3D","Trait Count":"5"}},"1337":{"name":"DoodRilla #1337","traits":{"Background":"Orange","Skin":"Golden Brown","Clothing":"Hawaiian","Mouth":"Unshaven Bored","Eyes":"Bored","Hat":"Safari","Trait Count":"6"}},"1338":{"name":"DoodRilla #1338","traits":{"Skin":"Cream","Clothing":"Lab Coat","Mouth":"Unshaven Bored","Earrings":"Silver Hoop","Eyes":"Bored","Hat":"Trippy Captains Hat","Trait Count":"6"}},"1339":{"name":"DoodRilla #1339","traits":{"Background":"Orange","Skin":"Trippy","Clothing":"Black T","Mouth":"Bubblegum","Eyes":"Heart","Trait Count":"5"}},"1340":{"name":"DoodRilla #1340","traits":{"Background":"Purple","Skin":"Brown","Mouth":"Phoneme L","Eyes":"Bloodshot","Hat":"Horns","Trait Count":"5"}},"1341":{"name":"DoodRilla #1341","traits":{"Background":"Army Green","Skin":"Zombie","Clothing":"Bone Necklace","Mouth":"Unshaven Bored","Earrings":"Gold Hoop","Eyes":"Bored","Hat":"Cowboy Hat","Trait Count":"7"}},"1342":{"name":"DoodRilla #1342","traits":{"Background":"Army Green","Skin":"Blue","Clothing":"Guaya","Mouth":"Unshaven Bored","Eyes":"Zombie","Hat":"Safari","Trait Count":"6"}},"1343":{"name":"DoodRilla #1343","traits":{"Background":"Aquamarine","Skin":"Brown","Clothing":"Navy Striped","Mouth":"Unshaven Bored","Eyes":"Bloodshot","Hat":"Beanie","Trait Count":"6"}},"1344":{"name":"DoodRilla #1344","traits":{"Background":"Army Green","Skin":"Tan","Clothing":"Striped T","Mouth":"Unshaven Bored","Eyes":"Bored","Hat":"Horns","Trait Count":"6"}},"1345":{"name":"DoodRilla #1345","traits":{"Background":"Ape Blue","Skin":"Cream","Clothing":"Black Holes T","Mouth":"Discomfort","Eyes":"Closed","Hat":"Bunny Ears","Trait Count":"6"}},"1346":{"name":"DoodRilla #1346","traits":{"Background":"Purple","Skin":"Grey","Clothing":"Rainbow Suspenders","Mouth":"Phoneme Vuh","Eyes":"Wide Eyed","Hat":"Beanie","Trait Count":"6"}},"1347":{"name":"DoodRilla #1347","traits":{"Background":"Army Green","Skin":"Brown","Clothing":"Bandolier","Mouth":"Unshaven Bored","Eyes":"Sleepy","Trait Count":"5"}},"1348":{"name":"DoodRilla #1348","traits":{"Background":"Grey","Skin":"Cheetah","Clothing":"Service","Mouth":"Unshaven Bored","Earrings":"Gold Stud","Eyes":"Bored","Hat":"Bunny Ears","Overlay":"Service","Trait Count":"8"}},"1349":{"name":"DoodRilla #1349","traits":{"Background":"Ape Blue","Skin":"Robot","Clothing":"Black T","Mouth":"Bored","Earrings":"Silver Hoop","Eyes":"3D","Hat":"Safari","Trait Count":"7"}},"1350":{"name":"DoodRilla #1350","traits":{"Background":"Army Green","Skin":"Cream","Clothing":"Tuxedo T","Mouth":"Spliff","Earrings":"Gold Hoop","Eyes":"Zombie","Hat":"Baby Bonnet","Trait Count":"7"}},"1351":{"name":"DoodRilla #1351","traits":{"Background":"Army Green","Skin":"Red","Clothing":"Hawaiian","Mouth":"Tongue","Earrings":"Silver Stud","Eyes":"Dead","Hat":"Seaman Hat","Trait Count":"7"}},"1352":{"name":"DoodRilla #1352","traits":{"Background":"Aquamarine","Skin":"Zombie","Clothing":"Punk Jacket","Mouth":"Unshaven Kazoo","Eyes":"Bored","Hat":"Halo","Trait Count":"6"}},"1353":{"name":"DoodRilla #1353","traits":{"Background":"Orange","Skin":"Black","Mouth":"Phoneme Wah","Earrings":"Silver Hoop","Eyes":"Cyborg","Hat":"Sushi Chef","Trait Count":"6"}},"1354":{"name":"DoodRilla #1354","traits":{"Background":"Purple","Skin":"Cheetah","Clothing":"Hawaiian","Mouth":"Rage","Earrings":"Silver Hoop","Eyes":"Bloodshot","Trait Count":"6"}},"1355":{"name":"DoodRilla #1355","traits":{"Background":"Army Green","Skin":"Death Bot","Clothing":"Black T","Mouth":"Bored","Eyes":"Crazy","Hat":"Black Hat","Overlay":"Crazy","Trait Count":"7"}},"1356":{"name":"DoodRilla #1356","traits":{"Background":"Orange","Skin":"Dark Brown","Clothing":"Sleeveless","Mouth":"Phoneme Wah","Eyes":"Bored","Hat":"Laurel Wreath","Trait Count":"6"}},"1357":{"name":"DoodRilla #1357","traits":{"Background":"Aquamarine","Skin":"Brown","Clothing":"Striped T","Mouth":"Bored","Eyes":"Closed","Trait Count":"5"}},"1358":{"name":"DoodRilla #1358","traits":{"Skin":"Cream","Clothing":"Biker","Mouth":"Phoneme 000","Eyes":"3D","Hat":"Fisherman Hat","Trait Count":"5"}},"1359":{"name":"DoodRilla #1359","traits":{"Background":"New Punk Blue","Skin":"Tan","Mouth":"Bored","Earrings":"Silver Hoop","Eyes":"Crazy","Hat":"Bandana Blue","Trait Count":"6"}},"1360":{"name":"DoodRilla #1360","traits":{"Background":"Purple","Skin":"Cheetah","Mouth":"Bored","Eyes":"Dead","Hat":"Faux Hawk","Trait Count":"5"}},"1361":{"name":"DoodRilla #1361","traits":{"Background":"Army Green","Skin":"Cheetah","Clothing":"Bone Necklace","Mouth":"Rainbow Grill","Earrings":"Silver Hoop","Eyes":"Bloodshot","Hat":"Irish Boho","Trait Count":"7"}},"1362":{"name":"DoodRilla #1362","traits":{"Background":"Aquamarine","Skin":"Golden Brown","Clothing":"Admirals Coat","Mouth":"Unshaven Bored","Eyes":"Bored","Trait Count":"5"}},"1363":{"name":"DoodRilla #1363","traits":{"Background":"Aquamarine","Skin":"Dark Brown","Clothing":"Work Vest","Mouth":"Dumbfounded","Earrings":"Silver Stud","Eyes":"Patch","Hat":"Police Motorcycle Helmet","Trait Count":"7"}},"1364":{"name":"DoodRilla #1364","traits":{"Background":"Orange","Skin":"Grey","Clothing":"Bone Necklace","Mouth":"Diamond Grill","Earrings":"Cross","Eyes":"Bloodshot","Hat":"Spinner Hat","Trait Count":"7"}},"1365":{"name":"DoodRilla #1365","traits":{"Background":"Aquamarine","Skin":"Noise","Clothing":"Nam Jacket","Mouth":"Dumbfounded","Earrings":"Silver Stud","Eyes":"Sleepy","Hat":"Flipped Brim","Trait Count":"7"}},"1366":{"name":"DoodRilla #1366","traits":{"Background":"Purple","Skin":"Tan","Clothing":"Navy Striped","Mouth":"Unshaven Spliff","Eyes":"Zombie","Hat":"Prussian Helmet","Trait Count":"6"}},"1367":{"name":"DoodRilla #1367","traits":{"Background":"Orange","Skin":"Dark Brown","Clothing":"Rainbow Suspenders","Mouth":"Spliff","Eyes":"Sleepy","Hat":"Beanie","Trait Count":"6"}},"1368":{"name":"DoodRilla #1368","traits":{"Background":"Blue","Skin":"Noise","Clothing":"Sleeveless","Mouth":"Small Grin","Eyes":"Bored","Hat":"Police Motorcycle Helmet","Trait Count":"6"}},"1369":{"name":"DoodRilla #1369","traits":{"Background":"Orange","Skin":"Zombie","Clothing":"Ape T Red","Mouth":"Diamond Grill","Eyes":"Wide Eyed","Hat":"Seaman Hat","Trait Count":"6"}},"1370":{"name":"DoodRilla #1370","traits":{"Background":"Grey","Skin":"Death Bot","Clothing":"Turtle Neck","Mouth":"Unshaven Spliff","Eyes":"Sad","Hat":"Fez","Trait Count":"6"}},"1371":{"name":"DoodRilla #1371","traits":{"Background":"Grey","Skin":"Cream","Clothing":"Board and Hungry","Mouth":"Unshaven Spliff","Eyes":"Patch","Hat":"Bored And Hungry","Trait Count":"6"}},"1372":{"name":"DoodRilla #1372","traits":{"Background":"Army Green","Skin":"Red","Clothing":"Nam Jacket","Mouth":"Unshaven Bored","Eyes":"3D","Hat":"Sushi Chef","Trait Count":"6"}},"1373":{"name":"DoodRilla #1373","traits":{"Background":"New Punk Blue","Skin":"Brown","Mouth":"Phoneme Wah","Eyes":"Crazy","Hat":"Seaman Hat","Trait Count":"5"}},"1374":{"name":"DoodRilla #1374","traits":{"Background":"Aquamarine","Skin":"Robot","Mouth":"Bubblegum","Eyes":"Sleepy","Hat":"Black Hat","Trait Count":"5"}},"1375":{"name":"DoodRilla #1375","traits":{"Background":"Yellow","Skin":"Cream","Clothing":"Work Vest","Mouth":"Unshaven Pipe","Earrings":"Gold Hoop","Eyes":"Angry","Hat":"Stuntman","Trait Count":"7"}},"1376":{"name":"DoodRilla #1376","traits":{"Background":"Army Green","Skin":"White","Clothing":"Sailor","Mouth":"Bored","Earrings":"Diamond Stud","Eyes":"Bloodshot","Hat":"WW2 Pilot","Trait Count":"7"}},"1377":{"name":"DoodRilla #1377","traits":{"Background":"Aquamarine","Skin":"Brown","Mouth":"Grin","Eyes":"Sad","Hat":"Baby Bonnet","Trait Count":"5"}},"1378":{"name":"DoodRilla #1378","traits":{"Skin":"White","Clothing":"Cowboy Shirt","Mouth":"Bored","Eyes":"Bored","Hat":"Bandana Blue","Trait Count":"5"}},"1379":{"name":"DoodRilla #1379","traits":{"Background":"Yellow","Skin":"Golden Brown","Clothing":"Hawaiian","Mouth":"Dagger","Eyes":"Closed","Hat":"Laurel Wreath","Trait Count":"6"}},"1380":{"name":"DoodRilla #1380","traits":{"Background":"Yellow","Skin":"Pink","Clothing":"Toga","Mouth":"Unshaven Bored","Eyes":"Wide Eyed","Hat":"Short Mohawk","Trait Count":"6"}},"1381":{"name":"DoodRilla #1381","traits":{"Background":"Yellow","Skin":"DMT","Clothing":"Lumberjack","Mouth":"Bored","Eyes":"Bored","Hat":"Short Mohawk","Trait Count":"6"}},"1382":{"name":"DoodRilla #1382","traits":{"Background":"Grey","Skin":"Blue","Clothing":"Work Vest","Mouth":"Unshaven Spliff","Eyes":"Coins","Trait Count":"5"}},"1383":{"name":"DoodRilla #1383","traits":{"Background":"Aquamarine","Skin":"Dark Brown","Clothing":"Prom Dress","Mouth":"Bored","Eyes":"Hypnotized","Trait Count":"5"}},"1384":{"name":"DoodRilla #1384","traits":{"Background":"Blue","Skin":"Black","Clothing":"Ape T","Mouth":"Phoneme Wah","Eyes":"Sad","Hat":"Faux Hawk","Trait Count":"6"}},"1385":{"name":"DoodRilla #1385","traits":{"Background":"Aquamarine","Skin":"Blue","Clothing":"Lab Coat","Mouth":"Unshaven Spliff","Eyes":"Closed","Hat":"BAYC Blue","Trait Count":"6"}},"1386":{"name":"DoodRilla #1386","traits":{"Background":"Ape Blue","Skin":"Dark Brown","Clothing":"Lab Coat","Mouth":"Unshaven Spliff","Eyes":"Shades","Hat":"Seaman Hat","Trait Count":"6"}},"1387":{"name":"DoodRilla #1387","traits":{"Background":"Purple","Skin":"Black","Clothing":"Ape T Red","Mouth":"Bored","Eyes":"Patch","Hat":"Sushi Chef","Trait Count":"6"}},"1388":{"name":"DoodRilla #1388","traits":{"Background":"Yellow","Skin":"Cheetah","Clothing":"Hip Hop","Mouth":"Bored","Eyes":"Bloodshot","Hat":"Faux Hawk","Trait Count":"6"}},"1389":{"name":"DoodRilla #1389","traits":{"Background":"Aquamarine","Skin":"Dark Brown","Clothing":"Navy Striped","Mouth":"Jovial","Earrings":"Silver Hoop","Eyes":"Closed","Hat":"Commie","Trait Count":"7"}},"1390":{"name":"DoodRilla #1390","traits":{"Background":"Aquamarine","Skin":"Brown","Clothing":"Lumberjack","Mouth":"Spliff","Eyes":"Sad","Hat":"Fez","Trait Count":"6"}},"1391":{"name":"DoodRilla #1391","traits":{"Background":"Ape Blue","Skin":"Black","Clothing":"Black Holes T","Mouth":"Phoneme 000","Earrings":"Silver Stud","Eyes":"Bloodshot","Hat":"Cowboy Hat","Trait Count":"7"}},"1392":{"name":"DoodRilla #1392","traits":{"Background":"New Punk Blue","Skin":"Brown","Clothing":"Striped T","Mouth":"Spliff","Eyes":"Patch","Hat":"Party Hat 1","Trait Count":"6"}},"1393":{"name":"DoodRilla #1393","traits":{"Background":"Ape Blue","Skin":"Noise","Mouth":"Bored","Eyes":"Sleepy","Hat":"Seaman Hat","Trait Count":"5"}},"1394":{"name":"DoodRilla #1394","traits":{"Background":"Blue","Skin":"Black","Clothing":"Hawaiian","Mouth":"Phoneme 000","Eyes":"Shades","Hat":"Irish Boho","Trait Count":"6"}},"1395":{"name":"DoodRilla #1395","traits":{"Background":"Army Green","Skin":"Golden Brown","Clothing":"Hawaiian","Mouth":"Stoge","Eyes":"Sleepy","Hat":"Short Mohawk","Trait Count":"6"}},"1396":{"name":"DoodRilla #1396","traits":{"Background":"Aquamarine","Skin":"Golden Brown","Clothing":"Sleeveless","Mouth":"Bored","Eyes":"Shades","Hat":"APE Blue Hat","Trait Count":"6"}},"1397":{"name":"DoodRilla #1397","traits":{"Background":"Blue","Skin":"Tan","Clothing":"Bandolier","Mouth":"Bubblegum","Earrings":"Gold Hoop","Eyes":"Cyborg","Hat":"Vietnam Era Helmet","Trait Count":"7"}},"1398":{"name":"DoodRilla #1398","traits":{"Background":"Yellow","Skin":"Robot","Clothing":"Black T","Mouth":"Jovial","Eyes":"Robot","Hat":"Horns","Trait Count":"6"}},"1399":{"name":"DoodRilla #1399","traits":{"Background":"Orange","Skin":"Noise","Clothing":"Hawaiian","Mouth":"Bored","Eyes":"Bored","Hat":"BAYC Grey","Trait Count":"6"}},"1400":{"name":"DoodRilla #1400","traits":{"Background":"Grey","Skin":"Cheetah","Clothing":"Bone Necklace","Mouth":"Bored","Earrings":"Silver Stud","Eyes":"Dead","Trait Count":"6"}},"1401":{"name":"DoodRilla #1401","traits":{"Background":"New Punk Blue","Skin":"Robot","Clothing":"Bone Necklace","Mouth":"Spliff","Eyes":"Closed","Hat":"Red Hat","Trait Count":"6"}},"1402":{"name":"DoodRilla #1402","traits":{"Background":"Orange","Skin":"Black","Clothing":"Blue Dress","Mouth":"Rainbow Grill","Earrings":"Silver Hoop","Eyes":"Sleepy","Hat":"Army Hat","Trait Count":"7"}},"1403":{"name":"DoodRilla #1403","traits":{"Background":"Purple","Skin":"Tan","Clothing":"Tweed Suit","Mouth":"Unshaven Bored","Earrings":"Silver Stud","Eyes":"Shades","Hat":"Cowboy Hat","Trait Count":"7"}},"1404":{"name":"DoodRilla #1404","traits":{"Background":"New Punk Blue","Skin":"Cream","Clothing":"Biker","Mouth":"Bored","Earrings":"Gold Hoop","Eyes":"Heart","Hat":"Party Hat 1","Trait Count":"7"}},"1405":{"name":"DoodRilla #1405","traits":{"Background":"Grey","Skin":"Robot","Clothing":"Caveman Pelt","Mouth":"Bored","Eyes":"Bloodshot","Hat":"Red Hat","Trait Count":"6"}},"1406":{"name":"DoodRilla #1406","traits":{"Background":"Army Green","Skin":"Pink","Clothing":"Lumberjack","Mouth":"Bored","Eyes":"Zombie","Hat":"Service","Trait Count":"6"}},"1407":{"name":"DoodRilla #1407","traits":{"Background":"Purple","Skin":"Black","Clothing":"Hawaiian","Mouth":"Dumbfounded","Earrings":"Silver Hoop","Eyes":"Angry","Trait Count":"6"}},"1408":{"name":"DoodRilla #1408","traits":{"Background":"Blue","Skin":"Death Bot","Clothing":"Space Suit","Mouth":"Small Grin","Earrings":"Silver Hoop","Eyes":"Closed","Hat":"APE Blue Band Bowler","Trait Count":"7"}},"1409":{"name":"DoodRilla #1409","traits":{"Background":"Army Green","Skin":"Zombie","Clothing":"Navy Striped","Mouth":"Unshaven Bored","Eyes":"Bloodshot","Hat":"Horns","Trait Count":"6"}},"1410":{"name":"DoodRilla #1410","traits":{"Background":"Army Green","Skin":"Black","Clothing":"Work Vest","Mouth":"Unshaven Bored","Earrings":"Gold Hoop","Eyes":"Wide Eyed","Hat":"Service","Trait Count":"7"}},"1411":{"name":"DoodRilla #1411","traits":{"Background":"Yellow","Skin":"Grey","Clothing":"Navy Striped","Mouth":"Unshaven Spliff","Eyes":"Wide Eyed","Hat":"Beanie","Trait Count":"6"}},"1412":{"name":"DoodRilla #1412","traits":{"Background":"Aquamarine","Skin":"Tan","Clothing":"Bandolier","Mouth":"Spliff","Eyes":"Sleepy","Hat":"Vietnam Era Helmet","Trait Count":"6"}},"1413":{"name":"DoodRilla #1413","traits":{"Background":"Ape Blue","Skin":"Black","Clothing":"Board and Hungry","Mouth":"Unshaven Bored","Eyes":"Zombie","Hat":"Bored And Hungry","Trait Count":"6"}},"1414":{"name":"DoodRilla #1414","traits":{"Skin":"Dark Brown","Clothing":"Ape T","Mouth":"Phoneme 000","Eyes":"Shades","Hat":"Girl Hair Short","Trait Count":"5"}},"1415":{"name":"DoodRilla #1415","traits":{"Background":"Aquamarine","Skin":"Black","Clothing":"Bone T","Mouth":"Unshaven Bored","Eyes":"Bored","Hat":"Irish Boho","Trait Count":"6"}},"1416":{"name":"DoodRilla #1416","traits":{"Background":"Purple","Skin":"Black","Mouth":"Unshaven Bored","Earrings":"Gold Stud","Eyes":"Crazy","Hat":"Seaman Hat","Trait Count":"6"}},"1417":{"name":"DoodRilla #1417","traits":{"Background":"Purple","Skin":"White","Clothing":"Nam Jacket","Mouth":"Bored","Eyes":"Bored","Hat":"Black Hat","Trait Count":"6"}},"1418":{"name":"DoodRilla #1418","traits":{"Background":"Ape Blue","Skin":"Brown","Clothing":"Hawaiian","Mouth":"Unshaven Bored","Eyes":"Crazy","Trait Count":"5"}},"1419":{"name":"DoodRilla #1419","traits":{"Background":"Army Green","Skin":"DMT","Clothing":"Work Vest","Mouth":"Bored","Eyes":"Dead","Trait Count":"5"}},"1420":{"name":"DoodRilla #1420","traits":{"Background":"Orange","Skin":"Dark Brown","Mouth":"Tongue","Earrings":"Silver Hoop","Eyes":"Angry","Hat":"Vietnam Era Helmet","Trait Count":"6"}},"1421":{"name":"DoodRilla #1421","traits":{"Background":"Purple","Skin":"Brown","Clothing":"Turtle Neck","Mouth":"Phoneme L","Earrings":"Silver Stud","Eyes":"Blindfold","Hat":"Horns","Trait Count":"7"}},"1422":{"name":"DoodRilla #1422","traits":{"Background":"Aquamarine","Skin":"Blue","Clothing":"Bone Necklace","Mouth":"Bored","Eyes":"Shades","Hat":"Spinner Hat","Trait Count":"6"}},"1423":{"name":"DoodRilla #1423","traits":{"Background":"New Punk Blue","Skin":"Tan","Clothing":"Service","Mouth":"Unshaven Bored","Eyes":"Bloodshot","Hat":"Black Hat","Trait Count":"6"}},"1424":{"name":"DoodRilla #1424","traits":{"Background":"Purple","Skin":"Brown","Clothing":"Hawaiian","Mouth":"Dumbfounded","Eyes":"Scumbag","Hat":"Sushi Chef","Trait Count":"6"}},"1425":{"name":"DoodRilla #1425","traits":{"Background":"Yellow","Skin":"Dark Brown","Clothing":"DoodRilla T","Mouth":"Unshaven Dagger","Eyes":"Heart","Trait Count":"5"}},"1426":{"name":"DoodRilla #1426","traits":{"Background":"Orange","Skin":"Pink","Clothing":"Lab Coat","Mouth":"Grin","Eyes":"Zombie","Hat":"Beanie","Trait Count":"6"}},"1427":{"name":"DoodRilla #1427","traits":{"Background":"Blue","Skin":"Golden Brown","Clothing":"Black T","Mouth":"Unshaven Spliff","Eyes":"Sad","Hat":"Party Hat 2","Trait Count":"6"}},"1428":{"name":"DoodRilla #1428","traits":{"Background":"Army Green","Skin":"Golden Brown","Clothing":"Hip Hop","Mouth":"Unshaven Bubblegum","Eyes":"Wide Eyed","Hat":"Seaman Hat","Trait Count":"6"}},"1429":{"name":"DoodRilla #1429","traits":{"Background":"Yellow","Skin":"Tan","Clothing":"Lumberjack","Mouth":"Bored","Eyes":"Closed","Hat":"WW2 Pilot","Trait Count":"6"}},"1430":{"name":"DoodRilla #1430","traits":{"Background":"New Punk Blue","Skin":"Dark Brown","Clothing":"Turtle Neck","Mouth":"Phoneme Oh","Earrings":"Diamond Stud","Eyes":"Bored","Hat":"Safari","Trait Count":"7"}},"1431":{"name":"DoodRilla #1431","traits":{"Background":"Purple","Skin":"Dark Brown","Mouth":"Spliff","Eyes":"Bloodshot","Hat":"Safari","Trait Count":"5"}},"1432":{"name":"DoodRilla #1432","traits":{"Background":"Ape Blue","Skin":"Death Bot","Clothing":"Puffy Vest","Mouth":"Unshaven Bored","Earrings":"Silver Stud","Eyes":"Sleepy","Hat":"Police Motorcycle Helmet","Trait Count":"7"}},"1433":{"name":"DoodRilla #1433","traits":{"Background":"Ape Blue","Skin":"DMT","Clothing":"Navy Striped","Mouth":"Small Grin","Eyes":"Angry","Hat":"Seaman Hat","Trait Count":"6"}},"1434":{"name":"DoodRilla #1434","traits":{"Background":"Purple","Skin":"Golden Brown","Clothing":"Punk Jacket","Mouth":"Jovial","Eyes":"Zombie","Hat":"S&M Hat","Trait Count":"6"}},"1435":{"name":"DoodRilla #1435","traits":{"Background":"Purple","Skin":"Black","Clothing":"Prisoner","Mouth":"Unshaven Bored","Eyes":"3D","Hat":"Sushi Chef","Trait Count":"6"}},"1436":{"name":"DoodRilla #1436","traits":{"Background":"Grey","Skin":"Golden Brown","Clothing":"Sailor","Mouth":"Unshaven Bored","Eyes":"Zombie","Hat":"Red Hat","Trait Count":"6"}},"1437":{"name":"DoodRilla #1437","traits":{"Background":"Yellow","Skin":"Golden Brown","Clothing":"Tie Dye","Mouth":"Spliff","Eyes":"3D","Hat":"Seaman Hat","Trait Count":"6"}},"1438":{"name":"DoodRilla #1438","traits":{"Background":"Yellow","Skin":"Brown","Clothing":"Lab Coat","Mouth":"Unshaven Pipe","Eyes":"Wide Eyed","Hat":"S&M Hat","Trait Count":"6"}},"1439":{"name":"DoodRilla #1439","traits":{"Background":"Grey","Skin":"Blue","Clothing":"Black Holes T","Mouth":"Spliff","Eyes":"Dead","Hat":"Service","Trait Count":"6"}},"1440":{"name":"DoodRilla #1440","traits":{"Background":"Aquamarine","Skin":"Brown","Clothing":"Lab Coat","Mouth":"Unshaven Spliff","Eyes":"Bored","Hat":"Halo","Trait Count":"6"}},"1441":{"name":"DoodRilla #1441","traits":{"Background":"New Punk Blue","Skin":"Cream","Clothing":"Lab Coat","Mouth":"Unshaven Bored","Eyes":"Bloodshot","Hat":"Short Mohawk","Trait Count":"6"}},"1442":{"name":"DoodRilla #1442","traits":{"Background":"Army Green","Skin":"Dark Brown","Clothing":"Toga","Mouth":"Unshaven Bored","Eyes":"Sleepy","Trait Count":"5"}},"1443":{"name":"DoodRilla #1443","traits":{"Background":"Purple","Skin":"Dark Brown","Mouth":"Grin","Eyes":"Shades","Hat":"Army Hat","Trait Count":"5"}},"1444":{"name":"DoodRilla #1444","traits":{"Background":"Army Green","Skin":"Grey","Clothing":"Tanktop","Mouth":"Phoneme Oh","Earrings":"Silver Hoop","Eyes":"Bored","Hat":"Short Mohawk","Trait Count":"7"}},"1445":{"name":"DoodRilla #1445","traits":{"Background":"Orange","Skin":"Zombie","Clothing":"Biker","Mouth":"Bored","Eyes":"Robot","Hat":"Kings Crown","Trait Count":"6"}},"1446":{"name":"DoodRilla #1446","traits":{"Background":"New Punk Blue","Skin":"Red","Clothing":"Black T","Mouth":"Unshaven Bored","Eyes":"Wide Eyed","Hat":"Bowler","Trait Count":"6"}},"1447":{"name":"DoodRilla #1447","traits":{"Background":"Purple","Skin":"Golden Brown","Clothing":"Lab Coat","Mouth":"Unshaven Spliff","Eyes":"Sad","Hat":"Flipped Brim","Trait Count":"6"}},"1448":{"name":"DoodRilla #1448","traits":{"Background":"Army Green","Skin":"Dark Brown","Clothing":"Bone T","Mouth":"Diamond Grill","Earrings":"Silver Hoop","Eyes":"Bored","Hat":"Safari","Trait Count":"7"}},"1449":{"name":"DoodRilla #1449","traits":{"Background":"Army Green","Skin":"Brown","Clothing":"Turtle Neck","Mouth":"Bored","Earrings":"Gold Hoop","Eyes":"Heart","Hat":"Party Hat 1","Trait Count":"7"}},"1450":{"name":"DoodRilla #1450","traits":{"Background":"Yellow","Skin":"Cheetah","Clothing":"Sleeveless","Mouth":"Tongue","Eyes":"Sleepy","Hat":"Seaman Hat","Trait Count":"6"}},"1451":{"name":"DoodRilla #1451","traits":{"Background":"Yellow","Skin":"Dark Brown","Clothing":"Biker","Mouth":"Grin","Earrings":"Silver Hoop","Eyes":"Blindfold","Hat":"Party Hat 1","Trait Count":"7"}},"1452":{"name":"DoodRilla #1452","traits":{"Background":"Grey","Skin":"Robot","Clothing":"Tuxedo T","Mouth":"Spliff","Eyes":"Sad","Hat":"Sushi Chef","Trait Count":"6"}},"1453":{"name":"DoodRilla #1453","traits":{"Background":"Yellow","Skin":"Blue","Clothing":"Leather Jacket","Mouth":"Bored","Earrings":"Silver Stud","Eyes":"Patch","Hat":"WW2 Pilot","Trait Count":"7"}},"1454":{"name":"DoodRilla #1454","traits":{"Background":"Aquamarine","Skin":"Dark Brown","Mouth":"Unshaven Bored","Eyes":"Holographic","Hat":"BAYC Trippy","Trait Count":"5"}},"1455":{"name":"DoodRilla #1455","traits":{"Background":"Orange","Skin":"Brown","Clothing":"Lumberjack","Mouth":"Unshaven Bored","Eyes":"Bored","Hat":"Army Hat","Trait Count":"6"}},"1456":{"name":"DoodRilla #1456","traits":{"Background":"Orange","Skin":"Zombie","Clothing":"Tanktop","Mouth":"Bored","Eyes":"Robot","Hat":"Fez","Trait Count":"6"}},"1457":{"name":"DoodRilla #1457","traits":{"Skin":"Cream","Clothing":"Cowboy Shirt","Mouth":"Bored","Eyes":"Dead","Hat":"Fisherman Hat","Trait Count":"5"}},"1458":{"name":"DoodRilla #1458","traits":{"Background":"Yellow","Skin":"Black","Clothing":"Sleeveless","Mouth":"Spliff","Eyes":"Laser","Hat":"Flipped Brim","Overlay":"Laser","Trait Count":"7"}},"1459":{"name":"DoodRilla #1459","traits":{"Background":"Ape Blue","Skin":"Noise","Clothing":"Sailor","Mouth":"Unshaven Bored","Eyes":"Blindfold","Hat":"Sushi Chef","Trait Count":"6"}},"1460":{"name":"DoodRilla #1460","traits":{"Skin":"Death Bot","Clothing":"Turtle Neck","Mouth":"Unshaven Bored","Earrings":"Silver Stud","Eyes":"Shades","Hat":"Red Hat","Trait Count":"6"}},"1461":{"name":"DoodRilla #1461","traits":{"Background":"Purple","Skin":"Tan","Clothing":"Tie Dye","Mouth":"Jovial","Earrings":"Diamond Stud","Eyes":"Wide Eyed","Hat":"Fez","Trait Count":"7"}},"1462":{"name":"DoodRilla #1462","traits":{"Background":"Army Green","Skin":"Death Bot","Clothing":"Lumberjack","Mouth":"Bored","Eyes":"Crazy","Hat":"Bunny Ears","Trait Count":"6"}},"1463":{"name":"DoodRilla #1463","traits":{"Background":"Army Green","Skin":"White","Clothing":"Cowboy Shirt","Mouth":"Bored","Eyes":"Bloodshot","Hat":"Fez","Trait Count":"6"}},"1464":{"name":"DoodRilla #1464","traits":{"Background":"Yellow","Skin":"Red","Clothing":"Prom Dress","Mouth":"Unshaven Spliff","Earrings":"Silver Hoop","Eyes":"Robot","Hat":"Sushi Chef","Trait Count":"7"}},"1465":{"name":"DoodRilla #1465","traits":{"Background":"New Punk Blue","Skin":"Grey","Clothing":"Nam Jacket","Mouth":"Bored","Earrings":"Silver Stud","Eyes":"Bored","Hat":"Vietnam Era Helmet","Trait Count":"7"}},"1466":{"name":"DoodRilla #1466","traits":{"Background":"Purple","Skin":"Black","Clothing":"Toga","Mouth":"Discomfort","Eyes":"Sleepy","Hat":"Spinner Hat","Trait Count":"6"}},"1467":{"name":"DoodRilla #1467","traits":{"Background":"Aquamarine","Skin":"Blue","Clothing":"Lumberjack","Mouth":"Unshaven Bored","Eyes":"Shades","Hat":"Faux Hawk","Trait Count":"6"}},"1468":{"name":"DoodRilla #1468","traits":{"Background":"Army Green","Skin":"Grey","Clothing":"Leather Jacket","Mouth":"Phoneme 000","Eyes":"Bored","Hat":"Army Hat","Trait Count":"6"}},"1469":{"name":"DoodRilla #1469","traits":{"Background":"Orange","Skin":"Black","Clothing":"Sleeveless Logo","Mouth":"Unshaven Spliff","Earrings":"Silver Stud","Eyes":"Bored","Hat":"Faux Hawk","Trait Count":"7"}},"1470":{"name":"DoodRilla #1470","traits":{"Background":"New Punk Blue","Skin":"Pink","Clothing":"Biker","Mouth":"Phoneme 000","Eyes":"Sleepy","Trait Count":"5"}},"1471":{"name":"DoodRilla #1471","traits":{"Background":"Army Green","Skin":"Red","Clothing":"Ape T Red","Mouth":"Unshaven Bored","Eyes":"Scumbag","Hat":"Short Mohawk","Trait Count":"6"}},"1472":{"name":"DoodRilla #1472","traits":{"Background":"Aquamarine","Skin":"Cream","Clothing":"Hawaiian","Mouth":"Small Grin","Eyes":"Bloodshot","Hat":"Bowler","Trait Count":"6"}},"1473":{"name":"DoodRilla #1473","traits":{"Background":"Purple","Skin":"Tan","Clothing":"Tuxedo T","Mouth":"Unshaven Bored","Eyes":"Bloodshot","Hat":"Flipped Brim","Trait Count":"6"}},"1474":{"name":"DoodRilla #1474","traits":{"Background":"Yellow","Skin":"Brown","Clothing":"Bone T","Mouth":"Spliff","Earrings":"Gold Hoop","Eyes":"Bored","Hat":"Kings Crown","Trait Count":"7"}},"1475":{"name":"DoodRilla #1475","traits":{"Skin":"Golden Brown","Clothing":"Smoking Jacket","Mouth":"Bored","Eyes":"Sleepy","Hat":"Prussian Helmet","Trait Count":"5"}},"1476":{"name":"DoodRilla #1476","traits":{"Background":"Aquamarine","Skin":"Zombie","Clothing":"Tuxedo T","Mouth":"Dumbfounded","Eyes":"Blindfold","Hat":"Short Mohawk","Trait Count":"6"}},"1477":{"name":"DoodRilla #1477","traits":{"Background":"Grey","Skin":"DMT","Clothing":"Stunt Jacket","Mouth":"Small Grin","Eyes":"Crazy","Hat":"Seaman Hat","Trait Count":"6"}},"1478":{"name":"DoodRilla #1478","traits":{"Background":"Orange","Skin":"Black","Clothing":"Bone Necklace","Mouth":"Party Horn","Earrings":"Diamond Stud","Eyes":"Heart","Trait Count":"6"}},"1479":{"name":"DoodRilla #1479","traits":{"Background":"Aquamarine","Skin":"Grey","Clothing":"Sleeveless Logo","Mouth":"Dumbfounded","Earrings":"Diamond Stud","Eyes":"Bored","Hat":"Army Hat","Trait Count":"7"}},"1480":{"name":"DoodRilla #1480","traits":{"Background":"New Punk Blue","Skin":"Red","Clothing":"Sailor","Mouth":"Bored","Earrings":"Silver Hoop","Eyes":"Bored","Hat":"Spinner Hat","Trait Count":"7"}},"1481":{"name":"DoodRilla #1481","traits":{"Background":"New Punk Blue","Skin":"Brown","Clothing":"Work Vest","Mouth":"Discomfort","Earrings":"Silver Stud","Eyes":"Shades","Hat":"Irish Boho","Trait Count":"7"}},"1482":{"name":"DoodRilla #1482","traits":{"Background":"Yellow","Skin":"Brown","Clothing":"Tuxedo","Mouth":"Bored","Eyes":"3D","Hat":"Girl Hair Short","Trait Count":"6"}},"1483":{"name":"DoodRilla #1483","traits":{"Background":"Yellow","Skin":"Dark Brown","Clothing":"Black T","Mouth":"Unshaven Bored","Eyes":"Scumbag","Hat":"Spinner Hat","Trait Count":"6"}},"1484":{"name":"DoodRilla #1484","traits":{"Background":"Grey","Skin":"Robot","Clothing":"Bone Necklace","Mouth":"Phoneme Oh","Eyes":"Zombie","Hat":"Safari","Trait Count":"6"}},"1485":{"name":"DoodRilla #1485","traits":{"Background":"Orange","Skin":"Brown","Clothing":"Tuxedo T","Mouth":"Phoneme 000","Eyes":"Holographic","Hat":"Commie","Trait Count":"6"}},"1486":{"name":"DoodRilla #1486","traits":{"Background":"Orange","Skin":"Golden Brown","Clothing":"Black Holes T","Mouth":"Tongue","Eyes":"Robot","Hat":"Bunny Ears","Trait Count":"6"}},"1487":{"name":"DoodRilla #1487","traits":{"Background":"Aquamarine","Skin":"Pink","Clothing":"Tweed Suit","Mouth":"Grin","Eyes":"Scumbag","Hat":"Bowler","Trait Count":"6"}},"1488":{"name":"DoodRilla #1488","traits":{"Background":"Orange","Skin":"Dark Brown","Clothing":"Navy Striped","Mouth":"Grin","Eyes":"3D","Hat":"Beanie","Trait Count":"6"}},"1489":{"name":"DoodRilla #1489","traits":{"Background":"Yellow","Skin":"Dark Brown","Mouth":"Grin","Eyes":"Holographic","Hat":"Seaman Hat","Trait Count":"5"}},"1490":{"name":"DoodRilla #1490","traits":{"Background":"Yellow","Skin":"Robot","Clothing":"Tuxedo","Mouth":"Grin","Eyes":"Crazy","Hat":"Fez","Trait Count":"6"}},"1491":{"name":"DoodRilla #1491","traits":{"Background":"Yellow","Skin":"Brown","Clothing":"Biker","Mouth":"Stoge","Eyes":"Sleepy","Hat":"Spinner Hat","Trait Count":"6"}},"1492":{"name":"DoodRilla #1492","traits":{"Background":"Purple","Skin":"Black","Clothing":"Tie Dye","Mouth":"Tongue","Earrings":"Gold Hoop","Eyes":"Robot","Hat":"Prussian Helmet","Trait Count":"7"}},"1493":{"name":"DoodRilla #1493","traits":{"Background":"Ape Blue","Skin":"Black","Clothing":"Ape T","Mouth":"Dumbfounded","Earrings":"Silver Stud","Eyes":"Closed","Hat":"Horns","Trait Count":"7"}},"1494":{"name":"DoodRilla #1494","traits":{"Background":"Ape Blue","Skin":"Cream","Clothing":"Leather Jacket","Mouth":"Unshaven Bored","Eyes":"Holographic","Hat":"Irish Boho","Trait Count":"6"}},"1495":{"name":"DoodRilla #1495","traits":{"Background":"Purple","Skin":"Brown","Clothing":"Smoking Jacket","Mouth":"Rage","Eyes":"Angry","Hat":"Red Hat","Trait Count":"6"}},"1496":{"name":"DoodRilla #1496","traits":{"Background":"Army Green","Skin":"Dark Brown","Mouth":"Gold Grill","Eyes":"Bored","Hat":"Irish Boho","Trait Count":"5"}},"1497":{"name":"DoodRilla #1497","traits":{"Background":"Orange","Skin":"Black","Clothing":"Sailor","Mouth":"Bored","Eyes":"Coins","Hat":"Short Mohawk","Trait Count":"6"}},"1498":{"name":"DoodRilla #1498","traits":{"Background":"Orange","Skin":"Dark Brown","Clothing":"Sleeveless","Mouth":"Unshaven Bubblegum","Eyes":"Bloodshot","Hat":"Seaman Hat","Trait Count":"6"}},"1499":{"name":"DoodRilla #1499","traits":{"Background":"Purple","Skin":"Dark Brown","Clothing":"Ape T","Mouth":"Bored","Eyes":"Scumbag","Hat":"Party Hat 1","Trait Count":"6"}},"1500":{"name":"DoodRilla #1500","traits":{"Background":"Army Green","Skin":"Cream","Mouth":"Spliff","Eyes":"Zombie","Trait Count":"4"}}}
